{"type": "Feature", "id": 22141754, "geometry": {"type": "Point", "coordinates": [1.60122, 48.966461]}, "properties": {"woe:id": 22141754, "woe:parent_id": 610944, "woe:name": "SNCF-M\u00e9nerville", "woe:placetype": 20, "woe:placetype_name": "POI", "woe:lang": "FRE", "iso:country": "FR", "meta:provider": ["geoplanet:7.3.1", "geoplanet:7.3.2", "geoplanet:7.4.0", "geoplanet:7.4.1", "geoplanet:7.5.1", "geoplanet:7.5.2", "geoplanet:7.6.0", "geoplanet:7.8.1", "geoplanet:7.9.0", "geoplanet:7.10.0", "geoplanet:8.0.0", "woeplanet:8.0.0"], "meta:indexed": "2020-08-20T20:54:04.931100", "woe:alias_ENG_V": ["Menerville Railway Station"], "woe:alias_ENG_P": ["Menerville Station"], "meta:updated": "2020-10-14T11:52:05.052368", "woe:alias_FRE_S": ["Gare Menerville", "SNCF-Menerville", "Gare du Menerville"], "woe:alias_FRE_V": ["Gare du M\u00e9nerville", "Gare M\u00e9nerville"], "woe:hierarchy": {"continent": 24865675, "country": 23424819, "town": 0, "planet": 1, "county": 12597126, "suburb": 0, "state": 7153319, "region": 0, "localadmin": 12639081}, "woe:timezone_id": 28350911, "woe:hash": "u09ns6jfr1uj", "woe:centroid": [1.60122, 48.966461], "geom:latitude": 48.966461, "geom:longitude": 1.60122, "geom:hash": "u09ns6jfr1uj", "woe:latitude": 48.966461, "geom:centroid": [1.60122, 48.966461], "woe:longitude": 1.60122, "woe:repo": "woeplanet-poi-fr", "geom:area": 0.0, "woe:scale": 19}}