{"type": "Feature", "id": 22870592, "properties": {"woe:id": 22870592, "woe:parent_id": 582987, "woe:name": "Gare de Capdenac", "woe:placetype": 20, "woe:placetype_name": "POI", "woe:lang": "FRE", "iso:country": "FR", "meta:provider": ["geoplanet:7.3.1", "geoplanet:7.3.2", "geoplanet:7.4.0", "geoplanet:7.4.1", "geoplanet:7.5.1", "geoplanet:7.5.2", "geoplanet:7.6.0", "geoplanet:7.8.1", "geoplanet:7.9.0", "geoplanet:7.10.0", "geoplanet:8.0.0", "woeplanet:8.0.0"], "meta:indexed": "2020-08-20T20:54:05.457337", "woe:alias_ENG_V": ["Capdenac Railway Station"], "meta:updated": "2020-08-22T01:53:29.296300", "woe:alias_ENG_P": ["Capdenac Station"], "woe:alias_FRE_V": ["Gare Capdenac"], "woe:hierarchy": {"continent": 24865675, "country": 23424819, "town": 0, "planet": 1, "county": 12597173, "suburb": 0, "state": 7153323, "region": 0, "localadmin": 20074944}, "woe:timezone_id": 28350911, "woe:hash": "spcmx71tj8tg", "woe:centroid": [2.07872, 44.577888], "geom:latitude": 44.577888, "geom:longitude": 2.07872, "geom:hash": "spcmx71tj8tg", "woe:latitude": 44.577888, "geom:centroid": [2.07872, 44.577888], "woe:longitude": 2.07872, "woe:repo": "woeplanet-poi-fr"}, "geometry": {"coordinates": [2.07872, 44.577888], "type": "Point"}}