{"type": "Feature", "id": 29333666, "geometry": {"type": "Point", "coordinates": [2.27759, 48.874538]}, "properties": {"woe:id": 29333666, "woe:parent_id": 12651009, "woe:name": "Porte de Neuilly", "woe:placetype": 20, "woe:placetype_name": "POI", "woe:lang": "FRE", "iso:country": "FR", "meta:provider": ["geoplanet:7.3.1", "geoplanet:7.3.2", "geoplanet:7.4.0", "geoplanet:7.4.1", "geoplanet:7.5.1", "geoplanet:7.5.2", "geoplanet:7.6.0", "geoplanet:7.8.1", "geoplanet:7.9.0", "geoplanet:7.10.0", "geoplanet:8.0.0", "woeplanet:8.0.0"], "meta:indexed": "2020-08-20T20:54:07.158999", "meta:updated": "2020-10-14T11:52:04.956271", "woe:hierarchy": {"continent": 24865675, "country": 23424819, "town": 0, "planet": 1, "county": 12597155, "suburb": 0, "state": 7153319, "region": 0, "localadmin": 12651009}, "woe:timezone_id": 28350911, "woe:hash": "u09w5c66zdnp", "woe:centroid": [2.27759, 48.874538], "geom:latitude": 48.874538, "geom:longitude": 2.27759, "geom:hash": "u09w5c66zdnp", "woe:latitude": 48.874538, "geom:centroid": [2.27759, 48.874538], "woe:longitude": 2.27759, "woe:repo": "woeplanet-poi-fr", "geom:area": 0.0, "woe:scale": 19}}