{"type": "Feature", "id": 22871367, "properties": {"woe:id": 22871367, "woe:parent_id": 599775, "woe:name": "Musee du Flacon A Parfum", "woe:placetype": 20, "woe:placetype_name": "POI", "woe:lang": "FRE", "iso:country": "FR", "meta:provider": ["geoplanet:7.3.1", "geoplanet:7.3.2", "geoplanet:7.4.0", "geoplanet:7.4.1", "geoplanet:7.5.1", "geoplanet:7.5.2", "geoplanet:7.6.0", "geoplanet:7.8.1", "geoplanet:7.9.0", "geoplanet:7.10.0", "geoplanet:8.0.0", "woeplanet:8.0.0"], "meta:indexed": "2020-08-20T20:54:05.478140", "meta:updated": "2020-08-22T01:53:29.305250", "woe:hierarchy": {"continent": 24865675, "country": 23424819, "town": 0, "planet": 1, "county": 12597189, "suburb": 0, "state": 7153327, "region": 0, "localadmin": 12663863}, "woe:timezone_id": 28350911, "woe:hash": "gbpntfbjsbrc", "woe:centroid": [-1.15335, 46.15863], "geom:latitude": 46.15863, "geom:longitude": -1.15335, "geom:hash": "gbpntfbjsbrc", "woe:latitude": 46.15863, "geom:centroid": [-1.15335, 46.15863], "woe:longitude": -1.15335, "woe:repo": "woeplanet-poi-fr"}, "geometry": {"coordinates": [-1.15335, 46.15863], "type": "Point"}}