{"type": "Feature", "id": 22898931, "properties": {"woe:id": 22898931, "woe:parent_id": 585183, "woe:name": "Gare de Chauffailles", "woe:placetype": 20, "woe:placetype_name": "POI", "woe:lang": "FRE", "iso:country": "FR", "meta:provider": ["geoplanet:7.3.1", "geoplanet:7.3.2", "geoplanet:7.4.0", "geoplanet:7.4.1", "geoplanet:7.5.1", "geoplanet:7.5.2", "geoplanet:7.6.0", "geoplanet:7.8.1", "geoplanet:7.9.0", "geoplanet:7.10.0", "geoplanet:8.0.0", "woeplanet:8.0.0"], "meta:indexed": "2020-08-20T20:54:06.212928", "woe:alias_ENG_V": ["Chauffailles Railway Station"], "meta:updated": "2020-08-22T01:53:29.593405", "woe:alias_ENG_P": ["Chauffailles Station"], "woe:alias_FRE_V": ["Gare Chauffailles"], "woe:hierarchy": {"continent": 24865675, "country": 23424819, "town": 0, "planet": 1, "county": 12597153, "suburb": 0, "state": 7153312, "region": 0, "localadmin": 12641371}, "woe:timezone_id": 28350911, "woe:hash": "u05nfgu1k87p", "woe:centroid": [4.34529, 46.20734], "geom:latitude": 46.20734, "geom:longitude": 4.34529, "geom:hash": "u05nfgu1k87p", "woe:latitude": 46.20734, "geom:centroid": [4.34529, 46.20734], "woe:longitude": 4.34529, "woe:repo": "woeplanet-poi-fr"}, "geometry": {"coordinates": [4.34529, 46.20734], "type": "Point"}}