{"type": "Feature", "id": 22904953, "properties": {"woe:id": 22904953, "woe:parent_id": 590249, "woe:name": "Mus\u00e9e de la Marine", "woe:placetype": 20, "woe:placetype_name": "POI", "woe:lang": "FRE", "iso:country": "FR", "meta:provider": ["geoplanet:7.3.1", "geoplanet:7.3.2", "geoplanet:7.4.0", "geoplanet:7.4.1", "geoplanet:7.5.1", "geoplanet:7.5.2", "geoplanet:7.6.0", "geoplanet:7.8.1", "geoplanet:7.9.0", "geoplanet:7.10.0", "geoplanet:8.0.0", "woeplanet:8.0.0"], "meta:indexed": "2020-08-20T20:54:06.415698", "meta:updated": "2020-08-22T01:53:29.669254", "woe:alias_FRE_S": ["Musee de la Marine"], "woe:hierarchy": {"continent": 24865675, "country": 23424819, "town": 0, "planet": 1, "county": 12597181, "suburb": 0, "state": 7153324, "region": 0, "localadmin": 12661105}, "woe:timezone_id": 28350911, "woe:hash": "u0cpmhjfsvfr", "woe:centroid": [1.63408, 50.515598], "geom:latitude": 50.515598, "geom:longitude": 1.63408, "geom:hash": "u0cpmhjfsvfr", "woe:latitude": 50.515598, "geom:centroid": [1.63408, 50.515598], "woe:longitude": 1.63408, "woe:repo": "woeplanet-poi-fr"}, "geometry": {"coordinates": [1.63408, 50.515598], "type": "Point"}}