{"type": "Feature", "id": 22916085, "geometry": {"type": "Point", "coordinates": [2.42492, 48.93219]}, "properties": {"woe:id": 22916085, "woe:parent_id": 55863501, "woe:name": "Centre Culturel Andr\u00e9 Malraux", "woe:placetype": 20, "woe:placetype_name": "POI", "woe:lang": "FRE", "iso:country": "FR", "meta:provider": ["geoplanet:7.3.1", "geoplanet:7.3.2", "geoplanet:7.4.0", "geoplanet:7.4.1", "geoplanet:7.5.1", "geoplanet:7.5.2", "geoplanet:7.6.0", "geoplanet:7.8.1", "geoplanet:7.9.0", "geoplanet:7.10.0", "geoplanet:8.0.0", "woeplanet:8.0.0"], "meta:indexed": "2020-08-20T20:54:06.939708", "meta:updated": "2020-10-14T11:52:05.764117", "woe:alias_FRE_S": ["Centre Culturel Andre Malraux"], "woe:hierarchy": {"continent": 24865675, "country": 23424819, "town": 0, "planet": 1, "county": 12597156, "suburb": 0, "state": 7153319, "region": 0, "localadmin": 12647212}, "woe:timezone_id": 28350911, "woe:hash": "u09wr5vf8tr7", "woe:centroid": [2.42492, 48.93219], "geom:latitude": 48.93219, "geom:longitude": 2.42492, "geom:hash": "u09wr5vf8tr7", "woe:latitude": 48.93219, "geom:centroid": [2.42492, 48.93219], "woe:longitude": 2.42492, "woe:repo": "woeplanet-poi-fr", "geom:area": 0.0, "woe:scale": 19}}