{"type": "Feature", "id": 56060304, "geometry": {"type": "Point", "coordinates": [-3.3593, 47.750561]}, "properties": {"woe:id": 56060304, "woe:parent_id": 608644, "woe:name": "\u00c9cole des Beaux-Arts", "woe:placetype": 20, "woe:placetype_name": "POI", "woe:lang": "FRE", "iso:country": "FR", "meta:provider": ["geoplanet:7.3.1", "geoplanet:7.3.2", "geoplanet:7.4.0", "geoplanet:7.4.1", "geoplanet:7.5.1", "geoplanet:7.5.2", "geoplanet:7.6.0", "geoplanet:7.8.1", "geoplanet:7.9.0", "geoplanet:7.10.0", "geoplanet:8.0.0", "woeplanet:8.0.0"], "meta:indexed": "2020-08-20T20:54:07.896484", "meta:updated": "2020-10-14T11:52:11.282457", "woe:alias_FRE_V": ["Ecole des Beaux-Arts"], "woe:hierarchy": {"continent": 24865675, "country": 23424819, "town": 0, "planet": 1, "county": 12591798, "suburb": 0, "state": 7153313, "region": 0, "localadmin": 12645633}, "woe:timezone_id": 28350911, "woe:hash": "gbmxes9z4tsr", "woe:centroid": [-3.3593, 47.750561], "geom:latitude": 47.750561, "geom:longitude": -3.3593, "geom:hash": "gbmxes9z4tsr", "woe:latitude": 47.750561, "geom:centroid": [-3.3593, 47.750561], "woe:longitude": -3.3593, "woe:repo": "woeplanet-poi-fr", "geom:area": 0.0, "woe:scale": 19}}