{"type": "Feature", "id": 22900560, "properties": {"woe:id": 22900560, "woe:parent_id": 598160, "woe:name": "Gare de la Fert\u00e9-Milon", "woe:placetype": 20, "woe:placetype_name": "POI", "woe:lang": "FRE", "iso:country": "FR", "meta:provider": ["geoplanet:7.3.1", "geoplanet:7.3.2", "geoplanet:7.4.0", "geoplanet:7.4.1", "geoplanet:7.5.1", "geoplanet:7.5.2", "geoplanet:7.6.0", "geoplanet:7.8.1", "geoplanet:7.9.0", "geoplanet:7.10.0", "geoplanet:8.0.0", "woeplanet:8.0.0"], "meta:indexed": "2020-08-20T20:54:06.272594", "woe:alias_ENG_V": ["La Ferte-Milon Railway Station"], "woe:alias_ENG_P": ["La Ferte-Milon Station"], "meta:updated": "2020-08-22T01:53:29.615418", "woe:alias_FRE_S": ["Gare de la Ferte-Milon", "Gare la Ferte-Milon"], "woe:alias_FRE_V": ["Gare la Fert\u00e9-Milon"], "woe:hierarchy": {"continent": 24865675, "country": 23424819, "town": 0, "planet": 1, "county": 12597170, "suburb": 0, "state": 7153326, "region": 0, "localadmin": 22756707}, "woe:timezone_id": 28350911, "woe:hash": "u0dpz0bg35rq", "woe:centroid": [3.1212, 49.179501], "geom:latitude": 49.179501, "geom:longitude": 3.1212, "geom:hash": "u0dpz0bg35rq", "woe:latitude": 49.179501, "geom:centroid": [3.1212, 49.179501], "woe:longitude": 3.1212, "woe:repo": "woeplanet-poi-fr"}, "geometry": {"coordinates": [3.1212, 49.179501], "type": "Point"}}