{"type": "Feature", "id": 22139729, "properties": {"woe:id": 22139729, "woe:parent_id": 627421, "woe:name": "Gare de Sainte-C\u00e9cile-d'Andorge", "woe:placetype": 20, "woe:placetype_name": "POI", "woe:lang": "FRE", "iso:country": "FR", "meta:provider": ["geoplanet:7.3.1", "geoplanet:7.3.2", "geoplanet:7.4.0", "geoplanet:7.4.1", "geoplanet:7.5.1", "geoplanet:7.5.2", "geoplanet:7.6.0", "geoplanet:7.8.1", "geoplanet:7.9.0", "geoplanet:7.10.0", "geoplanet:8.0.0", "woeplanet:8.0.0"], "meta:indexed": "2020-08-20T20:54:04.849003", "woe:alias_ENG_V": ["Sainte-Cecile-d'Andorge Railway Station"], "woe:alias_ENG_P": ["Sainte-Cecile-d'Andorge Station"], "meta:updated": "2020-08-22T01:53:29.051801", "woe:alias_FRE_S": ["Gare de Sainte-Cecile-d'Andorge", "Gare Sainte-Cecile-d'Andorge"], "woe:alias_FRE_V": ["Gare Sainte-C\u00e9cile-d'Andorge"], "woe:hierarchy": {"continent": 24865675, "country": 23424819, "town": 0, "planet": 1, "county": 12597193, "suburb": 0, "state": 7153320, "region": 0, "localadmin": 12664076}, "woe:timezone_id": 28350911, "woe:hash": "spfgf2r0cjp4", "woe:centroid": [3.97573, 44.254459], "geom:latitude": 44.254459, "geom:longitude": 3.97573, "geom:hash": "spfgf2r0cjp4", "woe:latitude": 44.254459, "geom:centroid": [3.97573, 44.254459], "woe:longitude": 3.97573, "woe:repo": "woeplanet-poi-fr"}, "geometry": {"coordinates": [3.97573, 44.254459], "type": "Point"}}