{"type": "Feature", "id": 56060659, "geometry": {"type": "Point", "coordinates": [6.07804, 44.562031]}, "properties": {"woe:id": 56060659, "woe:parent_id": 592389, "woe:name": "Facult\u00e9 des Sciences du Sport", "woe:placetype": 20, "woe:placetype_name": "POI", "woe:lang": "FRE", "iso:country": "FR", "meta:provider": ["geoplanet:7.3.1", "geoplanet:7.3.2", "geoplanet:7.4.0", "geoplanet:7.4.1", "geoplanet:7.5.1", "geoplanet:7.5.2", "geoplanet:7.6.0", "geoplanet:7.8.1", "geoplanet:7.9.0", "geoplanet:7.10.0", "geoplanet:8.0.0", "woeplanet:8.0.0"], "meta:indexed": "2020-08-20T20:54:08.213139", "meta:updated": "2020-10-14T11:52:11.346330", "woe:alias_FRE_V": ["Faculte des Sciences du Sport"], "woe:hierarchy": {"continent": 24865675, "country": 23424819, "town": 0, "planet": 1, "county": 12597183, "suburb": 0, "state": 7153328, "region": 0, "localadmin": 22756286}, "woe:timezone_id": 28350911, "woe:hash": "spumd23bssej", "woe:centroid": [6.07804, 44.562031], "geom:latitude": 44.562031, "geom:longitude": 6.07804, "geom:hash": "spumd23bssej", "woe:latitude": 44.562031, "geom:centroid": [6.07804, 44.562031], "woe:longitude": 6.07804, "woe:repo": "woeplanet-poi-fr", "geom:area": 0.0, "woe:scale": 19}}