{"type": "Feature", "id": 56059875, "properties": {"woe:id": 56059875, "woe:parent_id": 615134, "woe:name": "Institut d'Arts Visuels", "woe:placetype": 20, "woe:placetype_name": "POI", "woe:lang": "FRE", "iso:country": "FR", "meta:provider": ["geoplanet:7.3.1", "geoplanet:7.3.2", "geoplanet:7.4.0", "geoplanet:7.4.1", "geoplanet:7.5.1", "geoplanet:7.5.2", "geoplanet:7.6.0", "geoplanet:7.8.1", "geoplanet:7.9.0", "geoplanet:7.10.0", "geoplanet:8.0.0", "woeplanet:8.0.0"], "meta:indexed": "2020-08-20T20:54:07.515240", "meta:updated": "2020-08-22T01:53:30.059796", "woe:hierarchy": {"continent": 24865675, "country": 23424819, "town": 0, "planet": 1, "county": 12597141, "suburb": 0, "state": 7153314, "region": 0, "localadmin": 12650242}, "woe:timezone_id": 28350911, "woe:hash": "u092e2rhdw5d", "woe:centroid": [1.91036, 47.902569], "geom:latitude": 47.902569, "geom:longitude": 1.91036, "geom:hash": "u092e2rhdw5d", "woe:latitude": 47.902569, "geom:centroid": [1.91036, 47.902569], "woe:longitude": 1.91036, "woe:repo": "woeplanet-poi-fr"}, "geometry": {"coordinates": [1.91036, 47.902569], "type": "Point"}}