{"type": "Feature", "id": 22142747, "properties": {"woe:id": 22142747, "woe:parent_id": 612355, "woe:name": "Gare de Montb\u00e9liard", "woe:placetype": 20, "woe:placetype_name": "POI", "woe:lang": "FRE", "iso:country": "FR", "meta:provider": ["geoplanet:7.3.1", "geoplanet:7.3.2", "geoplanet:7.4.0", "geoplanet:7.4.1", "geoplanet:7.5.1", "geoplanet:7.5.2", "geoplanet:7.6.0", "geoplanet:7.8.1", "geoplanet:7.9.0", "geoplanet:7.10.0", "geoplanet:8.0.0", "woeplanet:8.0.0"], "meta:indexed": "2020-08-20T20:54:04.979380", "woe:alias_ENG_V": ["Montbeliard Railway Station"], "woe:alias_ENG_P": ["Montbeliard Station"], "meta:updated": "2020-08-22T01:53:29.106716", "woe:alias_FRE_S": ["Gare de Montbeliard", "Gare Montbeliard"], "woe:alias_FRE_V": ["Gare Montb\u00e9liard"], "woe:hierarchy": {"continent": 24865675, "country": 23424819, "town": 0, "planet": 1, "county": 12597116, "suburb": 0, "state": 7153317, "region": 0, "localadmin": 12649421}, "woe:timezone_id": 28350911, "woe:hash": "u0ky69pueqj4", "woe:centroid": [6.80034, 47.511181], "geom:latitude": 47.511181, "geom:longitude": 6.80034, "geom:hash": "u0ky69pueqj4", "woe:latitude": 47.511181, "geom:centroid": [6.80034, 47.511181], "woe:longitude": 6.80034, "woe:repo": "woeplanet-poi-fr"}, "geometry": {"coordinates": [6.80034, 47.511181], "type": "Point"}}