{"type": "Feature", "id": 22917796, "geometry": {"type": "Point", "coordinates": [2.47164, 48.83522]}, "properties": {"woe:id": 22917796, "woe:parent_id": 55863546, "woe:name": "RER-Nogent-sur-Marne", "woe:placetype": 20, "woe:placetype_name": "POI", "woe:lang": "FRE", "iso:country": "FR", "meta:provider": ["geoplanet:7.3.1", "geoplanet:7.3.2", "geoplanet:7.4.0", "geoplanet:7.4.1", "geoplanet:7.5.1", "geoplanet:7.5.2", "geoplanet:7.6.0", "geoplanet:7.8.1", "geoplanet:7.9.0", "geoplanet:7.10.0", "geoplanet:8.0.0", "woeplanet:8.0.0"], "meta:indexed": "2020-08-20T20:54:06.999130", "woe:alias_ENG_V": ["Nogent-sur-Marne Railway Station"], "meta:updated": "2020-10-14T11:52:06.026877", "woe:alias_ENG_P": ["Nogent-sur-Marne Station"], "woe:alias_FRE_V": ["Gare de Nogent-sur-Marne", "Gare Nogent-sur-Marne"], "woe:hierarchy": {"continent": 24865675, "country": 23424819, "town": 0, "planet": 1, "county": 12597151, "suburb": 0, "state": 7153319, "region": 0, "localadmin": 12649998}, "woe:timezone_id": 28350911, "woe:hash": "u09vb4pvc2u6", "woe:centroid": [2.47164, 48.83522], "geom:latitude": 48.83522, "geom:longitude": 2.47164, "geom:hash": "u09vb4pvc2u6", "woe:latitude": 48.83522, "geom:centroid": [2.47164, 48.83522], "woe:longitude": 2.47164, "woe:repo": "woeplanet-poi-fr", "geom:area": 0.0, "woe:scale": 19}}