{"type": "Feature", "id": 22885259, "properties": {"woe:id": 22885259, "woe:parent_id": 586656, "woe:name": "Gare de Commentry", "woe:placetype": 20, "woe:placetype_name": "POI", "woe:lang": "FRE", "iso:country": "FR", "meta:provider": ["geoplanet:7.3.1", "geoplanet:7.3.2", "geoplanet:7.4.0", "geoplanet:7.4.1", "geoplanet:7.5.1", "geoplanet:7.5.2", "geoplanet:7.6.0", "geoplanet:7.8.1", "geoplanet:7.9.0", "geoplanet:7.10.0", "geoplanet:8.0.0", "woeplanet:8.0.0"], "meta:indexed": "2020-08-20T20:54:05.815572", "woe:alias_ENG_V": ["Commentry Railway Station"], "meta:updated": "2020-08-22T01:53:29.435929", "woe:alias_ENG_P": ["Commentry Station"], "woe:alias_FRE_V": ["Gare Commentry"], "woe:hierarchy": {"continent": 24865675, "country": 23424819, "town": 0, "planet": 1, "county": 12597131, "suburb": 0, "state": 7153310, "region": 0, "localadmin": 22755031}, "woe:timezone_id": 28350911, "woe:hash": "u01zq7g28rrt", "woe:centroid": [2.74008, 46.295139], "geom:latitude": 46.295139, "geom:longitude": 2.74008, "geom:hash": "u01zq7g28rrt", "woe:latitude": 46.295139, "geom:centroid": [2.74008, 46.295139], "woe:longitude": 2.74008, "woe:repo": "woeplanet-poi-fr"}, "geometry": {"coordinates": [2.74008, 46.295139], "type": "Point"}}