{"type": "Feature", "id": 22873604, "properties": {"woe:id": 22873604, "woe:parent_id": 576420, "woe:name": "Gare d'Arcachon", "woe:placetype": 20, "woe:placetype_name": "POI", "woe:lang": "FRE", "iso:country": "FR", "meta:provider": ["geoplanet:7.3.1", "geoplanet:7.3.2", "geoplanet:7.4.0", "geoplanet:7.4.1", "geoplanet:7.5.1", "geoplanet:7.5.2", "geoplanet:7.6.0", "geoplanet:7.8.1", "geoplanet:7.9.0", "geoplanet:7.10.0", "geoplanet:8.0.0", "woeplanet:8.0.0"], "meta:indexed": "2020-08-20T20:54:05.552992", "woe:alias_ENG_V": ["Arcachon Railway Station"], "meta:updated": "2020-08-22T01:53:30.341820", "woe:alias_ENG_P": ["Arcachon Station"], "woe:hierarchy": {"continent": 24865675, "country": 23424819, "town": 0, "planet": 1, "county": 12597132, "suburb": 0, "state": 7153309, "region": 0, "localadmin": 12637262}, "woe:timezone_id": 28350911, "woe:hash": "ezznj3zqz4rs", "woe:centroid": [-1.16527, 44.659222], "geom:latitude": 44.659222, "geom:longitude": -1.16527, "geom:hash": "ezznj3zqz4rs", "woe:latitude": 44.659222, "geom:centroid": [-1.16527, 44.659222], "woe:longitude": -1.16527, "woe:repo": "woeplanet-poi-fr"}, "geometry": {"coordinates": [-1.16527, 44.659222], "type": "Point"}}