{"type": "Feature", "id": 22878429, "geometry": {"type": "Point", "coordinates": [5.94468, 44.194969]}, "properties": {"woe:id": 22878429, "woe:parent_id": 622236, "woe:name": "Musee Scout Baden Powell", "woe:placetype": 20, "woe:placetype_name": "POI", "woe:lang": "FRE", "iso:country": "FR", "meta:provider": ["geoplanet:7.3.1", "geoplanet:7.3.2", "geoplanet:7.4.0", "geoplanet:7.4.1", "geoplanet:7.5.1", "geoplanet:7.5.2", "geoplanet:7.6.0", "geoplanet:7.8.1", "geoplanet:7.9.0", "geoplanet:7.10.0", "geoplanet:8.0.0", "woeplanet:8.0.0"], "meta:indexed": "2020-08-20T20:54:05.673053", "meta:updated": "2020-10-14T11:52:12.267063", "woe:hierarchy": {"continent": 24865675, "country": 23424819, "town": 0, "planet": 1, "county": 12597191, "suburb": 0, "state": 7153328, "region": 0, "localadmin": 22757615}, "woe:timezone_id": 28350911, "woe:hash": "spu5rm2y356e", "woe:centroid": [5.94468, 44.194969], "geom:latitude": 44.194969, "geom:longitude": 5.94468, "geom:hash": "spu5rm2y356e", "woe:latitude": 44.194969, "geom:centroid": [5.94468, 44.194969], "woe:longitude": 5.94468, "woe:repo": "woeplanet-poi-fr", "geom:area": 0.0, "woe:scale": 19}}