{"type": "Feature", "id": 22885891, "properties": {"woe:id": 22885891, "woe:parent_id": 577346, "woe:name": "Museum des Volcans", "woe:placetype": 20, "woe:placetype_name": "POI", "woe:lang": "FRE", "iso:country": "FR", "meta:provider": ["geoplanet:7.3.1", "geoplanet:7.3.2", "geoplanet:7.4.0", "geoplanet:7.4.1", "geoplanet:7.5.1", "geoplanet:7.5.2", "geoplanet:7.6.0", "geoplanet:7.8.1", "geoplanet:7.9.0", "geoplanet:7.10.0", "geoplanet:8.0.0", "woeplanet:8.0.0"], "meta:indexed": "2020-08-20T20:54:05.829491", "meta:updated": "2020-08-22T01:53:29.440688", "woe:alias_FRE_V": ["Mus\u00e9um des Volcans"], "woe:hierarchy": {"continent": 24865675, "country": 23424819, "town": 0, "planet": 1, "county": 12597148, "suburb": 0, "state": 7153310, "region": 0, "localadmin": 12637730}, "woe:timezone_id": 28350911, "woe:hash": "spcxxshdkf10", "woe:centroid": [2.44535, 44.934479], "geom:latitude": 44.934479, "geom:longitude": 2.44535, "geom:hash": "spcxxshdkf10", "woe:latitude": 44.934479, "geom:centroid": [2.44535, 44.934479], "woe:longitude": 2.44535, "woe:repo": "woeplanet-poi-fr"}, "geometry": {"coordinates": [2.44535, 44.934479], "type": "Point"}}