{"type": "Feature", "id": 22148263, "properties": {"woe:id": 22148263, "woe:parent_id": 622437, "woe:name": "Gare de Sorgues", "woe:placetype": 20, "woe:placetype_name": "POI", "woe:lang": "FRE", "iso:country": "FR", "meta:provider": ["geoplanet:7.3.1", "geoplanet:7.3.2", "geoplanet:7.4.0", "geoplanet:7.4.1", "geoplanet:7.5.1", "geoplanet:7.5.2", "geoplanet:7.6.0", "geoplanet:7.8.1", "geoplanet:7.9.0", "geoplanet:7.10.0", "geoplanet:8.0.0", "woeplanet:8.0.0"], "meta:indexed": "2020-08-20T20:54:05.201036", "woe:alias_ENG_V": ["Sorgues Railway Station"], "meta:updated": "2020-08-22T01:53:29.192943", "woe:alias_ENG_P": ["Sorgues Station"], "woe:alias_FRE_V": ["Gare Sorgues"], "woe:hierarchy": {"continent": 24865675, "country": 23424819, "town": 0, "planet": 1, "county": 12597203, "suburb": 0, "state": 7153328, "region": 0, "localadmin": 22757754}, "woe:timezone_id": 28350911, "woe:hash": "spg6qgndh2jf", "woe:centroid": [4.87606, 44.006081], "geom:latitude": 44.006081, "geom:longitude": 4.87606, "geom:hash": "spg6qgndh2jf", "woe:latitude": 44.006081, "geom:centroid": [4.87606, 44.006081], "woe:longitude": 4.87606, "woe:repo": "woeplanet-poi-fr"}, "geometry": {"coordinates": [4.87606, 44.006081], "type": "Point"}}