{"type": "Feature", "id": 22141856, "properties": {"woe:id": 22141856, "woe:parent_id": 620968, "woe:name": "SNCF-Santeuil-le Perchay", "woe:placetype": 20, "woe:placetype_name": "POI", "woe:lang": "FRE", "iso:country": "FR", "meta:provider": ["geoplanet:7.3.1", "geoplanet:7.3.2", "geoplanet:7.4.0", "geoplanet:7.4.1", "geoplanet:7.5.1", "geoplanet:7.5.2", "geoplanet:7.6.0", "geoplanet:7.8.1", "geoplanet:7.9.0", "geoplanet:7.10.0", "geoplanet:8.0.0", "woeplanet:8.0.0"], "meta:indexed": "2020-08-20T20:54:04.935498", "woe:alias_ENG_V": ["Santeuil-Le Perchay Railway Station"], "meta:updated": "2020-08-22T01:53:29.086740", "woe:alias_ENG_P": ["Santeuil-Le Perchay Station"], "woe:alias_FRE_V": ["Gare du Santeuil-le Perchay", "Gare Santeuil-le Perchay"], "woe:hierarchy": {"continent": 24865675, "country": 23424819, "town": 0, "planet": 1, "county": 12597124, "suburb": 0, "state": 7153319, "region": 0, "localadmin": 12651634}, "woe:timezone_id": 28350911, "woe:hash": "u09rkqg6g6vr", "woe:centroid": [1.94919, 49.124481], "geom:latitude": 49.124481, "geom:longitude": 1.94919, "geom:hash": "u09rkqg6g6vr", "woe:latitude": 49.124481, "geom:centroid": [1.94919, 49.124481], "woe:longitude": 1.94919, "woe:repo": "woeplanet-poi-fr"}, "geometry": {"coordinates": [1.94919, 49.124481], "type": "Point"}}