{"type": "Feature", "id": 22142114, "properties": {"woe:id": 22142114, "woe:parent_id": 24865754, "woe:name": "Gare de le Canet", "woe:placetype": 20, "woe:placetype_name": "POI", "woe:lang": "FRE", "iso:country": "FR", "meta:provider": ["geoplanet:7.3.1", "geoplanet:7.3.2", "geoplanet:7.4.0", "geoplanet:7.4.1", "geoplanet:7.5.1", "geoplanet:7.5.2", "geoplanet:7.6.0", "geoplanet:7.8.1", "geoplanet:7.9.0", "geoplanet:7.10.0", "geoplanet:8.0.0", "woeplanet:8.0.0"], "meta:indexed": "2020-08-20T20:54:04.950529", "woe:alias_ENG_V": ["Le Canet Railway Station"], "meta:updated": "2020-08-22T01:53:29.093502", "woe:alias_ENG_P": ["Le Canet Station"], "woe:alias_FRE_V": ["Gare le Canet"], "woe:hierarchy": {"continent": 24865675, "country": 23424819, "town": 0, "planet": 1, "county": 12597199, "suburb": 0, "state": 7153328, "region": 0, "localadmin": 24865754}, "woe:timezone_id": 28350911, "woe:hash": "speyd88h94sd", "woe:centroid": [5.38335, 43.333611], "geom:latitude": 43.333611, "geom:longitude": 5.38335, "geom:hash": "speyd88h94sd", "woe:latitude": 43.333611, "geom:centroid": [5.38335, 43.333611], "woe:longitude": 5.38335, "woe:repo": "woeplanet-poi-fr"}, "geometry": {"coordinates": [5.38335, 43.333611], "type": "Point"}}