{"type": "Feature", "id": 22912788, "properties": {"woe:id": 22912788, "woe:parent_id": 600352, "woe:name": "SNCF-la Verri\u00e8re", "woe:placetype": 20, "woe:placetype_name": "POI", "woe:lang": "FRE", "iso:country": "FR", "meta:provider": ["geoplanet:7.3.1", "geoplanet:7.3.2", "geoplanet:7.4.0", "geoplanet:7.4.1", "geoplanet:7.5.1", "geoplanet:7.5.2", "geoplanet:7.6.0", "geoplanet:7.8.1", "geoplanet:7.9.0", "geoplanet:7.10.0", "geoplanet:8.0.0", "woeplanet:8.0.0"], "meta:indexed": "2020-08-20T20:54:06.845641", "woe:alias_ENG_V": ["La Verriere Railway Station"], "woe:alias_ENG_P": ["La Verriere Station"], "meta:updated": "2020-08-22T01:53:29.825063", "woe:alias_FRE_S": ["Gare la Verriere", "SNCF-la Verriere", "Gare du la Verriere"], "woe:alias_FRE_V": ["Gare du la Verri\u00e8re", "Gare la Verri\u00e8re"], "woe:hierarchy": {"continent": 24865675, "country": 23424819, "town": 0, "planet": 1, "county": 12597126, "suburb": 0, "state": 7153319, "region": 0, "localadmin": 12645755}, "woe:timezone_id": 28350911, "woe:hash": "u09mk5xgey1d", "woe:centroid": [1.9444, 48.755211], "geom:latitude": 48.755211, "geom:longitude": 1.9444, "geom:hash": "u09mk5xgey1d", "woe:latitude": 48.755211, "geom:centroid": [1.9444, 48.755211], "woe:longitude": 1.9444, "woe:repo": "woeplanet-poi-fr"}, "geometry": {"coordinates": [1.9444, 48.755211], "type": "Point"}}