{"type": "Feature", "id": 56060169, "properties": {"woe:id": 56060169, "woe:parent_id": 55863612, "woe:name": "Ufr de Psychologie", "woe:placetype": 20, "woe:placetype_name": "POI", "woe:lang": "FRE", "iso:country": "FR", "meta:provider": ["geoplanet:7.3.1", "geoplanet:7.3.2", "geoplanet:7.4.0", "geoplanet:7.4.1", "geoplanet:7.5.1", "geoplanet:7.5.2", "geoplanet:7.6.0", "geoplanet:7.8.1", "geoplanet:7.9.0", "geoplanet:7.10.0", "geoplanet:8.0.0", "woeplanet:8.0.0"], "meta:indexed": "2020-08-20T20:54:07.777868", "meta:updated": "2020-08-22T01:53:30.155612", "woe:hierarchy": {"continent": 24865675, "country": 23424819, "town": 0, "planet": 1, "county": 12597175, "suburb": 0, "state": 7153324, "region": 0, "localadmin": 12655300}, "woe:timezone_id": 28350911, "woe:hash": "u140p0k60w7t", "woe:centroid": [3.12598, 50.626751], "geom:latitude": 50.626751, "geom:longitude": 3.12598, "geom:hash": "u140p0k60w7t", "woe:latitude": 50.626751, "geom:centroid": [3.12598, 50.626751], "woe:longitude": 3.12598, "woe:repo": "woeplanet-poi-fr"}, "geometry": {"coordinates": [3.12598, 50.626751], "type": "Point"}}