{"type": "Feature", "id": 56060390, "geometry": {"type": "Point", "coordinates": [-1.15647, 46.140079]}, "properties": {"woe:id": 56060390, "woe:parent_id": 599775, "woe:name": "\u00c9cole Sup\u00e9rieure de Commerce", "woe:placetype": 20, "woe:placetype_name": "POI", "woe:lang": "FRE", "iso:country": "FR", "meta:provider": ["geoplanet:7.3.1", "geoplanet:7.3.2", "geoplanet:7.4.0", "geoplanet:7.4.1", "geoplanet:7.5.1", "geoplanet:7.5.2", "geoplanet:7.6.0", "geoplanet:7.8.1", "geoplanet:7.9.0", "geoplanet:7.10.0", "geoplanet:8.0.0", "woeplanet:8.0.0"], "meta:indexed": "2020-08-20T20:54:07.970128", "meta:updated": "2020-10-14T11:52:11.337215", "woe:alias_FRE_V": ["Ecole Superieure de Commerce"], "woe:hierarchy": {"continent": 24865675, "country": 23424819, "town": 0, "planet": 1, "county": 12597189, "suburb": 0, "state": 7153327, "region": 0, "localadmin": 12663863}, "woe:timezone_id": 28350911, "woe:hash": "gbpnmxtckq1k", "woe:centroid": [-1.15647, 46.140079], "geom:latitude": 46.140079, "geom:longitude": -1.15647, "geom:hash": "gbpnmxtckq1k", "woe:latitude": 46.140079, "geom:centroid": [-1.15647, 46.140079], "woe:longitude": -1.15647, "woe:repo": "woeplanet-poi-fr", "geom:area": 0.0, "woe:scale": 19}}