{"type": "Feature", "id": 22873556, "properties": {"woe:id": 22873556, "woe:parent_id": 614386, "woe:name": "Gare de Nogaro", "woe:placetype": 20, "woe:placetype_name": "POI", "woe:lang": "FRE", "iso:country": "FR", "meta:provider": ["geoplanet:7.3.1", "geoplanet:7.3.2", "geoplanet:7.4.0", "geoplanet:7.4.1", "geoplanet:7.5.1", "geoplanet:7.5.2", "geoplanet:7.6.0", "geoplanet:7.8.1", "geoplanet:7.9.0", "geoplanet:7.10.0", "geoplanet:8.0.0", "woeplanet:8.0.0"], "meta:indexed": "2020-08-20T20:54:05.551294", "woe:alias_ENG_V": ["Nogaro Railway Station"], "meta:updated": "2020-08-22T01:53:29.331084", "woe:alias_ENG_P": ["Nogaro Station"], "woe:alias_FRE_V": ["Gare Nogaro"], "woe:hierarchy": {"continent": 24865675, "country": 23424819, "town": 0, "planet": 1, "county": 12597194, "suburb": 0, "state": 7153323, "region": 0, "localadmin": 12667648}, "woe:timezone_id": 28350911, "woe:hash": "ezzbzq4u9qnd", "woe:centroid": [-0.02912, 43.75935], "geom:latitude": 43.75935, "geom:longitude": -0.02912, "geom:hash": "ezzbzq4u9qnd", "woe:latitude": 43.75935, "geom:centroid": [-0.02912, 43.75935], "woe:longitude": -0.02912, "woe:repo": "woeplanet-poi-fr"}, "geometry": {"coordinates": [-0.02912, 43.75935], "type": "Point"}}