{"type": "Feature", "id": 56060578, "geometry": {"type": "Point", "coordinates": [-4.09323, 47.971081]}, "properties": {"woe:id": 56060578, "woe:parent_id": 618627, "woe:name": "Inst Sup de Gestion Asie/pacifique", "woe:placetype": 20, "woe:placetype_name": "POI", "woe:lang": "FRE", "iso:country": "FR", "meta:provider": ["geoplanet:7.3.1", "geoplanet:7.3.2", "geoplanet:7.4.0", "geoplanet:7.4.1", "geoplanet:7.5.1", "geoplanet:7.5.2", "geoplanet:7.6.0", "geoplanet:7.8.1", "geoplanet:7.9.0", "geoplanet:7.10.0", "geoplanet:8.0.0", "woeplanet:8.0.0"], "meta:indexed": "2020-08-20T20:54:08.142938", "meta:updated": "2020-10-14T11:52:11.214193", "woe:alias_FRE_V": ["Isuga"], "woe:hierarchy": {"continent": 24865675, "country": 23424819, "town": 0, "planet": 1, "county": 12591797, "suburb": 0, "state": 7153313, "region": 0, "localadmin": 12643393}, "woe:timezone_id": 28350911, "woe:hash": "gbt0fug7ucdk", "woe:centroid": [-4.09323, 47.971081], "geom:latitude": 47.971081, "geom:longitude": -4.09323, "geom:hash": "gbt0fug7ucdk", "woe:latitude": 47.971081, "geom:centroid": [-4.09323, 47.971081], "woe:longitude": -4.09323, "woe:repo": "woeplanet-poi-fr", "geom:area": 0.0, "woe:scale": 19}}