{"type": "Feature", "id": 22866669, "properties": {"woe:id": 22866669, "woe:parent_id": 596885, "woe:name": "Gare de la Bernerie en Retz", "woe:placetype": 20, "woe:placetype_name": "POI", "woe:lang": "FRE", "iso:country": "FR", "meta:provider": ["geoplanet:7.3.1", "geoplanet:7.3.2", "geoplanet:7.4.0", "geoplanet:7.4.1", "geoplanet:7.5.1", "geoplanet:7.5.2", "geoplanet:7.6.0", "geoplanet:7.8.1", "geoplanet:7.9.0", "geoplanet:7.10.0", "geoplanet:8.0.0", "woeplanet:8.0.0"], "meta:indexed": "2020-08-20T20:54:05.385472", "woe:alias_ENG_V": ["La Bernerie en Retz Railway Station"], "meta:updated": "2020-08-22T01:53:29.268138", "woe:alias_ENG_P": ["La Bernerie en Retz Station"], "woe:alias_FRE_V": ["Gare la Bernerie en Retz"], "woe:hierarchy": {"continent": 24865675, "country": 23424819, "town": 0, "planet": 1, "county": 12597177, "suburb": 0, "state": 7153325, "region": 0, "localadmin": 12663338}, "woe:timezone_id": 28350911, "woe:hash": "gbqecenwufm0", "woe:centroid": [-2.03432, 47.08308], "geom:latitude": 47.08308, "geom:longitude": -2.03432, "geom:hash": "gbqecenwufm0", "woe:latitude": 47.08308, "geom:centroid": [-2.03432, 47.08308], "woe:longitude": -2.03432, "woe:repo": "woeplanet-poi-fr"}, "geometry": {"coordinates": [-2.03432, 47.08308], "type": "Point"}}