{"type": "Feature", "id": 22902091, "properties": {"woe:id": 22902091, "woe:parent_id": 601174, "woe:name": "Gare de Landrecies", "woe:placetype": 20, "woe:placetype_name": "POI", "woe:lang": "FRE", "iso:country": "FR", "meta:provider": ["geoplanet:7.3.1", "geoplanet:7.3.2", "geoplanet:7.4.0", "geoplanet:7.4.1", "geoplanet:7.5.1", "geoplanet:7.5.2", "geoplanet:7.6.0", "geoplanet:7.8.1", "geoplanet:7.9.0", "geoplanet:7.10.0", "geoplanet:8.0.0", "woeplanet:8.0.0"], "meta:indexed": "2020-08-20T20:54:06.318269", "woe:alias_ENG_V": ["Landrecies Railway Station"], "meta:updated": "2020-08-22T01:53:29.632382", "woe:alias_ENG_P": ["Landrecies Station"], "woe:alias_FRE_V": ["Gare Landrecies"], "woe:hierarchy": {"continent": 24865675, "country": 23424819, "town": 0, "planet": 1, "county": 12597175, "suburb": 0, "state": 7153324, "region": 0, "localadmin": 12664402}, "woe:timezone_id": 28350911, "woe:hash": "u0ft5v9db9w3", "woe:centroid": [3.68251, 50.128349], "geom:latitude": 50.128349, "geom:longitude": 3.68251, "geom:hash": "u0ft5v9db9w3", "woe:latitude": 50.128349, "geom:centroid": [3.68251, 50.128349], "woe:longitude": 3.68251, "woe:repo": "woeplanet-poi-fr"}, "geometry": {"coordinates": [3.68251, 50.128349], "type": "Point"}}