{"type": "Feature", "id": 22886131, "geometry": {"type": "Point", "coordinates": [4.74564, 44.558819]}, "properties": {"woe:id": 22886131, "woe:parent_id": 612522, "woe:name": "Gare de Mont\u00e9limar", "woe:placetype": 20, "woe:placetype_name": "POI", "woe:lang": "FRE", "iso:country": "FR", "meta:provider": ["geoplanet:7.3.1", "geoplanet:7.3.2", "geoplanet:7.4.0", "geoplanet:7.4.1", "geoplanet:7.5.1", "geoplanet:7.5.2", "geoplanet:7.6.0", "geoplanet:7.8.1", "geoplanet:7.9.0", "geoplanet:7.10.0", "geoplanet:8.0.0", "woeplanet:8.0.0"], "meta:indexed": "2020-08-20T20:54:05.839495", "woe:alias_ENG_V": ["Montelimar Railway Station"], "woe:alias_ENG_P": ["Montelimar Station"], "meta:updated": "2020-10-14T11:52:12.311946", "woe:alias_FRE_S": ["Gare de Montelimar", "Gare Montelimar"], "woe:alias_FRE_V": ["Gare Mont\u00e9limar"], "woe:hierarchy": {"continent": 24865675, "country": 23424819, "town": 0, "planet": 1, "county": 12597190, "suburb": 0, "state": 7153329, "region": 0, "localadmin": 12667038}, "woe:timezone_id": 28350911, "woe:hash": "spgm7zxtvmvs", "woe:centroid": [4.74564, 44.558819], "geom:latitude": 44.558819, "geom:longitude": 4.74564, "geom:hash": "spgm7zxtvmvs", "woe:latitude": 44.558819, "geom:centroid": [4.74564, 44.558819], "woe:longitude": 4.74564, "woe:repo": "woeplanet-poi-fr", "geom:area": 0.0, "woe:scale": 19}}