{"type": "Feature", "id": 22145957, "properties": {"woe:id": 22145957, "woe:parent_id": 618627, "woe:name": "Gare de Quimper", "woe:placetype": 20, "woe:placetype_name": "POI", "woe:lang": "FRE", "iso:country": "FR", "meta:provider": ["geoplanet:7.3.1", "geoplanet:7.3.2", "geoplanet:7.4.0", "geoplanet:7.4.1", "geoplanet:7.5.1", "geoplanet:7.5.2", "geoplanet:7.6.0", "geoplanet:7.8.1", "geoplanet:7.9.0", "geoplanet:7.10.0", "geoplanet:8.0.0", "woeplanet:8.0.0"], "meta:indexed": "2020-08-20T20:54:05.103414", "woe:alias_ENG_V": ["Quimper Railway Station"], "meta:updated": "2020-08-22T01:53:29.151402", "woe:alias_ENG_P": ["Quimper Station"], "woe:alias_FRE_V": ["Gare Quimper"], "woe:hierarchy": {"continent": 24865675, "country": 23424819, "town": 0, "planet": 1, "county": 12591797, "suburb": 0, "state": 7153313, "region": 0, "localadmin": 12643393}, "woe:timezone_id": 28350911, "woe:hash": "gbt14c5fgn97", "woe:centroid": [-4.09262, 47.994282], "geom:latitude": 47.994282, "geom:longitude": -4.09262, "geom:hash": "gbt14c5fgn97", "woe:latitude": 47.994282, "geom:centroid": [-4.09262, 47.994282], "woe:longitude": -4.09262, "woe:repo": "woeplanet-poi-fr"}, "geometry": {"coordinates": [-4.09262, 47.994282], "type": "Point"}}