{"type": "Feature", "id": 55863032, "geometry": {"type": "Point", "coordinates": [3.15709, 50.26487]}, "properties": {"woe:id": 55863032, "woe:parent_id": 577080, "woe:name": "Gare de Aubigny-au-Bac", "woe:placetype": 20, "woe:placetype_name": "POI", "woe:lang": "FRE", "iso:country": "FR", "meta:provider": ["geoplanet:7.3.1", "geoplanet:7.3.2", "geoplanet:7.4.0", "geoplanet:7.4.1", "geoplanet:7.5.1", "geoplanet:7.5.2", "geoplanet:7.6.0", "geoplanet:7.8.1", "geoplanet:7.9.0", "geoplanet:7.10.0", "geoplanet:8.0.0", "woeplanet:8.0.0"], "meta:indexed": "2020-08-20T20:54:07.259560", "woe:alias_ENG_V": ["Aubigny-au-Bac Railway Station"], "meta:updated": "2020-10-14T11:52:04.901994", "woe:alias_ENG_P": ["Aubigny-au-Bac Station"], "woe:alias_FRE_V": ["Gare Aubigny-au-Bac"], "woe:hierarchy": {"continent": 24865675, "country": 23424819, "town": 0, "planet": 1, "county": 12597175, "suburb": 0, "state": 7153324, "region": 0, "localadmin": 12655720}, "woe:timezone_id": 28350911, "woe:hash": "u0fjzy6yjdbu", "woe:centroid": [3.15709, 50.26487], "geom:latitude": 50.26487, "geom:longitude": 3.15709, "geom:hash": "u0fjzy6yjdbu", "woe:latitude": 50.26487, "geom:centroid": [3.15709, 50.26487], "woe:longitude": 3.15709, "woe:repo": "woeplanet-poi-fr", "geom:area": 0.0, "woe:scale": 19}}