{"type": "Feature", "id": 22145477, "geometry": {"type": "Point", "coordinates": [1.28916, 43.621269]}, "properties": {"woe:id": 22145477, "woe:parent_id": 616480, "woe:name": "Gare de Pibrac", "woe:placetype": 20, "woe:placetype_name": "POI", "woe:lang": "FRE", "iso:country": "FR", "meta:provider": ["geoplanet:7.3.1", "geoplanet:7.3.2", "geoplanet:7.4.0", "geoplanet:7.4.1", "geoplanet:7.5.1", "geoplanet:7.5.2", "geoplanet:7.6.0", "geoplanet:7.8.1", "geoplanet:7.9.0", "geoplanet:7.10.0", "geoplanet:8.0.0", "woeplanet:8.0.0"], "meta:indexed": "2020-08-20T20:54:05.084916", "woe:alias_ENG_V": ["Pibrac Railway Station"], "meta:updated": "2020-10-14T11:52:05.188723", "woe:alias_ENG_P": ["Pibrac Station"], "woe:alias_FRE_V": ["Gare Pibrac"], "woe:hierarchy": {"continent": 24865675, "country": 23424819, "town": 0, "planet": 1, "county": 12597186, "suburb": 0, "state": 7153323, "region": 0, "localadmin": 12659680}, "woe:timezone_id": 28350911, "woe:hash": "spbbjm48r9gm", "woe:centroid": [1.28916, 43.621269], "geom:latitude": 43.621269, "geom:longitude": 1.28916, "geom:hash": "spbbjm48r9gm", "woe:latitude": 43.621269, "geom:centroid": [1.28916, 43.621269], "woe:longitude": 1.28916, "woe:repo": "woeplanet-poi-fr", "geom:area": 0.0, "woe:scale": 19}}