{"type": "Feature", "id": 56060596, "geometry": {"type": "Point", "coordinates": [-1.42603, 46.675419]}, "properties": {"woe:id": 56060596, "woe:parent_id": 599765, "woe:name": "\u00c9cole de Gestion Et de Commerce", "woe:placetype": 20, "woe:placetype_name": "POI", "woe:lang": "FRE", "iso:country": "FR", "meta:provider": ["geoplanet:7.3.1", "geoplanet:7.3.2", "geoplanet:7.4.0", "geoplanet:7.4.1", "geoplanet:7.5.1", "geoplanet:7.5.2", "geoplanet:7.6.0", "geoplanet:7.8.1", "geoplanet:7.9.0", "geoplanet:7.10.0", "geoplanet:8.0.0", "woeplanet:8.0.0"], "meta:indexed": "2020-08-20T20:54:08.157835", "meta:updated": "2020-10-14T11:52:11.265774", "woe:alias_FRE_V": ["Ecole de Gestion Et de Commerce"], "woe:hierarchy": {"continent": 24865675, "country": 23424819, "town": 0, "planet": 1, "county": 12597200, "suburb": 0, "state": 7153325, "region": 0, "localadmin": 12663965}, "woe:timezone_id": 28350911, "woe:hash": "gbqcx91850dz", "woe:centroid": [-1.42603, 46.675419], "geom:latitude": 46.675419, "geom:longitude": -1.42603, "geom:hash": "gbqcx91850dz", "woe:latitude": 46.675419, "geom:centroid": [-1.42603, 46.675419], "woe:longitude": -1.42603, "woe:repo": "woeplanet-poi-fr", "geom:area": 0.0, "woe:scale": 19}}