{"type": "Feature", "id": 22869723, "properties": {"woe:id": 22869723, "woe:parent_id": 578160, "woe:name": "Gare de Barentin", "woe:placetype": 20, "woe:placetype_name": "POI", "woe:lang": "FRE", "iso:country": "FR", "meta:provider": ["geoplanet:7.3.1", "geoplanet:7.3.2", "geoplanet:7.4.0", "geoplanet:7.4.1", "geoplanet:7.5.1", "geoplanet:7.5.2", "geoplanet:7.6.0", "geoplanet:7.8.1", "geoplanet:7.9.0", "geoplanet:7.10.0", "geoplanet:8.0.0", "woeplanet:8.0.0"], "meta:indexed": "2020-08-20T20:54:05.428694", "woe:alias_ENG_V": ["Barentin Railway Station"], "meta:updated": "2020-08-22T01:53:29.284518", "woe:alias_ENG_P": ["Barentin Station"], "woe:alias_FRE_V": ["Gare Barentin"], "woe:hierarchy": {"continent": 24865675, "country": 23424819, "town": 0, "planet": 1, "county": 12597115, "suburb": 0, "state": 7153318, "region": 0, "localadmin": 12638111}, "woe:timezone_id": 28350911, "woe:hash": "u0b9vsn7bj45", "woe:centroid": [0.95341, 49.549011], "geom:latitude": 49.549011, "geom:longitude": 0.95341, "geom:hash": "u0b9vsn7bj45", "woe:latitude": 49.549011, "geom:centroid": [0.95341, 49.549011], "woe:longitude": 0.95341, "woe:repo": "woeplanet-poi-fr"}, "geometry": {"coordinates": [0.95341, 49.549011], "type": "Point"}}