{"type": "Feature", "id": 22895695, "geometry": {"type": "Point", "coordinates": [7.0715, 49.106991]}, "properties": {"woe:id": 22895695, "woe:parent_id": 621077, "woe:name": "Mus\u00e9e Historique de Sarreguemines", "woe:placetype": 20, "woe:placetype_name": "POI", "woe:lang": "FRE", "iso:country": "FR", "meta:provider": ["geoplanet:7.3.1", "geoplanet:7.3.2", "geoplanet:7.4.0", "geoplanet:7.4.1", "geoplanet:7.5.1", "geoplanet:7.5.2", "geoplanet:7.6.0", "geoplanet:7.8.1", "geoplanet:7.9.0", "geoplanet:7.10.0", "geoplanet:8.0.0", "woeplanet:8.0.0"], "meta:indexed": "2020-08-20T20:54:06.088109", "meta:updated": "2020-10-14T11:52:11.733804", "woe:alias_FRE_S": ["Musee Historique de Sarreguemines"], "woe:hierarchy": {"continent": 24865675, "country": 23424819, "town": 0, "planet": 1, "county": 12597171, "suburb": 0, "state": 7153322, "region": 0, "localadmin": 12667555}, "woe:timezone_id": 28350911, "woe:hash": "u0tp2gtkcyse", "woe:centroid": [7.0715, 49.106991], "geom:latitude": 49.106991, "geom:longitude": 7.0715, "geom:hash": "u0tp2gtkcyse", "woe:latitude": 49.106991, "geom:centroid": [7.0715, 49.106991], "woe:longitude": 7.0715, "woe:repo": "woeplanet-poi-fr", "geom:area": 0.0, "woe:scale": 19}}