{"type": "Feature", "id": 22910974, "properties": {"woe:id": 22910974, "woe:parent_id": 603576, "woe:name": "Gare Tgv A\u00e9roport Charles de Gaulle 2", "woe:placetype": 20, "woe:placetype_name": "POI", "woe:lang": "FRE", "iso:country": "FR", "meta:provider": ["geoplanet:7.3.1", "geoplanet:7.3.2", "geoplanet:7.4.0", "geoplanet:7.4.1", "geoplanet:7.5.1", "geoplanet:7.5.2", "geoplanet:7.6.0", "geoplanet:7.8.1", "geoplanet:7.9.0", "geoplanet:7.10.0", "geoplanet:8.0.0", "woeplanet:8.0.0"], "meta:indexed": "2020-08-20T20:54:06.792500", "meta:updated": "2020-08-22T01:53:29.804010", "woe:alias_FRE_S": ["Gare Tgv Aeroport Charles de Gaulle 2"], "woe:alias_FRE_V": ["Gare Tgv Roissy-Charles-de-Gaulle"], "woe:hierarchy": {"continent": 24865675, "country": 23424819, "town": 0, "planet": 1, "county": 12597156, "suburb": 0, "state": 7153319, "region": 0, "localadmin": 12636788}, "woe:timezone_id": 28350911, "woe:hash": "u09yf8b7cbbt", "woe:centroid": [2.57122, 49.003792], "geom:latitude": 49.003792, "geom:longitude": 2.57122, "geom:hash": "u09yf8b7cbbt", "woe:latitude": 49.003792, "geom:centroid": [2.57122, 49.003792], "woe:longitude": 2.57122, "woe:repo": "woeplanet-poi-fr"}, "geometry": {"coordinates": [2.57122, 49.003792], "type": "Point"}}