{"type": "Feature", "id": 22142763, "geometry": {"type": "Point", "coordinates": [4.07833, 45.604691]}, "properties": {"woe:id": 22142763, "woe:parent_id": 612393, "woe:name": "Gare de Montbrison", "woe:placetype": 20, "woe:placetype_name": "POI", "woe:lang": "FRE", "iso:country": "FR", "meta:provider": ["geoplanet:7.3.1", "geoplanet:7.3.2", "geoplanet:7.4.0", "geoplanet:7.4.1", "geoplanet:7.5.1", "geoplanet:7.5.2", "geoplanet:7.6.0", "geoplanet:7.8.1", "geoplanet:7.9.0", "geoplanet:7.10.0", "geoplanet:8.0.0", "woeplanet:8.0.0"], "meta:indexed": "2020-08-20T20:54:04.981223", "woe:alias_ENG_V": ["Montbrison Railway Station"], "meta:updated": "2020-10-14T11:52:05.445970", "woe:alias_ENG_P": ["Montbrison Station"], "woe:alias_FRE_V": ["Gare Montbrison"], "woe:hierarchy": {"continent": 24865675, "country": 23424819, "town": 0, "planet": 1, "county": 12597165, "suburb": 0, "state": 7153329, "region": 0, "localadmin": 12660301}, "woe:timezone_id": 28350911, "woe:hash": "u04gky1dxfx6", "woe:centroid": [4.07833, 45.604691], "geom:latitude": 45.604691, "geom:longitude": 4.07833, "geom:hash": "u04gky1dxfx6", "woe:latitude": 45.604691, "geom:centroid": [4.07833, 45.604691], "woe:longitude": 4.07833, "woe:repo": "woeplanet-poi-fr", "geom:area": 0.0, "woe:scale": 19}}