{"type": "Feature", "id": 22870241, "geometry": {"type": "Point", "coordinates": [-1.4344, 46.78759]}, "properties": {"woe:id": 22870241, "woe:parent_id": 579156, "woe:name": "Gare de Belleville", "woe:placetype": 20, "woe:placetype_name": "POI", "woe:lang": "FRE", "iso:country": "FR", "meta:provider": ["geoplanet:7.3.1", "geoplanet:7.3.2", "geoplanet:7.4.0", "geoplanet:7.4.1", "geoplanet:7.5.1", "geoplanet:7.5.2", "geoplanet:7.6.0", "geoplanet:7.8.1", "geoplanet:7.9.0", "geoplanet:7.10.0", "geoplanet:8.0.0", "woeplanet:8.0.0"], "meta:indexed": "2020-08-20T20:54:05.446124", "woe:alias_ENG_V": ["Belleville Railway Station"], "meta:updated": "2020-10-14T11:52:11.823189", "woe:alias_ENG_P": ["Belleville Station"], "woe:alias_FRE_V": ["Gare Belleville-sur-Vie", "Gare de Belleville-sur-Vie", "Gare Belleville"], "woe:hierarchy": {"continent": 24865675, "country": 23424819, "town": 0, "planet": 1, "county": 12597200, "suburb": 0, "state": 7153325, "region": 0, "localadmin": 12656721}, "woe:timezone_id": 28350911, "woe:hash": "gbqfpm7t2ncv", "woe:centroid": [-1.4344, 46.78759], "geom:latitude": 46.78759, "geom:longitude": -1.4344, "geom:hash": "gbqfpm7t2ncv", "woe:latitude": 46.78759, "geom:centroid": [-1.4344, 46.78759], "woe:longitude": -1.4344, "woe:repo": "woeplanet-poi-fr", "geom:area": 0.0, "woe:scale": 19}}