{"type": "Feature", "id": 22145990, "geometry": {"type": "Point", "coordinates": [3.47875, 50.39048]}, "properties": {"woe:id": 22145990, "woe:parent_id": 618752, "woe:name": "Gare de Raismes", "woe:placetype": 20, "woe:placetype_name": "POI", "woe:lang": "FRE", "iso:country": "FR", "meta:provider": ["geoplanet:7.3.1", "geoplanet:7.3.2", "geoplanet:7.4.0", "geoplanet:7.4.1", "geoplanet:7.5.1", "geoplanet:7.5.2", "geoplanet:7.6.0", "geoplanet:7.8.1", "geoplanet:7.9.0", "geoplanet:7.10.0", "geoplanet:8.0.0", "woeplanet:8.0.0"], "meta:indexed": "2020-08-20T20:54:05.107191", "woe:alias_ENG_V": ["Raismes Railway Station"], "meta:updated": "2020-10-14T11:52:05.473197", "woe:alias_ENG_P": ["Raismes Station"], "woe:alias_FRE_V": ["Gare Raismes"], "woe:hierarchy": {"continent": 24865675, "country": 23424819, "town": 0, "planet": 1, "county": 12597175, "suburb": 0, "state": 7153324, "region": 0, "localadmin": 12668744}, "woe:timezone_id": 28350911, "woe:hash": "u0fqxjm1uf21", "woe:centroid": [3.47875, 50.39048], "geom:latitude": 50.39048, "geom:longitude": 3.47875, "geom:hash": "u0fqxjm1uf21", "woe:latitude": 50.39048, "geom:centroid": [3.47875, 50.39048], "woe:longitude": 3.47875, "woe:repo": "woeplanet-poi-fr", "geom:area": 0.0, "woe:scale": 19}}