{"type": "Feature", "id": 55863122, "geometry": {"type": "Point", "coordinates": [0.68764, 45.24448]}, "properties": {"woe:id": 55863122, "woe:parent_id": 584924, "woe:name": "Gare de Ch\u00e2teau-l'Ev\u00eaque", "woe:placetype": 20, "woe:placetype_name": "POI", "woe:lang": "FRE", "iso:country": "FR", "meta:provider": ["geoplanet:7.3.1", "geoplanet:7.3.2", "geoplanet:7.4.0", "geoplanet:7.4.1", "geoplanet:7.5.1", "geoplanet:7.5.2", "geoplanet:7.6.0", "geoplanet:7.8.1", "geoplanet:7.9.0", "geoplanet:7.10.0", "geoplanet:8.0.0", "woeplanet:8.0.0"], "meta:indexed": "2020-08-20T20:54:07.341159", "woe:alias_ENG_V": ["Chateau-l'Eveque Railway Station"], "woe:alias_ENG_P": ["Chateau-l'Eveque Station"], "meta:updated": "2020-10-14T11:52:04.713383", "woe:alias_FRE_S": ["Gare de Chateau-l'Eveque", "Gare Chateau-l'Eveque"], "woe:alias_FRE_V": ["Gare Ch\u00e2teau-l'Ev\u00eaque"], "woe:hierarchy": {"continent": 24865675, "country": 23424819, "town": 0, "planet": 1, "county": 12597122, "suburb": 0, "state": 7153309, "region": 0, "localadmin": 12641250}, "woe:timezone_id": 28350911, "woe:hash": "u003rss8pnms", "woe:centroid": [0.68764, 45.24448], "geom:latitude": 45.24448, "geom:longitude": 0.68764, "geom:hash": "u003rss8pnms", "woe:latitude": 45.24448, "geom:centroid": [0.68764, 45.24448], "woe:longitude": 0.68764, "woe:repo": "woeplanet-poi-fr", "geom:area": 0.0, "woe:scale": 19}}