{"type": "Feature", "id": 22141966, "geometry": {"type": "Point", "coordinates": [5.46686, 43.288261]}, "properties": {"woe:id": 22141966, "woe:parent_id": 24865751, "woe:name": "Gare Saint-Marcel", "woe:placetype": 20, "woe:placetype_name": "POI", "woe:lang": "FRE", "iso:country": "FR", "meta:provider": ["geoplanet:7.3.1", "geoplanet:7.3.2", "geoplanet:7.4.0", "geoplanet:7.4.1", "geoplanet:7.5.1", "geoplanet:7.5.2", "geoplanet:7.6.0", "geoplanet:7.8.1", "geoplanet:7.9.0", "geoplanet:7.10.0", "geoplanet:8.0.0", "woeplanet:8.0.0"], "meta:indexed": "2020-08-20T20:54:04.947360", "woe:alias_ENG_V": ["Saint-Marcel Railway Station"], "meta:updated": "2020-10-14T11:52:05.086541", "woe:alias_ENG_P": ["Saint-Marcel Station"], "woe:hierarchy": {"continent": 24865675, "country": 23424819, "town": 0, "planet": 1, "county": 12597199, "suburb": 0, "state": 7153328, "region": 0, "localadmin": 24865751}, "woe:timezone_id": 28350911, "woe:hash": "speyk2ku7hdr", "woe:centroid": [5.46686, 43.288261], "geom:latitude": 43.288261, "geom:longitude": 5.46686, "geom:hash": "speyk2ku7hdr", "woe:latitude": 43.288261, "geom:centroid": [5.46686, 43.288261], "woe:longitude": 5.46686, "woe:repo": "woeplanet-poi-fr", "geom:area": 0.0, "woe:scale": 19}}