{"type": "Feature", "id": 22147714, "geometry": {"type": "Point", "coordinates": [0.22183, 44.837158]}, "properties": {"woe:id": 22147714, "woe:parent_id": 627538, "woe:name": "Gare de Sainte-Foy-la-Grande", "woe:placetype": 20, "woe:placetype_name": "POI", "woe:lang": "FRE", "iso:country": "FR", "meta:provider": ["geoplanet:7.3.1", "geoplanet:7.3.2", "geoplanet:7.4.0", "geoplanet:7.4.1", "geoplanet:7.5.1", "geoplanet:7.5.2", "geoplanet:7.6.0", "geoplanet:7.8.1", "geoplanet:7.9.0", "geoplanet:7.10.0", "geoplanet:8.0.0", "woeplanet:8.0.0"], "meta:indexed": "2020-08-20T20:54:05.182178", "woe:alias_ENG_V": ["Sainte-Foy-la-Grande Railway Station"], "meta:updated": "2020-10-14T11:52:05.242929", "woe:alias_ENG_P": ["Sainte-Foy-la-Grande Station"], "woe:alias_FRE_V": ["Gare Sainte-Foy-la-Grande"], "woe:hierarchy": {"continent": 24865675, "country": 23424819, "town": 0, "planet": 1, "county": 12597132, "suburb": 0, "state": 7153309, "region": 0, "localadmin": 12653375}, "woe:timezone_id": 28350911, "woe:hash": "spbpj43e3h03", "woe:centroid": [0.22183, 44.837158], "geom:latitude": 44.837158, "geom:longitude": 0.22183, "geom:hash": "spbpj43e3h03", "woe:latitude": 44.837158, "geom:centroid": [0.22183, 44.837158], "woe:longitude": 0.22183, "woe:repo": "woeplanet-poi-fr", "geom:area": 0.0, "woe:scale": 19}}