{"type": "Feature", "id": 56060280, "properties": {"woe:id": 56060280, "woe:parent_id": 628971, "woe:name": "Univ. Fran\u00e7ois Rabelais", "woe:placetype": 20, "woe:placetype_name": "POI", "woe:lang": "FRE", "iso:country": "FR", "meta:provider": ["geoplanet:7.3.1", "geoplanet:7.3.2", "geoplanet:7.4.0", "geoplanet:7.4.1", "geoplanet:7.5.1", "geoplanet:7.5.2", "geoplanet:7.6.0", "geoplanet:7.8.1", "geoplanet:7.9.0", "geoplanet:7.10.0", "geoplanet:8.0.0", "woeplanet:8.0.0"], "meta:indexed": "2020-08-20T20:54:07.873462", "meta:updated": "2020-08-22T01:53:30.190710", "woe:alias_FRE_V": ["Univ. Francois Rabelais"], "woe:hierarchy": {"continent": 24865675, "country": 23424819, "town": 0, "planet": 1, "county": 12597121, "suburb": 0, "state": 7153314, "region": 0, "localadmin": 12653257}, "woe:timezone_id": 28350911, "woe:hash": "u02mxs1rkyvk", "woe:centroid": [0.68308, 47.396301], "geom:latitude": 47.396301, "geom:longitude": 0.68308, "geom:hash": "u02mxs1rkyvk", "woe:latitude": 47.396301, "geom:centroid": [0.68308, 47.396301], "woe:longitude": 0.68308, "woe:repo": "woeplanet-poi-fr"}, "geometry": {"coordinates": [0.68308, 47.396301], "type": "Point"}}