{"type": "Feature", "id": 22879889, "properties": {"woe:id": 22879889, "woe:parent_id": 608153, "woe:name": "Musee Petiet", "woe:placetype": 20, "woe:placetype_name": "POI", "woe:lang": "FRE", "iso:country": "FR", "meta:provider": ["geoplanet:7.3.1", "geoplanet:7.3.2", "geoplanet:7.4.0", "geoplanet:7.4.1", "geoplanet:7.5.1", "geoplanet:7.5.2", "geoplanet:7.6.0", "geoplanet:7.8.1", "geoplanet:7.9.0", "geoplanet:7.10.0", "geoplanet:8.0.0", "woeplanet:8.0.0"], "meta:indexed": "2020-08-20T20:54:05.700678", "meta:updated": "2020-08-22T01:53:29.389472", "woe:alias_FRE_V": ["Mus\u00e9e Petiet"], "woe:hierarchy": {"continent": 24865675, "country": 23424819, "town": 0, "planet": 1, "county": 12597198, "suburb": 0, "state": 7153320, "region": 0, "localadmin": 20075068}, "woe:timezone_id": 28350911, "woe:hash": "sp9sfmg9fu6w", "woe:centroid": [2.21318, 43.054371], "geom:latitude": 43.054371, "geom:longitude": 2.21318, "geom:hash": "sp9sfmg9fu6w", "woe:latitude": 43.054371, "geom:centroid": [2.21318, 43.054371], "woe:longitude": 2.21318, "woe:repo": "woeplanet-poi-fr"}, "geometry": {"coordinates": [2.21318, 43.054371], "type": "Point"}}