{"type": "Feature", "id": 22915027, "geometry": {"type": "Point", "coordinates": [2.25046, 48.821861]}, "properties": {"woe:id": 22915027, "woe:parent_id": 55863487, "woe:name": "Mvcg", "woe:placetype": 20, "woe:placetype_name": "POI", "woe:lang": "FRE", "iso:country": "FR", "meta:provider": ["geoplanet:7.3.1", "geoplanet:7.3.2", "geoplanet:7.4.0", "geoplanet:7.4.1", "geoplanet:7.5.1", "geoplanet:7.5.2", "geoplanet:7.6.0", "geoplanet:7.8.1", "geoplanet:7.9.0", "geoplanet:7.10.0", "geoplanet:8.0.0", "woeplanet:8.0.0"], "meta:indexed": "2020-08-20T20:54:06.921867", "meta:updated": "2020-10-14T11:52:06.111405", "woe:hierarchy": {"continent": 24865675, "country": 23424819, "town": 0, "planet": 1, "county": 15022631, "suburb": 0, "state": 7153319, "region": 0, "localadmin": 12645408}, "woe:timezone_id": 28350911, "woe:hash": "u09tepwxzw88", "woe:centroid": [2.25046, 48.821861], "geom:latitude": 48.821861, "geom:longitude": 2.25046, "geom:hash": "u09tepwxzw88", "woe:latitude": 48.821861, "geom:centroid": [2.25046, 48.821861], "woe:longitude": 2.25046, "woe:repo": "woeplanet-poi-fr", "geom:area": 0.0, "woe:scale": 19}}