{"type": "Feature", "id": 22140142, "geometry": {"type": "Point", "coordinates": [5.05183, 43.339779]}, "properties": {"woe:id": 22140142, "woe:parent_id": 597913, "woe:name": "Gare de la Couronne", "woe:placetype": 20, "woe:placetype_name": "POI", "woe:lang": "FRE", "iso:country": "FR", "meta:provider": ["geoplanet:7.3.1", "geoplanet:7.3.2", "geoplanet:7.4.0", "geoplanet:7.4.1", "geoplanet:7.5.1", "geoplanet:7.5.2", "geoplanet:7.6.0", "geoplanet:7.8.1", "geoplanet:7.9.0", "geoplanet:7.10.0", "geoplanet:8.0.0", "woeplanet:8.0.0"], "meta:indexed": "2020-08-20T20:54:04.865763", "woe:alias_ENG_V": ["La Couronne Railway Station"], "meta:updated": "2020-10-14T11:52:05.485966", "woe:alias_ENG_P": ["La Couronne Station"], "woe:alias_FRE_V": ["Gare Martigues-la Couronne", "Gare de Martigues-la Couronne", "Gare la Couronne"], "woe:hierarchy": {"continent": 24865675, "country": 23424819, "town": 0, "planet": 1, "county": 12597199, "suburb": 0, "state": 7153328, "region": 0, "localadmin": 12655785}, "woe:timezone_id": 28350911, "woe:hash": "spewdcy8s0m7", "woe:centroid": [5.05183, 43.339779], "geom:latitude": 43.339779, "geom:longitude": 5.05183, "geom:hash": "spewdcy8s0m7", "woe:latitude": 43.339779, "geom:centroid": [5.05183, 43.339779], "woe:longitude": 5.05183, "woe:repo": "woeplanet-poi-fr", "geom:area": 0.0, "woe:scale": 19}}