{"type": "Feature", "id": 56060108, "geometry": {"type": "Point", "coordinates": [2.8246, 50.434429]}, "properties": {"woe:id": 56060108, "woe:parent_id": 605148, "woe:name": "Facult\u00e9 des Sciences Jean Perrin", "woe:placetype": 20, "woe:placetype_name": "POI", "woe:lang": "FRE", "iso:country": "FR", "meta:provider": ["geoplanet:7.3.1", "geoplanet:7.3.2", "geoplanet:7.4.0", "geoplanet:7.4.1", "geoplanet:7.5.1", "geoplanet:7.5.2", "geoplanet:7.6.0", "geoplanet:7.8.1", "geoplanet:7.9.0", "geoplanet:7.10.0", "geoplanet:8.0.0", "woeplanet:8.0.0"], "meta:indexed": "2020-08-20T20:54:07.723143", "meta:updated": "2020-10-14T11:52:11.407284", "woe:alias_FRE_V": ["Faculte des Sciences Jean Perrin"], "woe:hierarchy": {"continent": 24865675, "country": 23424819, "town": 0, "planet": 1, "county": 12597181, "suburb": 0, "state": 7153324, "region": 0, "localadmin": 12665249}, "woe:timezone_id": 28350911, "woe:hash": "u0fnbm2ccfyr", "woe:centroid": [2.8246, 50.434429], "geom:latitude": 50.434429, "geom:longitude": 2.8246, "geom:hash": "u0fnbm2ccfyr", "woe:latitude": 50.434429, "geom:centroid": [2.8246, 50.434429], "woe:longitude": 2.8246, "woe:repo": "woeplanet-poi-fr", "geom:area": 0.0, "woe:scale": 19}}