{"type": "Feature", "id": 22891945, "geometry": {"type": "Point", "coordinates": [6.02251, 47.24715]}, "properties": {"woe:id": 22891945, "woe:parent_id": 579560, "woe:name": "Gare de Besan\u00e7on-Viotte", "woe:placetype": 20, "woe:placetype_name": "POI", "woe:lang": "FRE", "iso:country": "FR", "meta:provider": ["geoplanet:7.3.1", "geoplanet:7.3.2", "geoplanet:7.4.0", "geoplanet:7.4.1", "geoplanet:7.5.1", "geoplanet:7.5.2", "geoplanet:7.6.0", "geoplanet:7.8.1", "geoplanet:7.9.0", "geoplanet:7.10.0", "geoplanet:8.0.0", "woeplanet:8.0.0"], "meta:indexed": "2020-08-20T20:54:05.995772", "woe:alias_ENG_V": ["Besancon-Viotte Railway Station"], "woe:alias_ENG_P": ["Besancon-Viotte Station"], "meta:updated": "2020-10-14T11:52:12.148191", "woe:alias_FRE_S": ["Gare Besancon-Viotte", "Gare Besancon", "Gare de Besancon-Viotte", "Gare de Besancon"], "woe:alias_FRE_V": ["Gare Besan\u00e7on", "Gare de Besan\u00e7on", "Gare Besan\u00e7on-Viotte"], "woe:hierarchy": {"continent": 24865675, "country": 23424819, "town": 0, "planet": 1, "county": 12597116, "suburb": 0, "state": 7153317, "region": 0, "localadmin": 12638478}, "woe:timezone_id": 28350911, "woe:hash": "u0kkc116wehg", "woe:centroid": [6.02251, 47.24715], "geom:latitude": 47.24715, "geom:longitude": 6.02251, "geom:hash": "u0kkc116wehg", "woe:latitude": 47.24715, "geom:centroid": [6.02251, 47.24715], "woe:longitude": 6.02251, "woe:repo": "woeplanet-poi-fr", "geom:area": 0.0, "woe:scale": 19}}