{"type": "Feature", "id": 55863177, "properties": {"woe:id": 55863177, "woe:parent_id": 613082, "woe:name": "Gare de Montrichard", "woe:placetype": 20, "woe:placetype_name": "POI", "woe:lang": "FRE", "iso:country": "FR", "meta:provider": ["geoplanet:7.3.1", "geoplanet:7.3.2", "geoplanet:7.4.0", "geoplanet:7.4.1", "geoplanet:7.5.1", "geoplanet:7.5.2", "geoplanet:7.6.0", "geoplanet:7.8.1", "geoplanet:7.9.0", "geoplanet:7.10.0", "geoplanet:8.0.0", "woeplanet:8.0.0"], "meta:indexed": "2020-08-20T20:54:07.388964", "woe:alias_ENG_V": ["Montrichard Railway Station"], "meta:updated": "2020-08-22T01:53:30.012169", "woe:alias_ENG_P": ["Montrichard Station"], "woe:alias_FRE_V": ["Montrichard", "Gare Montrichard"], "woe:hierarchy": {"continent": 24865675, "country": 23424819, "town": 0, "planet": 1, "county": 12597147, "suburb": 0, "state": 7153314, "region": 0, "localadmin": 12649616}, "woe:timezone_id": 28350911, "woe:hash": "u02v6dt5pv8n", "woe:centroid": [1.17175, 47.34338], "geom:latitude": 47.34338, "geom:longitude": 1.17175, "geom:hash": "u02v6dt5pv8n", "woe:latitude": 47.34338, "geom:centroid": [1.17175, 47.34338], "woe:longitude": 1.17175, "woe:repo": "woeplanet-poi-fr"}, "geometry": {"coordinates": [1.17175, 47.34338], "type": "Point"}}