{"type": "Feature", "id": 22918906, "geometry": {"type": "Point", "coordinates": [2.42122, 49.117031]}, "properties": {"woe:id": 22918906, "woe:parent_id": 609096, "woe:name": "SNCF-Luzarches", "woe:placetype": 20, "woe:placetype_name": "POI", "woe:lang": "FRE", "iso:country": "FR", "meta:provider": ["geoplanet:7.3.1", "geoplanet:7.3.2", "geoplanet:7.4.0", "geoplanet:7.4.1", "geoplanet:7.5.1", "geoplanet:7.5.2", "geoplanet:7.6.0", "geoplanet:7.8.1", "geoplanet:7.9.0", "geoplanet:7.10.0", "geoplanet:8.0.0", "woeplanet:8.0.0"], "meta:indexed": "2020-08-20T20:54:07.033719", "woe:alias_ENG_V": ["Luzarches Railway Station"], "meta:updated": "2020-10-14T11:52:05.944598", "woe:alias_ENG_P": ["Luzarches Station"], "woe:alias_FRE_V": ["Gare du Luzarches", "Gare Luzarches"], "woe:hierarchy": {"continent": 24865675, "country": 23424819, "town": 0, "planet": 1, "county": 12597124, "suburb": 0, "state": 7153319, "region": 0, "localadmin": 12648537}, "woe:timezone_id": 28350911, "woe:hash": "u09xrj7p6w0q", "woe:centroid": [2.42122, 49.117031], "geom:latitude": 49.117031, "geom:longitude": 2.42122, "geom:hash": "u09xrj7p6w0q", "woe:latitude": 49.117031, "geom:centroid": [2.42122, 49.117031], "woe:longitude": 2.42122, "woe:repo": "woeplanet-poi-fr", "geom:area": 0.0, "woe:scale": 19}}