{"type": "Feature", "id": 22874636, "properties": {"woe:id": 22874636, "woe:parent_id": 622711, "woe:name": "Gare de Saint-Andr\u00e9 de Cubzac", "woe:placetype": 20, "woe:placetype_name": "POI", "woe:lang": "FRE", "iso:country": "FR", "meta:provider": ["geoplanet:7.3.1", "geoplanet:7.3.2", "geoplanet:7.4.0", "geoplanet:7.4.1", "geoplanet:7.5.1", "geoplanet:7.5.2", "geoplanet:7.6.0", "geoplanet:7.8.1", "geoplanet:7.9.0", "geoplanet:7.10.0", "geoplanet:8.0.0", "woeplanet:8.0.0"], "meta:indexed": "2020-08-20T20:54:05.574084", "woe:alias_ENG_V": ["Saint-Andre de Cubzac Railway Station"], "woe:alias_ENG_P": ["Saint-Andre de Cubzac Station"], "meta:updated": "2020-08-22T01:53:29.340741", "woe:alias_FRE_S": ["Gare Saint-Andre de Cubzac", "Gare Saint-Andre-de-Cubzac", "Gare de Saint-Andre de Cubzac", "Gare de Saint-Andre-de-Cubzac"], "woe:alias_FRE_V": ["Gare Saint-Andr\u00e9-de-Cubzac", "Gare de Saint-Andr\u00e9-de-Cubzac", "Gare Saint-Andr\u00e9 de Cubzac"], "woe:hierarchy": {"continent": 24865675, "country": 23424819, "town": 0, "planet": 1, "county": 12597132, "suburb": 0, "state": 7153309, "region": 0, "localadmin": 12652110}, "woe:timezone_id": 28350911, "woe:hash": "ezzxvyqtpfbm", "woe:centroid": [-0.44118, 44.991261], "geom:latitude": 44.991261, "geom:longitude": -0.44118, "geom:hash": "ezzxvyqtpfbm", "woe:latitude": 44.991261, "geom:centroid": [-0.44118, 44.991261], "woe:longitude": -0.44118, "woe:repo": "woeplanet-poi-fr"}, "geometry": {"coordinates": [-0.44118, 44.991261], "type": "Point"}}