{"type": "Feature", "id": 22139961, "geometry": {"type": "Point", "coordinates": [1.53235, 43.530701]}, "properties": {"woe:id": 22139961, "woe:parent_id": 600591, "woe:name": "Gare de Lab\u00e8ge", "woe:placetype": 20, "woe:placetype_name": "POI", "woe:lang": "FRE", "iso:country": "FR", "meta:provider": ["geoplanet:7.3.1", "geoplanet:7.3.2", "geoplanet:7.4.0", "geoplanet:7.4.1", "geoplanet:7.5.1", "geoplanet:7.5.2", "geoplanet:7.6.0", "geoplanet:7.8.1", "geoplanet:7.9.0", "geoplanet:7.10.0", "geoplanet:8.0.0", "woeplanet:8.0.0"], "meta:indexed": "2020-08-20T20:54:04.857394", "woe:alias_ENG_V": ["Labege Railway Station"], "woe:alias_ENG_P": ["Labege Station"], "meta:updated": "2020-10-14T11:52:05.433976", "woe:alias_FRE_S": ["Gare de Labege", "Gare Labege"], "woe:alias_FRE_V": ["Gare Lab\u00e8ge"], "woe:hierarchy": {"continent": 24865675, "country": 23424819, "town": 0, "planet": 1, "county": 12597186, "suburb": 0, "state": 7153323, "region": 0, "localadmin": 12664166}, "woe:timezone_id": 28350911, "woe:hash": "sp9pduebdqff", "woe:centroid": [1.53235, 43.530701], "geom:latitude": 43.530701, "geom:longitude": 1.53235, "geom:hash": "sp9pduebdqff", "woe:latitude": 43.530701, "geom:centroid": [1.53235, 43.530701], "woe:longitude": 1.53235, "woe:repo": "woeplanet-poi-fr", "geom:area": 0.0, "woe:scale": 19}}