{"type": "Feature", "id": 56060247, "geometry": {"type": "Point", "coordinates": [2.3438, 48.841511]}, "properties": {"woe:id": 56060247, "woe:parent_id": 55843767, "woe:name": "\u00c9cole Normale Sup\u00e9rieure", "woe:placetype": 20, "woe:placetype_name": "POI", "woe:lang": "FRE", "iso:country": "FR", "meta:provider": ["geoplanet:7.3.1", "geoplanet:7.3.2", "geoplanet:7.4.0", "geoplanet:7.4.1", "geoplanet:7.5.1", "geoplanet:7.5.2", "geoplanet:7.6.0", "geoplanet:7.8.1", "geoplanet:7.9.0", "geoplanet:7.10.0", "geoplanet:8.0.0", "woeplanet:8.0.0"], "meta:indexed": "2020-08-20T20:54:07.844154", "meta:updated": "2020-10-14T11:52:11.139053", "woe:alias_FRE_V": ["Ecole Normale Superieure"], "woe:hierarchy": {"continent": 24865675, "country": 23424819, "town": 0, "planet": 1, "county": 12597155, "suburb": 0, "state": 7153319, "region": 0, "localadmin": 12652969}, "woe:timezone_id": 28350911, "woe:hash": "u09tv76dqmxc", "woe:centroid": [2.3438, 48.841511], "geom:latitude": 48.841511, "geom:longitude": 2.3438, "geom:hash": "u09tv76dqmxc", "woe:latitude": 48.841511, "geom:centroid": [2.3438, 48.841511], "woe:longitude": 2.3438, "woe:repo": "woeplanet-poi-fr", "geom:area": 0.0, "woe:scale": 19}}