{"type": "Feature", "id": 22899817, "properties": {"woe:id": 22899817, "woe:parent_id": 627617, "woe:name": "Ferme Musee de la Soyotte", "woe:placetype": 20, "woe:placetype_name": "POI", "woe:lang": "FRE", "iso:country": "FR", "meta:provider": ["geoplanet:7.3.1", "geoplanet:7.3.2", "geoplanet:7.4.0", "geoplanet:7.4.1", "geoplanet:7.5.1", "geoplanet:7.5.2", "geoplanet:7.6.0", "geoplanet:7.8.1", "geoplanet:7.9.0", "geoplanet:7.10.0", "geoplanet:8.0.0", "woeplanet:8.0.0"], "meta:indexed": "2020-08-20T20:54:06.251148", "meta:updated": "2020-08-22T01:53:29.606938", "woe:hierarchy": {"continent": 24865675, "country": 23424819, "town": 0, "planet": 1, "county": 12597174, "suburb": 0, "state": 7153322, "region": 0, "localadmin": 12671424}, "woe:timezone_id": 28350911, "woe:hash": "u0sfw7rx188h", "woe:centroid": [6.96471, 48.271011], "geom:latitude": 48.271011, "geom:longitude": 6.96471, "geom:hash": "u0sfw7rx188h", "woe:latitude": 48.271011, "geom:centroid": [6.96471, 48.271011], "woe:longitude": 6.96471, "woe:repo": "woeplanet-poi-fr"}, "geometry": {"coordinates": [6.96471, 48.271011], "type": "Point"}}