{"type": "Feature", "id": 22140618, "properties": {"woe:id": 22140618, "woe:parent_id": 604756, "woe:name": "Gare de le Tr\u00e9port", "woe:placetype": 20, "woe:placetype_name": "POI", "woe:lang": "FRE", "iso:country": "FR", "meta:provider": ["geoplanet:7.3.1", "geoplanet:7.3.2", "geoplanet:7.4.0", "geoplanet:7.4.1", "geoplanet:7.5.1", "geoplanet:7.5.2", "geoplanet:7.6.0", "geoplanet:7.8.1", "geoplanet:7.9.0", "geoplanet:7.10.0", "geoplanet:8.0.0", "woeplanet:8.0.0"], "meta:indexed": "2020-08-20T20:54:04.882941", "woe:alias_ENG_V": ["Le Treport Railway Station"], "woe:alias_ENG_P": ["Le Treport Station"], "meta:updated": "2020-08-22T01:53:29.066317", "woe:alias_FRE_S": ["Gare le Treport", "Gare Mers le Treport", "Gare de le Treport", "Gare de Mers le Treport"], "woe:alias_FRE_V": ["Gare Mers le Tr\u00e9port", "Gare de Mers le Tr\u00e9port", "Gare le Tr\u00e9port"], "woe:hierarchy": {"continent": 24865675, "country": 23424819, "town": 0, "planet": 1, "county": 12597115, "suburb": 0, "state": 7153318, "region": 0, "localadmin": 12647495}, "woe:timezone_id": 28350911, "woe:hash": "u0buz39g9j64", "woe:centroid": [1.37574, 50.06258], "geom:latitude": 50.06258, "geom:longitude": 1.37574, "geom:hash": "u0buz39g9j64", "woe:latitude": 50.06258, "geom:centroid": [1.37574, 50.06258], "woe:longitude": 1.37574, "woe:repo": "woeplanet-poi-fr"}, "geometry": {"coordinates": [1.37574, 50.06258], "type": "Point"}}