{"type": "Feature", "id": 22919281, "geometry": {"type": "Point", "coordinates": [2.3979, 49.118839]}, "properties": {"woe:id": 22919281, "woe:parent_id": 622039, "woe:name": "SNCF-Seugy", "woe:placetype": 20, "woe:placetype_name": "POI", "woe:lang": "FRE", "iso:country": "FR", "meta:provider": ["geoplanet:7.3.1", "geoplanet:7.3.2", "geoplanet:7.4.0", "geoplanet:7.4.1", "geoplanet:7.5.1", "geoplanet:7.5.2", "geoplanet:7.6.0", "geoplanet:7.8.1", "geoplanet:7.9.0", "geoplanet:7.10.0", "geoplanet:8.0.0", "woeplanet:8.0.0"], "meta:indexed": "2020-08-20T20:54:07.042683", "woe:alias_ENG_V": ["Seugy Railway Station"], "meta:updated": "2020-10-14T11:52:06.219118", "woe:alias_ENG_P": ["Seugy Station"], "woe:alias_FRE_V": ["Gare du Seugy", "Gare Seugy"], "woe:hierarchy": {"continent": 24865675, "country": 23424819, "town": 0, "planet": 1, "county": 12597124, "suburb": 0, "state": 7153319, "region": 0, "localadmin": 12651934}, "woe:timezone_id": 28350911, "woe:hash": "u09xqtf1gp5z", "woe:centroid": [2.3979, 49.118839], "geom:latitude": 49.118839, "geom:longitude": 2.3979, "geom:hash": "u09xqtf1gp5z", "woe:latitude": 49.118839, "geom:centroid": [2.3979, 49.118839], "woe:longitude": 2.3979, "woe:repo": "woeplanet-poi-fr", "geom:area": 0.0, "woe:scale": 19}}