{"type": "Feature", "id": 56059995, "properties": {"woe:id": 56059995, "woe:parent_id": 609125, "woe:name": "Univ. Lyon 3-Jean Moulin", "woe:placetype": 20, "woe:placetype_name": "POI", "woe:lang": "FRE", "iso:country": "FR", "meta:provider": ["geoplanet:7.3.1", "geoplanet:7.3.2", "geoplanet:7.4.0", "geoplanet:7.4.1", "geoplanet:7.5.1", "geoplanet:7.5.2", "geoplanet:7.6.0", "geoplanet:7.8.1", "geoplanet:7.9.0", "geoplanet:7.10.0", "geoplanet:8.0.0", "woeplanet:8.0.0"], "meta:indexed": "2020-08-20T20:54:07.622540", "meta:updated": "2020-08-22T01:53:30.097851", "woe:hierarchy": {"continent": 24865675, "country": 23424819, "town": 0, "planet": 1, "county": 12597185, "suburb": 0, "state": 7153329, "region": 0, "localadmin": 24865738}, "woe:timezone_id": 28350911, "woe:hash": "u05kq0fm9c03", "woe:centroid": [4.83715, 45.75214], "geom:latitude": 45.75214, "geom:longitude": 4.83715, "geom:hash": "u05kq0fm9c03", "woe:latitude": 45.75214, "geom:centroid": [4.83715, 45.75214], "woe:longitude": 4.83715, "woe:repo": "woeplanet-poi-fr"}, "geometry": {"coordinates": [4.83715, 45.75214], "type": "Point"}}