{"type": "Feature", "id": 22145482, "geometry": {"type": "Point", "coordinates": [4.82465, 45.70657]}, "properties": {"woe:id": 22145482, "woe:parent_id": 616523, "woe:name": "Gare de Pierre-B\u00e9nite", "woe:placetype": 20, "woe:placetype_name": "POI", "woe:lang": "FRE", "iso:country": "FR", "meta:provider": ["geoplanet:7.3.1", "geoplanet:7.3.2", "geoplanet:7.4.0", "geoplanet:7.4.1", "geoplanet:7.5.1", "geoplanet:7.5.2", "geoplanet:7.6.0", "geoplanet:7.8.1", "geoplanet:7.9.0", "geoplanet:7.10.0", "geoplanet:8.0.0", "woeplanet:8.0.0"], "meta:indexed": "2020-08-20T20:54:05.085799", "woe:alias_ENG_V": ["Pierre-Benite Railway Station"], "woe:alias_ENG_P": ["Pierre-Benite Station"], "meta:updated": "2020-10-14T11:52:05.192915", "woe:alias_FRE_S": ["Gare de Pierre-Benite", "Gare Pierre-Benite"], "woe:alias_FRE_V": ["Gare Pierre-B\u00e9nite"], "woe:hierarchy": {"continent": 24865675, "country": 23424819, "town": 0, "planet": 1, "county": 12597185, "suburb": 0, "state": 7153329, "region": 0, "localadmin": 22757214}, "woe:timezone_id": 28350911, "woe:hash": "u05kjb9hn6py", "woe:centroid": [4.82465, 45.70657], "geom:latitude": 45.70657, "geom:longitude": 4.82465, "geom:hash": "u05kjb9hn6py", "woe:latitude": 45.70657, "geom:centroid": [4.82465, 45.70657], "woe:longitude": 4.82465, "woe:repo": "woeplanet-poi-fr", "geom:area": 0.0, "woe:scale": 19}}