{"type": "Feature", "id": 22874738, "geometry": {"type": "Point", "coordinates": [-0.5917, 44.80912]}, "properties": {"woe:id": 22874738, "woe:parent_id": 627985, "woe:name": "Universit\u00e9 Bordeaux I", "woe:placetype": 20, "woe:placetype_name": "POI", "woe:lang": "FRE", "iso:country": "FR", "meta:provider": ["geoplanet:7.3.1", "geoplanet:7.3.2", "geoplanet:7.4.0", "geoplanet:7.4.1", "geoplanet:7.5.1", "geoplanet:7.5.2", "geoplanet:7.6.0", "geoplanet:7.8.1", "geoplanet:7.9.0", "geoplanet:7.10.0", "geoplanet:8.0.0", "woeplanet:8.0.0"], "meta:indexed": "2020-08-20T20:54:05.582198", "meta:updated": "2020-10-14T11:52:12.176419", "woe:alias_FRE_S": ["Universite Bordeaux I"], "woe:alias_FRE_V": ["Univ. de Bordeaux 1", "Facult\u00e9 des Sciences", "Faculte des Sciences"], "woe:hierarchy": {"continent": 24865675, "country": 23424819, "town": 0, "planet": 1, "county": 12597132, "suburb": 0, "state": 7153309, "region": 0, "localadmin": 12653515}, "woe:timezone_id": 28350911, "woe:hash": "ezzwft30h3ks", "woe:centroid": [-0.5917, 44.80912], "geom:latitude": 44.80912, "geom:longitude": -0.5917, "geom:hash": "ezzwft30h3ks", "woe:latitude": 44.80912, "geom:centroid": [-0.5917, 44.80912], "woe:longitude": -0.5917, "woe:repo": "woeplanet-poi-fr", "geom:area": 0.0, "woe:scale": 19}}