{"type": "Feature", "id": 22146194, "properties": {"woe:id": 22146194, "woe:parent_id": 619217, "woe:name": "Gare de Rethal", "woe:placetype": 20, "woe:placetype_name": "POI", "woe:lang": "FRE", "iso:country": "FR", "meta:provider": ["geoplanet:7.3.1", "geoplanet:7.3.2", "geoplanet:7.4.0", "geoplanet:7.4.1", "geoplanet:7.5.1", "geoplanet:7.5.2", "geoplanet:7.6.0", "geoplanet:7.8.1", "geoplanet:7.9.0", "geoplanet:7.10.0", "geoplanet:8.0.0", "woeplanet:8.0.0"], "meta:indexed": "2020-08-20T20:54:05.118688", "woe:alias_ENG_V": ["Rethal Railway Station"], "meta:updated": "2020-08-22T01:53:29.157537", "woe:alias_ENG_P": ["Rethal Station"], "woe:alias_FRE_V": ["Gare Rethel", "Gare de Rethel", "Gare Rethal"], "woe:hierarchy": {"continent": 24865675, "country": 23424819, "town": 0, "planet": 1, "county": 12597142, "suburb": 0, "state": 7153315, "region": 0, "localadmin": 12650412}, "woe:timezone_id": 28350911, "woe:hash": "u0g1ekj9128w", "woe:centroid": [4.36918, 49.50457], "geom:latitude": 49.50457, "geom:longitude": 4.36918, "geom:hash": "u0g1ekj9128w", "woe:latitude": 49.50457, "geom:centroid": [4.36918, 49.50457], "woe:longitude": 4.36918, "woe:repo": "woeplanet-poi-fr"}, "geometry": {"coordinates": [4.36918, 49.50457], "type": "Point"}}