{"type": "Feature", "id": 22135625, "properties": {"woe:id": 22135625, "woe:parent_id": 582041, "woe:name": "Gare de Brive la Gaillarde", "woe:placetype": 20, "woe:placetype_name": "POI", "woe:lang": "FRE", "iso:country": "FR", "meta:provider": ["geoplanet:7.3.1", "geoplanet:7.3.2", "geoplanet:7.4.0", "geoplanet:7.4.1", "geoplanet:7.5.1", "geoplanet:7.5.2", "geoplanet:7.6.0", "geoplanet:7.8.1", "geoplanet:7.9.0", "geoplanet:7.10.0", "geoplanet:8.0.0", "woeplanet:8.0.0"], "meta:indexed": "2020-08-20T20:54:04.682143", "woe:alias_ENG_V": ["Brive la Gaillarde Railway Station"], "meta:updated": "2020-08-22T01:53:28.982602", "woe:alias_ENG_P": ["Brive la Gaillarde Station"], "woe:alias_FRE_V": ["Gare Brive-la-Gaillarde", "Gare de Brive-la-Gaillarde", "Gare Brive la Gaillarde"], "woe:hierarchy": {"continent": 24865675, "country": 23424819, "town": 0, "planet": 1, "county": 12597163, "suburb": 0, "state": 7153321, "region": 0, "localadmin": 12656710}, "woe:timezone_id": 28350911, "woe:hash": "u010fgc44dp7", "woe:centroid": [1.52859, 45.15279], "geom:latitude": 45.15279, "geom:longitude": 1.52859, "geom:hash": "u010fgc44dp7", "woe:latitude": 45.15279, "geom:centroid": [1.52859, 45.15279], "woe:longitude": 1.52859, "woe:repo": "woeplanet-poi-fr"}, "geometry": {"coordinates": [1.52859, 45.15279], "type": "Point"}}