{"type": "Feature", "id": 22879558, "geometry": {"type": "Point", "coordinates": [7.18826, 43.820789]}, "properties": {"woe:id": 22879558, "woe:parent_id": 625708, "woe:name": "Gare de Saint-Martin-du-Var", "woe:placetype": 20, "woe:placetype_name": "POI", "woe:lang": "FRE", "iso:country": "FR", "meta:provider": ["geoplanet:7.3.1", "geoplanet:7.3.2", "geoplanet:7.4.0", "geoplanet:7.4.1", "geoplanet:7.5.1", "geoplanet:7.5.2", "geoplanet:7.6.0", "geoplanet:7.8.1", "geoplanet:7.9.0", "geoplanet:7.10.0", "geoplanet:8.0.0", "woeplanet:8.0.0"], "meta:indexed": "2020-08-20T20:54:05.689550", "woe:alias_ENG_V": ["Saint-Martin-du-Var Railway Station"], "meta:updated": "2020-10-14T11:52:12.229075", "woe:alias_ENG_P": ["Saint-Martin-du-Var Station"], "woe:alias_FRE_V": ["Gare Saint-Martin-du-Var"], "woe:hierarchy": {"continent": 24865675, "country": 23424819, "town": 0, "planet": 1, "county": 12591800, "suburb": 0, "state": 7153328, "region": 0, "localadmin": 22757753}, "woe:timezone_id": 28350911, "woe:hash": "spv17966de5h", "woe:centroid": [7.18826, 43.820789], "geom:latitude": 43.820789, "geom:longitude": 7.18826, "geom:hash": "spv17966de5h", "woe:latitude": 43.820789, "geom:centroid": [7.18826, 43.820789], "woe:longitude": 7.18826, "woe:repo": "woeplanet-poi-fr", "geom:area": 0.0, "woe:scale": 19}}