{"type": "Feature", "id": 22142860, "geometry": {"type": "Point", "coordinates": [2.19794, 49.00758]}, "properties": {"woe:id": 22142860, "woe:parent_id": 55863423, "woe:name": "RER-Montigny-Beauchamp", "woe:placetype": 20, "woe:placetype_name": "POI", "woe:lang": "FRE", "iso:country": "FR", "meta:provider": ["geoplanet:7.3.1", "geoplanet:7.3.2", "geoplanet:7.4.0", "geoplanet:7.4.1", "geoplanet:7.5.1", "geoplanet:7.5.2", "geoplanet:7.6.0", "geoplanet:7.8.1", "geoplanet:7.9.0", "geoplanet:7.10.0", "geoplanet:8.0.0", "woeplanet:8.0.0"], "meta:indexed": "2020-08-20T20:54:04.984894", "woe:alias_ENG_V": ["Montigny-Beauchamp Railway Station"], "meta:updated": "2020-10-14T11:52:05.218309", "woe:alias_ENG_P": ["Montigny-Beauchamp Station"], "woe:alias_FRE_V": ["Gare de Montigny-Beauchamp", "Gare Montigny-Beauchamp"], "woe:hierarchy": {"continent": 24865675, "country": 23424819, "town": 0, "planet": 1, "county": 12597124, "suburb": 0, "state": 7153319, "region": 0, "localadmin": 12638327}, "woe:timezone_id": 28350911, "woe:hash": "u09wf183zenc", "woe:centroid": [2.19794, 49.00758], "geom:latitude": 49.00758, "geom:longitude": 2.19794, "geom:hash": "u09wf183zenc", "woe:latitude": 49.00758, "geom:centroid": [2.19794, 49.00758], "woe:longitude": 2.19794, "woe:repo": "woeplanet-poi-fr", "geom:area": 0.0, "woe:scale": 19}}