{"type": "Feature", "id": 22870036, "properties": {"woe:id": 22870036, "woe:parent_id": 620108, "woe:name": "M\u00e9tro-Joffre Mutualit\u00e9", "woe:placetype": 20, "woe:placetype_name": "POI", "woe:lang": "FRE", "iso:country": "FR", "meta:provider": ["geoplanet:7.3.1", "geoplanet:7.3.2", "geoplanet:7.4.0", "geoplanet:7.4.1", "geoplanet:7.5.1", "geoplanet:7.5.2", "geoplanet:7.6.0", "geoplanet:7.8.1", "geoplanet:7.9.0", "geoplanet:7.10.0", "geoplanet:8.0.0", "woeplanet:8.0.0"], "meta:indexed": "2020-08-20T20:54:05.441589", "meta:updated": "2020-08-22T01:53:29.289986", "woe:alias_ENG_P": ["Joffre Mutualite Metro Station"], "woe:alias_FRE_S": ["Metro-Joffre Mutualite"], "woe:hierarchy": {"continent": 24865675, "country": 23424819, "town": 0, "planet": 1, "county": 12597115, "suburb": 0, "state": 7153318, "region": 0, "localadmin": 12638064}, "woe:timezone_id": 28350911, "woe:hash": "u0bc0xnwqy6c", "woe:centroid": [1.08588, 49.43409], "geom:latitude": 49.43409, "geom:longitude": 1.08588, "geom:hash": "u0bc0xnwqy6c", "woe:latitude": 49.43409, "geom:centroid": [1.08588, 49.43409], "woe:longitude": 1.08588, "woe:repo": "woeplanet-poi-fr"}, "geometry": {"coordinates": [1.08588, 49.43409], "type": "Point"}}