{"type": "Feature", "id": 22888051, "properties": {"woe:id": 22888051, "woe:parent_id": 586242, "woe:name": "Parc des Sports Marcel Michelin", "woe:placetype": 20, "woe:placetype_name": "POI", "woe:lang": "FRE", "iso:country": "FR", "meta:provider": ["geoplanet:7.3.1", "geoplanet:7.3.2", "geoplanet:7.4.0", "geoplanet:7.4.1", "geoplanet:7.5.1", "geoplanet:7.5.2", "geoplanet:7.6.0", "geoplanet:7.8.1", "geoplanet:7.9.0", "geoplanet:7.10.0", "geoplanet:8.0.0", "woeplanet:8.0.0"], "meta:indexed": "2020-08-20T20:54:05.884356", "meta:updated": "2020-08-22T01:53:29.461251", "woe:hierarchy": {"continent": 24865675, "country": 23424819, "town": 0, "planet": 1, "county": 12597146, "suburb": 0, "state": 7153310, "region": 0, "localadmin": 12641742}, "woe:timezone_id": 28350911, "woe:hash": "u04hqxtvu6hz", "woe:centroid": [3.10623, 45.789268], "geom:latitude": 45.789268, "geom:longitude": 3.10623, "geom:hash": "u04hqxtvu6hz", "woe:latitude": 45.789268, "geom:centroid": [3.10623, 45.789268], "woe:longitude": 3.10623, "woe:repo": "woeplanet-poi-fr"}, "geometry": {"coordinates": [3.10623, 45.789268], "type": "Point"}}