{"type": "Feature", "id": 55863248, "geometry": {"type": "Point", "coordinates": [2.06969, 48.894939]}, "properties": {"woe:id": 55863248, "woe:parent_id": 624330, "woe:name": "SNCF-Saint-Germain-Bel-Air", "woe:placetype": 20, "woe:placetype_name": "POI", "woe:lang": "FRE", "iso:country": "FR", "meta:provider": ["geoplanet:7.3.1", "geoplanet:7.3.2", "geoplanet:7.4.0", "geoplanet:7.4.1", "geoplanet:7.5.1", "geoplanet:7.5.2", "geoplanet:7.6.0", "geoplanet:7.8.1", "geoplanet:7.9.0", "geoplanet:7.10.0", "geoplanet:8.0.0", "woeplanet:8.0.0"], "meta:indexed": "2020-08-20T20:54:07.448296", "woe:alias_ENG_V": ["Saint-Germain-Bel-Air Railway Station"], "meta:updated": "2020-10-14T11:52:04.834657", "woe:alias_ENG_P": ["Saint-Germain-Bel-Air Station"], "woe:alias_FRE_V": ["Gare du Saint-Germain-Bel-Air", "Gare Saint-Germain-Bel-Air"], "woe:hierarchy": {"continent": 24865675, "country": 23424819, "town": 0, "planet": 1, "county": 12597126, "suburb": 0, "state": 7153319, "region": 0, "localadmin": 12652533}, "woe:timezone_id": 28350911, "woe:hash": "u09qpj51em28", "woe:centroid": [2.06969, 48.894939], "geom:latitude": 48.894939, "geom:longitude": 2.06969, "geom:hash": "u09qpj51em28", "woe:latitude": 48.894939, "geom:centroid": [2.06969, 48.894939], "woe:longitude": 2.06969, "woe:repo": "woeplanet-poi-fr", "geom:area": 0.0, "woe:scale": 19}}