{"type": "Feature", "id": 22142112, "geometry": {"type": "Point", "coordinates": [5.39271, 43.323349]}, "properties": {"woe:id": 22142112, "woe:parent_id": 24865754, "woe:name": "Gare de Saint Barthelemy", "woe:placetype": 20, "woe:placetype_name": "POI", "woe:lang": "FRE", "iso:country": "FR", "meta:provider": ["geoplanet:7.3.1", "geoplanet:7.3.2", "geoplanet:7.4.0", "geoplanet:7.4.1", "geoplanet:7.5.1", "geoplanet:7.5.2", "geoplanet:7.6.0", "geoplanet:7.8.1", "geoplanet:7.9.0", "geoplanet:7.10.0", "geoplanet:8.0.0", "woeplanet:8.0.0"], "meta:indexed": "2020-08-20T20:54:04.949224", "woe:alias_ENG_V": ["Saint Barthelemy Railway Station"], "meta:updated": "2020-10-14T11:52:05.315719", "woe:alias_ENG_P": ["Saint Barthelemy Station"], "woe:alias_FRE_V": ["Gare Saint Barthelemy"], "woe:hierarchy": {"continent": 24865675, "country": 23424819, "town": 0, "planet": 1, "county": 12597199, "suburb": 0, "state": 7153328, "region": 0, "localadmin": 24865754}, "woe:timezone_id": 28350911, "woe:hash": "spey6wybg385", "woe:centroid": [5.39271, 43.323349], "geom:latitude": 43.323349, "geom:longitude": 5.39271, "geom:hash": "spey6wybg385", "woe:latitude": 43.323349, "geom:centroid": [5.39271, 43.323349], "woe:longitude": 5.39271, "woe:repo": "woeplanet-poi-fr", "geom:area": 0.0, "woe:scale": 19}}