{"type": "Feature", "id": 22886917, "properties": {"woe:id": 22886917, "woe:parent_id": 604235, "woe:name": "Gare de Pont de Beauvoisin", "woe:placetype": 20, "woe:placetype_name": "POI", "woe:lang": "FRE", "iso:country": "FR", "meta:provider": ["geoplanet:7.3.1", "geoplanet:7.3.2", "geoplanet:7.4.0", "geoplanet:7.4.1", "geoplanet:7.5.1", "geoplanet:7.5.2", "geoplanet:7.6.0", "geoplanet:7.8.1", "geoplanet:7.9.0", "geoplanet:7.10.0", "geoplanet:8.0.0", "woeplanet:8.0.0"], "meta:indexed": "2020-08-20T20:54:05.851093", "woe:alias_ENG_V": ["Pont de Beauvoisin Railway Station"], "meta:updated": "2020-08-22T01:53:29.450097", "woe:alias_ENG_P": ["Pont de Beauvoisin Station"], "woe:alias_FRE_V": ["Gare Pont de Beauvoisin"], "woe:hierarchy": {"continent": 24865675, "country": 23424819, "town": 0, "planet": 1, "county": 12597188, "suburb": 0, "state": 7153329, "region": 0, "localadmin": 20075136}, "woe:timezone_id": 28350911, "woe:hash": "u0h4cr3p2k50", "woe:centroid": [5.68132, 45.52449], "geom:latitude": 45.52449, "geom:longitude": 5.68132, "geom:hash": "u0h4cr3p2k50", "woe:latitude": 45.52449, "geom:centroid": [5.68132, 45.52449], "woe:longitude": 5.68132, "woe:repo": "woeplanet-poi-fr"}, "geometry": {"coordinates": [5.68132, 45.52449], "type": "Point"}}