{"type": "Feature", "id": 22892883, "properties": {"woe:id": 22892883, "woe:parent_id": 583959, "woe:name": "Musee du Cloitre Notre-Dame en Vaux", "woe:placetype": 20, "woe:placetype_name": "POI", "woe:lang": "FRE", "iso:country": "FR", "meta:provider": ["geoplanet:7.3.1", "geoplanet:7.3.2", "geoplanet:7.4.0", "geoplanet:7.4.1", "geoplanet:7.5.1", "geoplanet:7.5.2", "geoplanet:7.6.0", "geoplanet:7.8.1", "geoplanet:7.9.0", "geoplanet:7.10.0", "geoplanet:8.0.0", "woeplanet:8.0.0"], "meta:indexed": "2020-08-20T20:54:06.024343", "meta:updated": "2020-08-22T01:53:29.517656", "woe:hierarchy": {"continent": 24865675, "country": 23424819, "town": 0, "planet": 1, "county": 12597123, "suburb": 0, "state": 7153315, "region": 0, "localadmin": 12640804}, "woe:timezone_id": 28350911, "woe:hash": "u0ene29dd30u", "woe:centroid": [4.36373, 48.95826], "geom:latitude": 48.95826, "geom:longitude": 4.36373, "geom:hash": "u0ene29dd30u", "woe:latitude": 48.95826, "geom:centroid": [4.36373, 48.95826], "woe:longitude": 4.36373, "woe:repo": "woeplanet-poi-fr"}, "geometry": {"coordinates": [4.36373, 48.95826], "type": "Point"}}