{"type": "Feature", "id": 55863149, "geometry": {"type": "Point", "coordinates": [2.11259, 42.502361]}, "properties": {"woe:id": 55863149, "woe:parent_id": 597219, "woe:name": "Gare de la Cabanasse", "woe:placetype": 20, "woe:placetype_name": "POI", "woe:lang": "FRE", "iso:country": "FR", "meta:provider": ["geoplanet:7.3.1", "geoplanet:7.3.2", "geoplanet:7.4.0", "geoplanet:7.4.1", "geoplanet:7.5.1", "geoplanet:7.5.2", "geoplanet:7.6.0", "geoplanet:7.8.1", "geoplanet:7.9.0", "geoplanet:7.10.0", "geoplanet:8.0.0", "woeplanet:8.0.0"], "meta:indexed": "2020-08-20T20:54:07.365537", "woe:alias_ENG_V": ["La Cabanasse Railway Station"], "meta:updated": "2020-10-14T11:52:04.730839", "woe:alias_ENG_P": ["La Cabanasse Station"], "woe:alias_FRE_V": ["Gare la Cabanasse"], "woe:hierarchy": {"continent": 24865675, "country": 23424819, "town": 0, "planet": 1, "county": 12597201, "suburb": 0, "state": 7153320, "region": 0, "localadmin": 12663405}, "woe:timezone_id": 28350911, "woe:hash": "sp99b1664ym7", "woe:centroid": [2.11259, 42.502361], "geom:latitude": 42.502361, "geom:longitude": 2.11259, "geom:hash": "sp99b1664ym7", "woe:latitude": 42.502361, "geom:centroid": [2.11259, 42.502361], "woe:longitude": 2.11259, "woe:repo": "woeplanet-poi-fr", "geom:area": 0.0, "woe:scale": 19}}