{"type": "Feature", "id": 22887179, "properties": {"woe:id": 22887179, "woe:parent_id": 629522, "woe:name": "Gare de Tullins Fures", "woe:placetype": 20, "woe:placetype_name": "POI", "woe:lang": "FRE", "iso:country": "FR", "meta:provider": ["geoplanet:7.3.1", "geoplanet:7.3.2", "geoplanet:7.4.0", "geoplanet:7.4.1", "geoplanet:7.5.1", "geoplanet:7.5.2", "geoplanet:7.6.0", "geoplanet:7.8.1", "geoplanet:7.9.0", "geoplanet:7.10.0", "geoplanet:8.0.0", "woeplanet:8.0.0"], "meta:indexed": "2020-08-20T20:54:05.852849", "woe:alias_ENG_V": ["Tullins Fures Railway Station"], "meta:updated": "2020-08-22T01:53:29.450724", "woe:alias_ENG_P": ["Tullins Fures Station"], "woe:alias_FRE_V": ["Gare Tullins Fures"], "woe:hierarchy": {"continent": 24865675, "country": 23424819, "town": 0, "planet": 1, "county": 12597188, "suburb": 0, "state": 7153329, "region": 0, "localadmin": 12661880}, "woe:timezone_id": 28350911, "woe:hash": "u05csyz1p7qn", "woe:centroid": [5.49211, 45.300941], "geom:latitude": 45.300941, "geom:longitude": 5.49211, "geom:hash": "u05csyz1p7qn", "woe:latitude": 45.300941, "geom:centroid": [5.49211, 45.300941], "woe:longitude": 5.49211, "woe:repo": "woeplanet-poi-fr"}, "geometry": {"coordinates": [5.49211, 45.300941], "type": "Point"}}