{"type": "Feature", "id": 22898641, "geometry": {"type": "Point", "coordinates": [6.62223, 47.69838]}, "properties": {"woe:id": 22898641, "woe:parent_id": 619895, "woe:name": "Gare de Ronchamp", "woe:placetype": 20, "woe:placetype_name": "POI", "woe:lang": "FRE", "iso:country": "FR", "meta:provider": ["geoplanet:7.3.1", "geoplanet:7.3.2", "geoplanet:7.4.0", "geoplanet:7.4.1", "geoplanet:7.5.1", "geoplanet:7.5.2", "geoplanet:7.6.0", "geoplanet:7.8.1", "geoplanet:7.9.0", "geoplanet:7.10.0", "geoplanet:8.0.0", "woeplanet:8.0.0"], "meta:indexed": "2020-08-20T20:54:06.200260", "woe:alias_ENG_V": ["Ronchamp Railway Station"], "meta:updated": "2020-10-14T11:52:12.325109", "woe:alias_ENG_P": ["Ronchamp Station"], "woe:alias_FRE_V": ["Gare Ronchamp"], "woe:hierarchy": {"continent": 24865675, "country": 23424819, "town": 0, "planet": 1, "county": 12597119, "suburb": 0, "state": 7153317, "region": 0, "localadmin": 12651392}, "woe:timezone_id": 28350911, "woe:hash": "u0kxqenpjnkx", "woe:centroid": [6.62223, 47.69838], "geom:latitude": 47.69838, "geom:longitude": 6.62223, "geom:hash": "u0kxqenpjnkx", "woe:latitude": 47.69838, "geom:centroid": [6.62223, 47.69838], "woe:longitude": 6.62223, "woe:repo": "woeplanet-poi-fr", "geom:area": 0.0, "woe:scale": 19}}