{"type": "Feature", "id": 22892747, "geometry": {"type": "Point", "coordinates": [5.33438, 46.434132]}, "properties": {"woe:id": 22892747, "woe:parent_id": 622881, "woe:name": "Gare de Saint-Amour", "woe:placetype": 20, "woe:placetype_name": "POI", "woe:lang": "FRE", "iso:country": "FR", "meta:provider": ["geoplanet:7.3.1", "geoplanet:7.3.2", "geoplanet:7.4.0", "geoplanet:7.4.1", "geoplanet:7.5.1", "geoplanet:7.5.2", "geoplanet:7.6.0", "geoplanet:7.8.1", "geoplanet:7.9.0", "geoplanet:7.10.0", "geoplanet:8.0.0", "woeplanet:8.0.0"], "meta:indexed": "2020-08-20T20:54:06.022609", "woe:alias_ENG_V": ["Saint-Amour Railway Station"], "meta:updated": "2020-10-14T11:52:11.971374", "woe:alias_ENG_P": ["Saint-Amour Station"], "woe:alias_FRE_V": ["Gare Saint-Amour"], "woe:hierarchy": {"continent": 24865675, "country": 23424819, "town": 0, "planet": 1, "county": 12597120, "suburb": 0, "state": 7153317, "region": 0, "localadmin": 12652157}, "woe:timezone_id": 28350911, "woe:hash": "u07b1mh6kjd4", "woe:centroid": [5.33438, 46.434132], "geom:latitude": 46.434132, "geom:longitude": 5.33438, "geom:hash": "u07b1mh6kjd4", "woe:latitude": 46.434132, "geom:centroid": [5.33438, 46.434132], "woe:longitude": 5.33438, "woe:repo": "woeplanet-poi-fr", "geom:area": 0.0, "woe:scale": 19}}