{"type": "Feature", "id": 22872917, "geometry": {"type": "Point", "coordinates": [1.45071, 43.577171]}, "properties": {"woe:id": 22872917, "woe:parent_id": 628886, "woe:name": "Institut de Technologie des Transports Et", "woe:placetype": 20, "woe:placetype_name": "POI", "woe:lang": "FRE", "iso:country": "FR", "meta:provider": ["geoplanet:7.3.1", "geoplanet:7.3.2", "geoplanet:7.4.0", "geoplanet:7.4.1", "geoplanet:7.5.1", "geoplanet:7.5.2", "geoplanet:7.6.0", "geoplanet:7.8.1", "geoplanet:7.9.0", "geoplanet:7.10.0", "geoplanet:8.0.0", "woeplanet:8.0.0"], "meta:indexed": "2020-08-20T20:54:05.531714", "meta:updated": "2020-10-14T11:52:12.026287", "woe:hierarchy": {"continent": 24865675, "country": 23424819, "town": 0, "planet": 1, "county": 12597186, "suburb": 0, "state": 7153323, "region": 0, "localadmin": 12657325}, "woe:timezone_id": 28350911, "woe:hash": "sp9pchbr7vry", "woe:centroid": [1.45071, 43.577171], "geom:latitude": 43.577171, "geom:longitude": 1.45071, "geom:hash": "sp9pchbr7vry", "woe:latitude": 43.577171, "geom:centroid": [1.45071, 43.577171], "woe:longitude": 1.45071, "woe:repo": "woeplanet-poi-fr", "geom:area": 0.0, "woe:scale": 19}}