{"type": "Feature", "id": 22138170, "geometry": {"type": "Point", "coordinates": [6.987, 47.89761]}, "properties": {"woe:id": 22138170, "woe:parent_id": 590774, "woe:name": "Gare de Fellering", "woe:placetype": 20, "woe:placetype_name": "POI", "woe:lang": "FRE", "iso:country": "FR", "meta:provider": ["geoplanet:7.3.1", "geoplanet:7.3.2", "geoplanet:7.4.0", "geoplanet:7.4.1", "geoplanet:7.5.1", "geoplanet:7.5.2", "geoplanet:7.6.0", "geoplanet:7.8.1", "geoplanet:7.9.0", "geoplanet:7.10.0", "geoplanet:8.0.0", "woeplanet:8.0.0"], "meta:indexed": "2020-08-20T20:54:04.774841", "woe:alias_ENG_V": ["Fellering Railway Station"], "meta:updated": "2020-10-14T11:52:05.283426", "woe:alias_ENG_P": ["Fellering Station"], "woe:alias_FRE_V": ["Gare Fellering"], "woe:hierarchy": {"continent": 24865675, "country": 23424819, "town": 0, "planet": 1, "county": 12597152, "suburb": 0, "state": 7153330, "region": 0, "localadmin": 12643720}, "woe:timezone_id": 28350911, "woe:hash": "u0sbqzrzbcsu", "woe:centroid": [6.987, 47.89761], "geom:latitude": 47.89761, "geom:longitude": 6.987, "geom:hash": "u0sbqzrzbcsu", "woe:latitude": 47.89761, "geom:centroid": [6.987, 47.89761], "woe:longitude": 6.987, "woe:repo": "woeplanet-poi-fr", "geom:area": 0.0, "woe:scale": 19}}