{"type": "Feature", "id": 22915073, "geometry": {"type": "Point", "coordinates": [2.28034, 48.89724]}, "properties": {"woe:id": 22915073, "woe:parent_id": 55863515, "woe:name": "M\u00e9tro-Pont de Levallois-B\u00e9con", "woe:placetype": 20, "woe:placetype_name": "POI", "woe:lang": "FRE", "iso:country": "FR", "meta:provider": ["geoplanet:7.3.1", "geoplanet:7.3.2", "geoplanet:7.4.0", "geoplanet:7.4.1", "geoplanet:7.5.1", "geoplanet:7.5.2", "geoplanet:7.6.0", "geoplanet:7.8.1", "geoplanet:7.9.0", "geoplanet:7.10.0", "geoplanet:8.0.0", "woeplanet:8.0.0"], "meta:indexed": "2020-08-20T20:54:06.924418", "meta:updated": "2020-10-14T11:52:06.116015", "woe:alias_ENG_P": ["Pont de Levallois-Becon Metro Station"], "woe:alias_FRE_S": ["Metro-Pont de Levallois-Becon"], "woe:hierarchy": {"continent": 24865675, "country": 23424819, "town": 0, "planet": 1, "county": 15022631, "suburb": 0, "state": 7153319, "region": 0, "localadmin": 12648179}, "woe:timezone_id": 28350911, "woe:hash": "u09w5vkrpf0w", "woe:centroid": [2.28034, 48.89724], "geom:latitude": 48.89724, "geom:longitude": 2.28034, "geom:hash": "u09w5vkrpf0w", "woe:latitude": 48.89724, "geom:centroid": [2.28034, 48.89724], "woe:longitude": 2.28034, "woe:repo": "woeplanet-poi-fr", "geom:area": 0.0, "woe:scale": 19}}