{"type": "Feature", "id": 29333661, "properties": {"woe:id": 29333661, "woe:parent_id": 12651009, "woe:name": "Stade Roland Garros", "woe:placetype": 20, "woe:placetype_name": "POI", "woe:lang": "FRE", "iso:country": "FR", "meta:provider": ["geoplanet:7.3.1", "geoplanet:7.3.2", "geoplanet:7.4.0", "geoplanet:7.4.1", "geoplanet:7.5.1", "geoplanet:7.5.2", "geoplanet:7.6.0", "geoplanet:7.8.1", "geoplanet:7.9.0", "geoplanet:7.10.0", "geoplanet:8.0.0", "woeplanet:8.0.0"], "meta:indexed": "2020-08-20T20:54:07.154514", "meta:updated": "2020-08-22T01:53:29.928423", "woe:hierarchy": {"continent": 24865675, "country": 23424819, "town": 0, "planet": 1, "county": 12597155, "suburb": 0, "state": 7153319, "region": 0, "localadmin": 12651009}, "woe:timezone_id": 28350911, "woe:hash": "u09tghrr2u8r", "woe:centroid": [2.2512, 48.847858], "geom:latitude": 48.847858, "geom:longitude": 2.2512, "geom:hash": "u09tghrr2u8r", "woe:latitude": 48.847858, "geom:centroid": [2.2512, 48.847858], "woe:longitude": 2.2512, "woe:repo": "woeplanet-poi-fr"}, "geometry": {"coordinates": [2.2512, 48.847858], "type": "Point"}}