{"type": "Feature", "id": 22909484, "properties": {"woe:id": 22909484, "woe:parent_id": 12638223, "woe:name": "RER-P\u00e9reire-Levallois", "woe:placetype": 20, "woe:placetype_name": "POI", "woe:lang": "FRE", "iso:country": "FR", "meta:provider": ["geoplanet:7.3.1", "geoplanet:7.3.2", "geoplanet:7.4.0", "geoplanet:7.4.1", "geoplanet:7.5.1", "geoplanet:7.5.2", "geoplanet:7.6.0", "geoplanet:7.8.1", "geoplanet:7.9.0", "geoplanet:7.10.0", "geoplanet:8.0.0", "woeplanet:8.0.0"], "meta:indexed": "2020-08-20T20:54:06.717434", "woe:alias_ENG_V": ["Pereire-Levallois Railway Station"], "woe:alias_ENG_P": ["Pereire-Levallois Station"], "meta:updated": "2020-08-22T01:53:29.773746", "woe:alias_FRE_S": ["Gare Pereire-Levallois", "RER-Pereire-Levallois", "Gare de Pereire-Levallois"], "woe:alias_FRE_V": ["Gare de P\u00e9reire-Levallois", "Gare P\u00e9reire-Levallois"], "woe:hierarchy": {"continent": 24865675, "country": 23424819, "town": 0, "planet": 1, "county": 12597155, "suburb": 0, "state": 7153319, "region": 0, "localadmin": 12638223}, "woe:timezone_id": 28350911, "woe:hash": "u09wh77n8whs", "woe:centroid": [2.30029, 48.886189], "geom:latitude": 48.886189, "geom:longitude": 2.30029, "geom:hash": "u09wh77n8whs", "woe:latitude": 48.886189, "geom:centroid": [2.30029, 48.886189], "woe:longitude": 2.30029, "woe:repo": "woeplanet-poi-fr"}, "geometry": {"coordinates": [2.30029, 48.886189], "type": "Point"}}