{"type": "Feature", "id": 22874441, "properties": {"woe:id": 22874441, "woe:parent_id": 607957, "woe:name": "Mus\u00e9e des Beaux-Arts et d'Arch\u00e9ologie de Libourne", "woe:placetype": 20, "woe:placetype_name": "POI", "woe:lang": "FRE", "iso:country": "FR", "meta:provider": ["geoplanet:7.3.1", "geoplanet:7.3.2", "geoplanet:7.4.0", "geoplanet:7.4.1", "geoplanet:7.5.1", "geoplanet:7.5.2", "geoplanet:7.6.0", "geoplanet:7.8.1", "geoplanet:7.9.0", "geoplanet:7.10.0", "geoplanet:8.0.0", "woeplanet:8.0.0"], "meta:indexed": "2020-08-20T20:54:05.568278", "meta:updated": "2020-08-22T01:53:29.338537", "woe:alias_FRE_S": ["Musee des Beaux-Arts et d'Archeologie de Libourne"], "woe:hierarchy": {"continent": 24865675, "country": 23424819, "town": 0, "planet": 1, "county": 12597132, "suburb": 0, "state": 7153309, "region": 0, "localadmin": 12648200}, "woe:timezone_id": 28350911, "woe:hash": "ezzzd2mteq40", "woe:centroid": [-0.24499, 44.914459], "geom:latitude": 44.914459, "geom:longitude": -0.24499, "geom:hash": "ezzzd2mteq40", "woe:latitude": 44.914459, "geom:centroid": [-0.24499, 44.914459], "woe:longitude": -0.24499, "woe:repo": "woeplanet-poi-fr"}, "geometry": {"coordinates": [-0.24499, 44.914459], "type": "Point"}}