{"type": "Feature", "id": 22915958, "geometry": {"type": "Point", "coordinates": [2.47722, 48.932751]}, "properties": {"woe:id": 22915958, "woe:parent_id": 55863500, "woe:name": "RER-Blanc-Mesnil", "woe:placetype": 20, "woe:placetype_name": "POI", "woe:lang": "FRE", "iso:country": "FR", "meta:provider": ["geoplanet:7.3.1", "geoplanet:7.3.2", "geoplanet:7.4.0", "geoplanet:7.4.1", "geoplanet:7.5.1", "geoplanet:7.5.2", "geoplanet:7.6.0", "geoplanet:7.8.1", "geoplanet:7.9.0", "geoplanet:7.10.0", "geoplanet:8.0.0", "woeplanet:8.0.0"], "meta:indexed": "2020-08-20T20:54:06.937902", "woe:alias_ENG_V": ["Blanc-Mesnil Railway Station"], "meta:updated": "2020-10-14T11:52:05.619692", "woe:alias_ENG_P": ["Blanc-Mesnil Station"], "woe:alias_FRE_V": ["Gare de Blanc-Mesnil", "Gare Blanc-Mesnil"], "woe:hierarchy": {"continent": 24865675, "country": 23424819, "town": 0, "planet": 1, "county": 12597156, "suburb": 0, "state": 7153319, "region": 0, "localadmin": 12637691}, "woe:timezone_id": 28350911, "woe:hash": "u09y27gvgmvj", "woe:centroid": [2.47722, 48.932751], "geom:latitude": 48.932751, "geom:longitude": 2.47722, "geom:hash": "u09y27gvgmvj", "woe:latitude": 48.932751, "geom:centroid": [2.47722, 48.932751], "woe:longitude": 2.47722, "woe:repo": "woeplanet-poi-fr", "geom:area": 0.0, "woe:scale": 19}}