{"type": "Feature", "id": 22868268, "geometry": {"type": "Point", "coordinates": [-0.08742, 47.250381]}, "properties": {"woe:id": 22868268, "woe:parent_id": 577816, "woe:name": "Musee du Moteur", "woe:placetype": 20, "woe:placetype_name": "POI", "woe:lang": "FRE", "iso:country": "FR", "meta:provider": ["geoplanet:7.3.1", "geoplanet:7.3.2", "geoplanet:7.4.0", "geoplanet:7.4.1", "geoplanet:7.5.1", "geoplanet:7.5.2", "geoplanet:7.6.0", "geoplanet:7.8.1", "geoplanet:7.9.0", "geoplanet:7.10.0", "geoplanet:8.0.0", "woeplanet:8.0.0"], "meta:indexed": "2020-08-20T20:54:05.406920", "meta:updated": "2020-10-14T11:52:11.825769", "woe:alias_FRE_V": ["Mus\u00e9e du Moteur"], "woe:hierarchy": {"continent": 24865675, "country": 23424819, "town": 0, "planet": 1, "county": 12597202, "suburb": 0, "state": 7153325, "region": 0, "localadmin": 12656084}, "woe:timezone_id": 28350911, "woe:hash": "gbruy18m6vqv", "woe:centroid": [-0.08742, 47.250381], "geom:latitude": 47.250381, "geom:longitude": -0.08742, "geom:hash": "gbruy18m6vqv", "woe:latitude": 47.250381, "geom:centroid": [-0.08742, 47.250381], "woe:longitude": -0.08742, "woe:repo": "woeplanet-poi-fr", "geom:area": 0.0, "woe:scale": 19}}