{"type": "Feature", "id": 22909769, "geometry": {"type": "Point", "coordinates": [2.35908, 48.897758]}, "properties": {"woe:id": 22909769, "woe:parent_id": 12646533, "woe:name": "M\u00e9tro-Porte de la Chapelle", "woe:placetype": 20, "woe:placetype_name": "POI", "woe:lang": "FRE", "iso:country": "FR", "meta:provider": ["geoplanet:7.3.1", "geoplanet:7.3.2", "geoplanet:7.4.0", "geoplanet:7.4.1", "geoplanet:7.5.1", "geoplanet:7.5.2", "geoplanet:7.6.0", "geoplanet:7.8.1", "geoplanet:7.9.0", "geoplanet:7.10.0", "geoplanet:8.0.0", "woeplanet:8.0.0"], "meta:indexed": "2020-08-20T20:54:06.727992", "meta:updated": "2020-10-14T11:52:05.974638", "woe:alias_ENG_P": ["Porte de la Chapelle Metro Station"], "woe:alias_FRE_S": ["Metro-Porte de la Chapelle"], "woe:hierarchy": {"continent": 24865675, "country": 23424819, "town": 0, "planet": 1, "county": 12597155, "suburb": 0, "state": 7153319, "region": 0, "localadmin": 12646533}, "woe:timezone_id": 28350911, "woe:hash": "u09wjttf4dc8", "woe:centroid": [2.35908, 48.897758], "geom:latitude": 48.897758, "geom:longitude": 2.35908, "geom:hash": "u09wjttf4dc8", "woe:latitude": 48.897758, "geom:centroid": [2.35908, 48.897758], "woe:longitude": 2.35908, "woe:repo": "woeplanet-poi-fr", "geom:area": 0.0, "woe:scale": 19}}