{"type": "Feature", "id": 22138023, "geometry": {"type": "Point", "coordinates": [3.27558, 50.19202]}, "properties": {"woe:id": 22138023, "woe:parent_id": 589953, "woe:name": "Gare de Escaudoeuvres", "woe:placetype": 20, "woe:placetype_name": "POI", "woe:lang": "FRE", "iso:country": "FR", "meta:provider": ["geoplanet:7.3.1", "geoplanet:7.3.2", "geoplanet:7.4.0", "geoplanet:7.4.1", "geoplanet:7.5.1", "geoplanet:7.5.2", "geoplanet:7.6.0", "geoplanet:7.8.1", "geoplanet:7.9.0", "geoplanet:7.10.0", "geoplanet:8.0.0", "woeplanet:8.0.0"], "meta:indexed": "2020-08-20T20:54:04.767134", "woe:alias_ENG_V": ["Escaudoeuvres Railway Station"], "meta:updated": "2020-10-14T11:52:05.041250", "woe:alias_ENG_P": ["Escaudoeuvres Station"], "woe:alias_FRE_V": ["Gare Escaudoeuvres"], "woe:hierarchy": {"continent": 24865675, "country": 23424819, "town": 0, "planet": 1, "county": 12597175, "suburb": 0, "state": 7153324, "region": 0, "localadmin": 12660960}, "woe:timezone_id": 28350911, "woe:hash": "u0fmd91jww9m", "woe:centroid": [3.27558, 50.19202], "geom:latitude": 50.19202, "geom:longitude": 3.27558, "geom:hash": "u0fmd91jww9m", "woe:latitude": 50.19202, "geom:centroid": [3.27558, 50.19202], "woe:longitude": 3.27558, "woe:repo": "woeplanet-poi-fr", "geom:area": 0.0, "woe:scale": 19}}