{"type": "Feature", "id": 22141318, "geometry": {"type": "Point", "coordinates": [2.12314, 48.860859]}, "properties": {"woe:id": 22141318, "woe:parent_id": 55863522, "woe:name": "SNCF-Louveciennes", "woe:placetype": 20, "woe:placetype_name": "POI", "woe:lang": "FRE", "iso:country": "FR", "meta:provider": ["geoplanet:7.3.1", "geoplanet:7.3.2", "geoplanet:7.4.0", "geoplanet:7.4.1", "geoplanet:7.5.1", "geoplanet:7.5.2", "geoplanet:7.6.0", "geoplanet:7.8.1", "geoplanet:7.9.0", "geoplanet:7.10.0", "geoplanet:8.0.0", "woeplanet:8.0.0"], "meta:indexed": "2020-08-20T20:54:04.916131", "woe:alias_ENG_V": ["Louveciennes Railway Station"], "meta:updated": "2020-10-14T11:52:04.988166", "woe:alias_ENG_P": ["Louveciennes Station"], "woe:alias_FRE_V": ["Gare du Louveciennes", "Gare Louveciennes"], "woe:hierarchy": {"continent": 24865675, "country": 23424819, "town": 0, "planet": 1, "county": 12597126, "suburb": 0, "state": 7153319, "region": 0, "localadmin": 12648447}, "woe:timezone_id": 28350911, "woe:hash": "u09tbqf50src", "woe:centroid": [2.12314, 48.860859], "geom:latitude": 48.860859, "geom:longitude": 2.12314, "geom:hash": "u09tbqf50src", "woe:latitude": 48.860859, "geom:centroid": [2.12314, 48.860859], "woe:longitude": 2.12314, "woe:repo": "woeplanet-poi-fr", "geom:area": 0.0, "woe:scale": 19}}