{"type": "Feature", "id": 22917366, "properties": {"woe:id": 22917366, "woe:parent_id": 55863452, "woe:name": "RER-Villeneuve-Prairie", "woe:placetype": 20, "woe:placetype_name": "POI", "woe:lang": "FRE", "iso:country": "FR", "meta:provider": ["geoplanet:7.3.1", "geoplanet:7.3.2", "geoplanet:7.4.0", "geoplanet:7.4.1", "geoplanet:7.5.1", "geoplanet:7.5.2", "geoplanet:7.6.0", "geoplanet:7.8.1", "geoplanet:7.9.0", "geoplanet:7.10.0", "geoplanet:8.0.0", "woeplanet:8.0.0"], "meta:indexed": "2020-08-20T20:54:06.982928", "woe:alias_ENG_V": ["Villeneuve-Prairie Railway Station"], "meta:updated": "2020-08-22T01:53:29.882319", "woe:alias_ENG_P": ["Villeneuve-Prairie Station"], "woe:alias_FRE_V": ["Gare de Villeneuve-Prairie", "Gare Villeneuve-Prairie"], "woe:hierarchy": {"continent": 24865675, "country": 23424819, "town": 0, "planet": 1, "county": 12597151, "suburb": 0, "state": 7153319, "region": 0, "localadmin": 12641687}, "woe:timezone_id": 28350911, "woe:hash": "u09trm7sb45x", "woe:centroid": [2.43279, 48.765018], "geom:latitude": 48.765018, "geom:longitude": 2.43279, "geom:hash": "u09trm7sb45x", "woe:latitude": 48.765018, "geom:centroid": [2.43279, 48.765018], "woe:longitude": 2.43279, "woe:repo": "woeplanet-poi-fr"}, "geometry": {"coordinates": [2.43279, 48.765018], "type": "Point"}}