{"type": "Feature", "id": 22880187, "geometry": {"type": "Point", "coordinates": [4.79463, 43.743149]}, "properties": {"woe:id": 22880187, "woe:parent_id": 605420, "woe:name": "Mus\u00e9e de la Tour du Brau", "woe:placetype": 20, "woe:placetype_name": "POI", "woe:lang": "FRE", "iso:country": "FR", "meta:provider": ["geoplanet:7.3.1", "geoplanet:7.3.2", "geoplanet:7.4.0", "geoplanet:7.4.1", "geoplanet:7.5.1", "geoplanet:7.5.2", "geoplanet:7.6.0", "geoplanet:7.8.1", "geoplanet:7.9.0", "geoplanet:7.10.0", "geoplanet:8.0.0", "woeplanet:8.0.0"], "meta:indexed": "2020-08-20T20:54:05.705105", "meta:updated": "2020-10-14T11:52:11.943062", "woe:alias_FRE_S": ["Musee de la Tour du Brau"], "woe:hierarchy": {"continent": 24865675, "country": 23424819, "town": 0, "planet": 1, "county": 12597199, "suburb": 0, "state": 7153328, "region": 0, "localadmin": 12665304}, "woe:timezone_id": 28350911, "woe:hash": "spg2v55q6czr", "woe:centroid": [4.79463, 43.743149], "geom:latitude": 43.743149, "geom:longitude": 4.79463, "geom:hash": "spg2v55q6czr", "woe:latitude": 43.743149, "geom:centroid": [4.79463, 43.743149], "woe:longitude": 4.79463, "woe:repo": "woeplanet-poi-fr", "geom:area": 0.0, "woe:scale": 19}}