{"type": "Feature", "id": 22901550, "geometry": {"type": "Point", "coordinates": [3.07588, 50.374149]}, "properties": {"woe:id": 22901550, "woe:parent_id": 589057, "woe:name": "Mus\u00e9e de la Chartreuse de Douai", "woe:placetype": 20, "woe:placetype_name": "POI", "woe:lang": "FRE", "iso:country": "FR", "meta:provider": ["geoplanet:7.3.1", "geoplanet:7.3.2", "geoplanet:7.4.0", "geoplanet:7.4.1", "geoplanet:7.5.1", "geoplanet:7.5.2", "geoplanet:7.6.0", "geoplanet:7.8.1", "geoplanet:7.9.0", "geoplanet:7.10.0", "geoplanet:8.0.0", "woeplanet:8.0.0"], "meta:indexed": "2020-08-20T20:54:06.310539", "meta:updated": "2020-10-14T11:52:06.170521", "woe:alias_FRE_S": ["Musee de la Chartreuse de Douai"], "woe:alias_FRE_V": ["Mus\u00e9e de la Chartreuse", "Musee de la Chartreuse"], "woe:hierarchy": {"continent": 24865675, "country": 23424819, "town": 0, "planet": 1, "county": 12597175, "suburb": 0, "state": 7153324, "region": 0, "localadmin": 12660617}, "woe:timezone_id": 28350911, "woe:hash": "u0fntfrf9jyr", "woe:centroid": [3.07588, 50.374149], "geom:latitude": 50.374149, "geom:longitude": 3.07588, "geom:hash": "u0fntfrf9jyr", "woe:latitude": 50.374149, "geom:centroid": [3.07588, 50.374149], "woe:longitude": 3.07588, "woe:repo": "woeplanet-poi-fr", "geom:area": 0.0, "woe:scale": 19}}