{"type": "Feature", "id": 22141136, "properties": {"woe:id": 22141136, "woe:parent_id": 608320, "woe:name": "SNCF-Lizy-sur-Ourcq", "woe:placetype": 20, "woe:placetype_name": "POI", "woe:lang": "FRE", "iso:country": "FR", "meta:provider": ["geoplanet:7.3.1", "geoplanet:7.3.2", "geoplanet:7.4.0", "geoplanet:7.4.1", "geoplanet:7.5.1", "geoplanet:7.5.2", "geoplanet:7.6.0", "geoplanet:7.8.1", "geoplanet:7.9.0", "geoplanet:7.10.0", "geoplanet:8.0.0", "woeplanet:8.0.0"], "meta:indexed": "2020-08-20T20:54:04.907057", "woe:alias_ENG_V": ["Lizy-sur-Ourcq Railway Station"], "meta:updated": "2020-08-22T01:53:29.076311", "woe:alias_ENG_P": ["Lizy-sur-Ourcq Station"], "woe:alias_FRE_V": ["Gare du Lizy-sur-Ourcq", "Gare Lizy-sur-Ourcq"], "woe:hierarchy": {"continent": 24865675, "country": 23424819, "town": 0, "planet": 1, "county": 12597137, "suburb": 0, "state": 7153319, "region": 0, "localadmin": 12648310}, "woe:timezone_id": 28350911, "woe:hash": "u0dnuupxrjrp", "woe:centroid": [3.03185, 49.02227], "geom:latitude": 49.02227, "geom:longitude": 3.03185, "geom:hash": "u0dnuupxrjrp", "woe:latitude": 49.02227, "geom:centroid": [3.03185, 49.02227], "woe:longitude": 3.03185, "woe:repo": "woeplanet-poi-fr"}, "geometry": {"coordinates": [3.03185, 49.02227], "type": "Point"}}