{"type": "Feature", "id": 56059903, "geometry": {"type": "Point", "coordinates": [-0.61892, 44.797901]}, "properties": {"woe:id": 56059903, "woe:parent_id": 55863556, "woe:name": "Univ. Montesquieu Bordeaux 4", "woe:placetype": 20, "woe:placetype_name": "POI", "woe:lang": "FRE", "iso:country": "FR", "meta:provider": ["geoplanet:7.3.1", "geoplanet:7.3.2", "geoplanet:7.4.0", "geoplanet:7.4.1", "geoplanet:7.5.1", "geoplanet:7.5.2", "geoplanet:7.6.0", "geoplanet:7.8.1", "geoplanet:7.9.0", "geoplanet:7.10.0", "geoplanet:8.0.0", "woeplanet:8.0.0"], "meta:indexed": "2020-08-20T20:54:07.539422", "meta:updated": "2020-10-14T11:52:11.207847", "woe:alias_FRE_V": ["Faculte de Droit Et d'Economie", "Facult\u00e9 de Droit Et d'\u00c9conomie"], "woe:hierarchy": {"continent": 24865675, "country": 23424819, "town": 0, "planet": 1, "county": 12597132, "suburb": 0, "state": 7153309, "region": 0, "localadmin": 12650540}, "woe:timezone_id": 28350911, "woe:hash": "ezzwcgjqdn5b", "woe:centroid": [-0.61892, 44.797901], "geom:latitude": 44.797901, "geom:longitude": -0.61892, "geom:hash": "ezzwcgjqdn5b", "woe:latitude": 44.797901, "geom:centroid": [-0.61892, 44.797901], "woe:longitude": -0.61892, "woe:repo": "woeplanet-poi-fr", "geom:area": 0.0, "woe:scale": 19}}