{"type": "Feature", "id": 22145247, "properties": {"woe:id": 22145247, "woe:parent_id": 615808, "woe:name": "Gare de Pau", "woe:placetype": 20, "woe:placetype_name": "POI", "woe:lang": "FRE", "iso:country": "FR", "meta:provider": ["geoplanet:7.3.1", "geoplanet:7.3.2", "geoplanet:7.4.0", "geoplanet:7.4.1", "geoplanet:7.5.1", "geoplanet:7.5.2", "geoplanet:7.6.0", "geoplanet:7.8.1", "geoplanet:7.9.0", "geoplanet:7.10.0", "geoplanet:8.0.0", "woeplanet:8.0.0"], "meta:indexed": "2020-08-20T20:54:05.074168", "woe:alias_ENG_V": ["Pau Railway Station"], "meta:updated": "2020-08-22T01:53:29.139735", "woe:alias_ENG_P": ["Pau Station"], "woe:alias_FRE_V": ["Gare Pau"], "woe:hierarchy": {"continent": 24865675, "country": 23424819, "town": 0, "planet": 1, "county": 12597114, "suburb": 0, "state": 7153309, "region": 0, "localadmin": 12650454}, "woe:timezone_id": 28350911, "woe:hash": "ezxwr94c5hr7", "woe:centroid": [-0.36962, 43.291821], "geom:latitude": 43.291821, "geom:longitude": -0.36962, "geom:hash": "ezxwr94c5hr7", "woe:latitude": 43.291821, "geom:centroid": [-0.36962, 43.291821], "woe:longitude": -0.36962, "woe:repo": "woeplanet-poi-fr"}, "geometry": {"coordinates": [-0.36962, 43.291821], "type": "Point"}}