{"type": "Feature", "id": 22877438, "geometry": {"type": "Point", "coordinates": [1.80799, 43.856091]}, "properties": {"woe:id": 22877438, "woe:parent_id": 608243, "woe:name": "Gare de Lisle-sur-Tarn", "woe:placetype": 20, "woe:placetype_name": "POI", "woe:lang": "FRE", "iso:country": "FR", "meta:provider": ["geoplanet:7.3.1", "geoplanet:7.3.2", "geoplanet:7.4.0", "geoplanet:7.4.1", "geoplanet:7.5.1", "geoplanet:7.5.2", "geoplanet:7.6.0", "geoplanet:7.8.1", "geoplanet:7.9.0", "geoplanet:7.10.0", "geoplanet:8.0.0", "woeplanet:8.0.0"], "meta:indexed": "2020-08-20T20:54:05.639989", "woe:alias_ENG_V": ["Lisle-sur-Tarn Railway Station"], "meta:updated": "2020-10-14T11:52:11.997189", "woe:alias_ENG_P": ["Lisle-sur-Tarn Station"], "woe:alias_FRE_V": ["Gare Lisle-sur-Tarn"], "woe:hierarchy": {"continent": 24865675, "country": 23424819, "town": 0, "planet": 1, "county": 12597192, "suburb": 0, "state": 7153323, "region": 0, "localadmin": 12661829}, "woe:timezone_id": 28350911, "woe:hash": "spc33pu81pzj", "woe:centroid": [1.80799, 43.856091], "geom:latitude": 43.856091, "geom:longitude": 1.80799, "geom:hash": "spc33pu81pzj", "woe:latitude": 43.856091, "geom:centroid": [1.80799, 43.856091], "woe:longitude": 1.80799, "woe:repo": "woeplanet-poi-fr", "geom:area": 0.0, "woe:scale": 19}}