{"type": "Feature", "id": 28737144, "geometry": {"type": "Point", "coordinates": [9.36581, 41.59613]}, "properties": {"woe:id": 28737144, "woe:parent_id": 20201889, "woe:name": "La Chiappa", "woe:placetype": 20, "woe:placetype_name": "POI", "woe:lang": "ENG", "iso:country": "FR", "meta:provider": ["geoplanet:7.3.1", "geoplanet:7.3.2", "geoplanet:7.4.0", "geoplanet:7.4.1", "geoplanet:7.5.1", "geoplanet:7.5.2", "geoplanet:7.6.0", "geoplanet:7.8.1", "geoplanet:7.9.0", "geoplanet:7.10.0", "geoplanet:8.0.0", "woeplanet:8.0.0"], "meta:indexed": "2020-08-20T20:54:07.115747", "meta:updated": "2020-10-14T11:52:04.688896", "woe:hierarchy": {"continent": 24865675, "country": 23424819, "town": 0, "planet": 1, "county": 12597134, "suburb": 0, "state": 7153316, "region": 0, "localadmin": 20075028}, "woe:timezone_id": 28350911, "woe:hash": "spqsth7gp0wh", "woe:centroid": [9.36581, 41.59613], "geom:latitude": 41.59613, "geom:longitude": 9.36581, "geom:hash": "spqsth7gp0wh", "woe:latitude": 41.59613, "geom:centroid": [9.36581, 41.59613], "woe:longitude": 9.36581, "woe:repo": "woeplanet-poi-fr", "geom:area": 0.0, "woe:scale": 19}}