{"type": "Feature", "id": 22880866, "properties": {"woe:id": 22880866, "woe:parent_id": 24865748, "woe:name": "M\u00e9tro-P\u00e9rier", "woe:placetype": 20, "woe:placetype_name": "POI", "woe:lang": "FRE", "iso:country": "FR", "meta:provider": ["geoplanet:7.3.1", "geoplanet:7.3.2", "geoplanet:7.4.0", "geoplanet:7.4.1", "geoplanet:7.5.1", "geoplanet:7.5.2", "geoplanet:7.6.0", "geoplanet:7.8.1", "geoplanet:7.9.0", "geoplanet:7.10.0", "geoplanet:8.0.0", "woeplanet:8.0.0"], "meta:indexed": "2020-08-20T20:54:05.727259", "meta:updated": "2020-08-22T01:53:29.399218", "woe:alias_ENG_P": ["Perier Metro Station"], "woe:alias_FRE_S": ["Metro-Perier"], "woe:hierarchy": {"continent": 24865675, "country": 23424819, "town": 0, "planet": 1, "county": 12597199, "suburb": 0, "state": 7153328, "region": 0, "localadmin": 24865748}, "woe:timezone_id": 28350911, "woe:hash": "spey4wfcq9fu", "woe:centroid": [5.38736, 43.279491], "geom:latitude": 43.279491, "geom:longitude": 5.38736, "geom:hash": "spey4wfcq9fu", "woe:latitude": 43.279491, "geom:centroid": [5.38736, 43.279491], "woe:longitude": 5.38736, "woe:repo": "woeplanet-poi-fr"}, "geometry": {"coordinates": [5.38736, 43.279491], "type": "Point"}}