{"type": "Feature", "id": 22146787, "properties": {"woe:id": 22146787, "woe:parent_id": 623661, "woe:name": "Gare de Saint-Cyr-en-Val", "woe:placetype": 20, "woe:placetype_name": "POI", "woe:lang": "FRE", "iso:country": "FR", "meta:provider": ["geoplanet:7.3.1", "geoplanet:7.3.2", "geoplanet:7.4.0", "geoplanet:7.4.1", "geoplanet:7.5.1", "geoplanet:7.5.2", "geoplanet:7.6.0", "geoplanet:7.8.1", "geoplanet:7.9.0", "geoplanet:7.10.0", "geoplanet:8.0.0", "woeplanet:8.0.0"], "meta:indexed": "2020-08-20T20:54:05.152925", "woe:alias_ENG_V": ["Saint-Cyr-en-Val Railway Station"], "meta:updated": "2020-08-22T01:53:29.171256", "woe:alias_ENG_P": ["Saint-Cyr-en-Val Station"], "woe:alias_FRE_V": ["Gare Saint-Cyr-en-Val"], "woe:hierarchy": {"continent": 24865675, "country": 23424819, "town": 0, "planet": 1, "county": 12597141, "suburb": 0, "state": 7153314, "region": 0, "localadmin": 20074833}, "woe:timezone_id": 28350911, "woe:hash": "u092h34ptrtb", "woe:centroid": [1.94756, 47.819321], "geom:latitude": 47.819321, "geom:longitude": 1.94756, "geom:hash": "u092h34ptrtb", "woe:latitude": 47.819321, "geom:centroid": [1.94756, 47.819321], "woe:longitude": 1.94756, "woe:repo": "woeplanet-poi-fr"}, "geometry": {"coordinates": [1.94756, 47.819321], "type": "Point"}}