{"type": "Feature", "id": 22137496, "properties": {"woe:id": 22137496, "woe:parent_id": 588515, "woe:name": "Gare de Dardilly", "woe:placetype": 20, "woe:placetype_name": "POI", "woe:lang": "FRE", "iso:country": "FR", "meta:provider": ["geoplanet:7.3.1", "geoplanet:7.3.2", "geoplanet:7.4.0", "geoplanet:7.4.1", "geoplanet:7.5.1", "geoplanet:7.5.2", "geoplanet:7.6.0", "geoplanet:7.8.1", "geoplanet:7.9.0", "geoplanet:7.10.0", "geoplanet:8.0.0", "woeplanet:8.0.0"], "meta:indexed": "2020-08-20T20:54:04.746317", "woe:alias_ENG_V": ["Dardilly Railway Station"], "meta:updated": "2020-08-22T01:53:29.011421", "woe:alias_ENG_P": ["Dardilly Station"], "woe:alias_FRE_V": ["Gare Dardilly"], "woe:hierarchy": {"continent": 24865675, "country": 23424819, "town": 0, "planet": 1, "county": 12597185, "suburb": 0, "state": 7153329, "region": 0, "localadmin": 22756280}, "woe:timezone_id": 28350911, "woe:hash": "u05kskfsxmk1", "woe:centroid": [4.76083, 45.817909], "geom:latitude": 45.817909, "geom:longitude": 4.76083, "geom:hash": "u05kskfsxmk1", "woe:latitude": 45.817909, "geom:centroid": [4.76083, 45.817909], "woe:longitude": 4.76083, "woe:repo": "woeplanet-poi-fr"}, "geometry": {"coordinates": [4.76083, 45.817909], "type": "Point"}}