{"type": "Feature", "id": 22893573, "properties": {"woe:id": 22893573, "woe:parent_id": 588205, "woe:name": "Gare de Culmont-Chalindrey", "woe:placetype": 20, "woe:placetype_name": "POI", "woe:lang": "FRE", "iso:country": "FR", "meta:provider": ["geoplanet:7.3.1", "geoplanet:7.3.2", "geoplanet:7.4.0", "geoplanet:7.4.1", "geoplanet:7.5.1", "geoplanet:7.5.2", "geoplanet:7.6.0", "geoplanet:7.8.1", "geoplanet:7.9.0", "geoplanet:7.10.0", "geoplanet:8.0.0", "woeplanet:8.0.0"], "meta:indexed": "2020-08-20T20:54:06.034094", "woe:alias_ENG_V": ["Culmont-Chalindrey Railway Station"], "meta:updated": "2020-08-22T01:53:29.521906", "woe:alias_ENG_P": ["Culmont-Chalindrey Station"], "woe:alias_FRE_V": ["Gare Culmont-Chalindrey"], "woe:hierarchy": {"continent": 24865675, "country": 23424819, "town": 0, "planet": 1, "county": 12597145, "suburb": 0, "state": 7153315, "region": 0, "localadmin": 12642677}, "woe:timezone_id": 28350911, "woe:hash": "u07zgzs0d5y7", "woe:centroid": [5.44382, 47.80986], "geom:latitude": 47.80986, "geom:longitude": 5.44382, "geom:hash": "u07zgzs0d5y7", "woe:latitude": 47.80986, "geom:centroid": [5.44382, 47.80986], "woe:longitude": 5.44382, "woe:repo": "woeplanet-poi-fr"}, "geometry": {"coordinates": [5.44382, 47.80986], "type": "Point"}}