{"type": "Feature", "id": 56060598, "properties": {"woe:id": 56060598, "woe:parent_id": 599765, "woe:name": "Iufm des Pays de Loire", "woe:placetype": 20, "woe:placetype_name": "POI", "woe:lang": "FRE", "iso:country": "FR", "meta:provider": ["geoplanet:7.3.1", "geoplanet:7.3.2", "geoplanet:7.4.0", "geoplanet:7.4.1", "geoplanet:7.5.1", "geoplanet:7.5.2", "geoplanet:7.6.0", "geoplanet:7.8.1", "geoplanet:7.9.0", "geoplanet:7.10.0", "geoplanet:8.0.0", "woeplanet:8.0.0"], "meta:indexed": "2020-08-20T20:54:08.159129", "meta:updated": "2020-08-22T01:53:30.291745", "woe:hierarchy": {"continent": 24865675, "country": 23424819, "town": 0, "planet": 1, "county": 12597200, "suburb": 0, "state": 7153325, "region": 0, "localadmin": 12663965}, "woe:timezone_id": 28350911, "woe:hash": "gbqcx34chh2d", "woe:centroid": [-1.43526, 46.67561], "geom:latitude": 46.67561, "geom:longitude": -1.43526, "geom:hash": "gbqcx34chh2d", "woe:latitude": 46.67561, "geom:centroid": [-1.43526, 46.67561], "woe:longitude": -1.43526, "woe:repo": "woeplanet-poi-fr"}, "geometry": {"coordinates": [-1.43526, 46.67561], "type": "Point"}}