{"type": "Feature", "id": 22877382, "geometry": {"type": "Point", "coordinates": [1.73018, 43.819721]}, "properties": {"woe:id": 22877382, "woe:parent_id": 587246, "woe:name": "Gare de Coufouleux", "woe:placetype": 20, "woe:placetype_name": "POI", "woe:lang": "FRE", "iso:country": "FR", "meta:provider": ["geoplanet:7.3.1", "geoplanet:7.3.2", "geoplanet:7.4.0", "geoplanet:7.4.1", "geoplanet:7.5.1", "geoplanet:7.5.2", "geoplanet:7.6.0", "geoplanet:7.8.1", "geoplanet:7.9.0", "geoplanet:7.10.0", "geoplanet:8.0.0", "woeplanet:8.0.0"], "meta:indexed": "2020-08-20T20:54:05.636705", "woe:alias_ENG_V": ["Coufouleux Railway Station"], "meta:updated": "2020-10-14T11:52:12.327828", "woe:alias_ENG_P": ["Coufouleux Station"], "woe:alias_FRE_V": ["Gare Coufouleux-Rabastens", "Gare de Coufouleux-Rabastens", "Gare Coufouleux"], "woe:hierarchy": {"continent": 24865675, "country": 23424819, "town": 0, "planet": 1, "county": 12597192, "suburb": 0, "state": 7153323, "region": 0, "localadmin": 12659932}, "woe:timezone_id": 28350911, "woe:hash": "spc1r35ukh59", "woe:centroid": [1.73018, 43.819721], "geom:latitude": 43.819721, "geom:longitude": 1.73018, "geom:hash": "spc1r35ukh59", "woe:latitude": 43.819721, "geom:centroid": [1.73018, 43.819721], "woe:longitude": 1.73018, "woe:repo": "woeplanet-poi-fr", "geom:area": 0.0, "woe:scale": 19}}