{"type": "Feature", "id": 55848201, "geometry": {"type": "Point", "coordinates": [5.11023, 43.332722]}, "properties": {"woe:id": 55848201, "woe:parent_id": 621259, "woe:name": "Gare de Sausset-les-Pins", "woe:placetype": 20, "woe:placetype_name": "POI", "woe:lang": "FRE", "iso:country": "FR", "meta:provider": ["geoplanet:7.3.1", "geoplanet:7.3.2", "geoplanet:7.4.0", "geoplanet:7.4.1", "geoplanet:7.5.1", "geoplanet:7.5.2", "geoplanet:7.6.0", "geoplanet:7.8.1", "geoplanet:7.9.0", "geoplanet:7.10.0", "geoplanet:8.0.0", "woeplanet:8.0.0"], "meta:indexed": "2020-08-20T20:54:07.177759", "woe:alias_ENG_V": ["Sausset-les-Pins Railway Station"], "meta:updated": "2020-10-14T11:52:04.793069", "woe:alias_ENG_P": ["Sausset-les-Pins Station"], "woe:alias_FRE_V": ["Gare Sausset-les-Pins"], "woe:hierarchy": {"continent": 24865675, "country": 23424819, "town": 0, "planet": 1, "county": 12597199, "suburb": 0, "state": 7153328, "region": 0, "localadmin": 12669531}, "woe:timezone_id": 28350911, "woe:hash": "spews23pkuze", "woe:centroid": [5.11023, 43.332722], "geom:latitude": 43.332722, "geom:longitude": 5.11023, "geom:hash": "spews23pkuze", "woe:latitude": 43.332722, "geom:centroid": [5.11023, 43.332722], "woe:longitude": 5.11023, "woe:repo": "woeplanet-poi-fr", "geom:area": 0.0, "woe:scale": 19}}