{"type": "Feature", "id": 55848262, "geometry": {"type": "Point", "coordinates": [4.88832, 45.70557]}, "properties": {"woe:id": 55848262, "woe:parent_id": 630587, "woe:name": "M\u00e9tro-Gare de V\u00e9nissieux", "woe:placetype": 20, "woe:placetype_name": "POI", "woe:lang": "FRE", "iso:country": "FR", "meta:provider": ["geoplanet:7.3.1", "geoplanet:7.3.2", "geoplanet:7.4.0", "geoplanet:7.4.1", "geoplanet:7.5.1", "geoplanet:7.5.2", "geoplanet:7.6.0", "geoplanet:7.8.1", "geoplanet:7.9.0", "geoplanet:7.10.0", "geoplanet:8.0.0", "woeplanet:8.0.0"], "meta:indexed": "2020-08-20T20:54:07.231148", "meta:updated": "2020-10-14T11:52:04.786581", "woe:alias_ENG_P": ["Gare de Venissieux Metro Station"], "woe:alias_FRE_S": ["Metro-Gare de Venissieux"], "woe:hierarchy": {"continent": 24865675, "country": 23424819, "town": 0, "planet": 1, "county": 12597185, "suburb": 0, "state": 7153329, "region": 0, "localadmin": 22757800}, "woe:timezone_id": 28350911, "woe:hash": "u05kp0rw4pg8", "woe:centroid": [4.88832, 45.70557], "geom:latitude": 45.70557, "geom:longitude": 4.88832, "geom:hash": "u05kp0rw4pg8", "woe:latitude": 45.70557, "geom:centroid": [4.88832, 45.70557], "woe:longitude": 4.88832, "woe:repo": "woeplanet-poi-fr", "geom:area": 0.0, "woe:scale": 19}}