{"type": "Feature", "id": 22903274, "geometry": {"type": "Point", "coordinates": [3.15734, 50.73225]}, "properties": {"woe:id": 22903274, "woe:parent_id": 628909, "woe:name": "M\u00e9tro-Phalempins", "woe:placetype": 20, "woe:placetype_name": "POI", "woe:lang": "FRE", "iso:country": "FR", "meta:provider": ["geoplanet:7.3.1", "geoplanet:7.3.2", "geoplanet:7.4.0", "geoplanet:7.4.1", "geoplanet:7.5.1", "geoplanet:7.5.2", "geoplanet:7.6.0", "geoplanet:7.8.1", "geoplanet:7.9.0", "geoplanet:7.10.0", "geoplanet:8.0.0", "woeplanet:8.0.0"], "meta:indexed": "2020-08-20T20:54:06.358458", "meta:updated": "2020-10-14T11:52:06.166173", "woe:alias_ENG_P": ["Phalempins Metro Station"], "woe:alias_FRE_S": ["Metro-Phalempins"], "woe:hierarchy": {"continent": 24865675, "country": 23424819, "town": 0, "planet": 1, "county": 12597175, "suburb": 0, "state": 7153324, "region": 0, "localadmin": 12671758}, "woe:timezone_id": 28350911, "woe:hash": "u140xge0g2g7", "woe:centroid": [3.15734, 50.73225], "geom:latitude": 50.73225, "geom:longitude": 3.15734, "geom:hash": "u140xge0g2g7", "woe:latitude": 50.73225, "geom:centroid": [3.15734, 50.73225], "woe:longitude": 3.15734, "woe:repo": "woeplanet-poi-fr", "geom:area": 0.0, "woe:scale": 19}}