{"type": "Feature", "id": 22148140, "geometry": {"type": "Point", "coordinates": [2.22446, 48.829079]}, "properties": {"woe:id": 22148140, "woe:parent_id": 55863575, "woe:name": "Gare de Mus\u00e9e de S\u00e8vres", "woe:placetype": 20, "woe:placetype_name": "POI", "woe:lang": "FRE", "iso:country": "FR", "meta:provider": ["geoplanet:7.3.1", "geoplanet:7.3.2", "geoplanet:7.4.0", "geoplanet:7.4.1", "geoplanet:7.5.1", "geoplanet:7.5.2", "geoplanet:7.6.0", "geoplanet:7.8.1", "geoplanet:7.9.0", "geoplanet:7.10.0", "geoplanet:8.0.0", "woeplanet:8.0.0"], "meta:indexed": "2020-08-20T20:54:05.194891", "woe:alias_ENG_V": ["Sevres Railway Station"], "woe:alias_ENG_P": ["Sevres Station"], "meta:updated": "2020-10-14T11:52:05.130689", "woe:alias_FRE_S": ["Gare de Musee de Sevres", "Gare Musee de Sevres"], "woe:alias_FRE_V": ["Mus\u00e9e de S\u00e8vres", "Musee de Sevres", "Gare Mus\u00e9e de S\u00e8vres"], "woe:hierarchy": {"continent": 24865675, "country": 23424819, "town": 0, "planet": 1, "county": 15022631, "suburb": 0, "state": 7153319, "region": 0, "localadmin": 12638579}, "woe:timezone_id": 28350911, "woe:hash": "u09tf95f18j9", "woe:centroid": [2.22446, 48.829079], "geom:latitude": 48.829079, "geom:longitude": 2.22446, "geom:hash": "u09tf95f18j9", "woe:latitude": 48.829079, "geom:centroid": [2.22446, 48.829079], "woe:longitude": 2.22446, "woe:repo": "woeplanet-poi-fr", "geom:area": 0.0, "woe:scale": 19}}