{"type": "Feature", "id": 56060088, "geometry": {"type": "Point", "coordinates": [6.18842, 48.660118]}, "properties": {"woe:id": 56060088, "woe:parent_id": 630016, "woe:name": "\u00c9cole Sup. Sciences Et Technologies", "woe:placetype": 20, "woe:placetype_name": "POI", "woe:lang": "FRE", "iso:country": "FR", "meta:provider": ["geoplanet:7.3.1", "geoplanet:7.3.2", "geoplanet:7.4.0", "geoplanet:7.4.1", "geoplanet:7.5.1", "geoplanet:7.5.2", "geoplanet:7.6.0", "geoplanet:7.8.1", "geoplanet:7.9.0", "geoplanet:7.10.0", "geoplanet:8.0.0", "woeplanet:8.0.0"], "meta:indexed": "2020-08-20T20:54:07.705365", "meta:updated": "2020-10-14T11:52:11.036037", "woe:alias_FRE_V": ["Ecole Sup. Sciences Et Technologies"], "woe:hierarchy": {"continent": 24865675, "country": 23424819, "town": 0, "planet": 1, "county": 12597176, "suburb": 0, "state": 7153322, "region": 0, "localadmin": 12672040}, "woe:timezone_id": 28350911, "woe:hash": "u0skuf638xkq", "woe:centroid": [6.18842, 48.660118], "geom:latitude": 48.660118, "geom:longitude": 6.18842, "geom:hash": "u0skuf638xkq", "woe:latitude": 48.660118, "geom:centroid": [6.18842, 48.660118], "woe:longitude": 6.18842, "woe:repo": "woeplanet-poi-fr", "geom:area": 0.0, "woe:scale": 19}}