{"type": "Feature", "id": 55848256, "geometry": {"type": "Point", "coordinates": [5.37173, 43.32069]}, "properties": {"woe:id": 55848256, "woe:parent_id": 24865754, "woe:name": "M\u00e9tro-Bougainville", "woe:placetype": 20, "woe:placetype_name": "POI", "woe:lang": "FRE", "iso:country": "FR", "meta:provider": ["geoplanet:7.3.1", "geoplanet:7.3.2", "geoplanet:7.4.0", "geoplanet:7.4.1", "geoplanet:7.5.1", "geoplanet:7.5.2", "geoplanet:7.6.0", "geoplanet:7.8.1", "geoplanet:7.9.0", "geoplanet:7.10.0", "geoplanet:8.0.0", "woeplanet:8.0.0"], "meta:indexed": "2020-08-20T20:54:07.225725", "meta:updated": "2020-10-14T11:52:04.801655", "woe:alias_ENG_P": ["Bougainville Metro Station"], "woe:alias_FRE_S": ["Metro-Bougainville"], "woe:hierarchy": {"continent": 24865675, "country": 23424819, "town": 0, "planet": 1, "county": 12597199, "suburb": 0, "state": 7153328, "region": 0, "localadmin": 24865754}, "woe:timezone_id": 28350911, "woe:hash": "spey6nr963uj", "woe:centroid": [5.37173, 43.32069], "geom:latitude": 43.32069, "geom:longitude": 5.37173, "geom:hash": "spey6nr963uj", "woe:latitude": 43.32069, "geom:centroid": [5.37173, 43.32069], "woe:longitude": 5.37173, "woe:repo": "woeplanet-poi-fr", "geom:area": 0.0, "woe:scale": 19}}