{"type": "Feature", "id": 22906263, "properties": {"woe:id": 22906263, "woe:parent_id": 12654825, "woe:name": "M\u00e9tro-Strasbourg-Saint-Denis", "woe:placetype": 20, "woe:placetype_name": "POI", "woe:lang": "FRE", "iso:country": "FR", "meta:provider": ["geoplanet:7.3.1", "geoplanet:7.3.2", "geoplanet:7.4.0", "geoplanet:7.4.1", "geoplanet:7.5.1", "geoplanet:7.5.2", "geoplanet:7.6.0", "geoplanet:7.8.1", "geoplanet:7.9.0", "geoplanet:7.10.0", "geoplanet:8.0.0", "woeplanet:8.0.0"], "meta:indexed": "2020-08-20T20:54:06.473879", "meta:updated": "2020-08-22T01:53:29.687676", "woe:alias_ENG_P": ["Strasbourg-Saint-Denis Metro Station"], "woe:alias_FRE_S": ["Metro-Strasbourg-Saint-Denis"], "woe:hierarchy": {"continent": 24865675, "country": 23424819, "town": 0, "planet": 1, "county": 12597155, "suburb": 0, "state": 7153319, "region": 0, "localadmin": 12654825}, "woe:timezone_id": 28350911, "woe:hash": "u09wj86hnn3q", "woe:centroid": [2.35408, 48.869282], "geom:latitude": 48.869282, "geom:longitude": 2.35408, "geom:hash": "u09wj86hnn3q", "woe:latitude": 48.869282, "geom:centroid": [2.35408, 48.869282], "woe:longitude": 2.35408, "woe:repo": "woeplanet-poi-fr"}, "geometry": {"coordinates": [2.35408, 48.869282], "type": "Point"}}