{"type": "Feature", "id": 22865260, "geometry": {"type": "Point", "coordinates": [-1.75063, 48.544022]}, "properties": {"woe:id": 22865260, "woe:parent_id": 588842, "woe:name": "Gare de Dol de Bretagne", "woe:placetype": 20, "woe:placetype_name": "POI", "woe:lang": "FRE", "iso:country": "FR", "meta:provider": ["geoplanet:7.3.1", "geoplanet:7.3.2", "geoplanet:7.4.0", "geoplanet:7.4.1", "geoplanet:7.5.1", "geoplanet:7.5.2", "geoplanet:7.6.0", "geoplanet:7.8.1", "geoplanet:7.9.0", "geoplanet:7.10.0", "geoplanet:8.0.0", "woeplanet:8.0.0"], "meta:indexed": "2020-08-20T20:54:05.338808", "woe:alias_ENG_V": ["Dol de Bretagne Railway Station"], "meta:updated": "2020-10-14T11:52:11.626887", "woe:alias_ENG_P": ["Dol de Bretagne Station"], "woe:alias_FRE_V": ["Gare Dol-de-Bretagne", "Gare de Dol-de-Bretagne", "Gare Dol de Bretagne"], "woe:hierarchy": {"continent": 24865675, "country": 23424819, "town": 0, "planet": 1, "county": 12597138, "suburb": 0, "state": 7153313, "region": 0, "localadmin": 12642963}, "woe:timezone_id": 28350911, "woe:hash": "gbwu0jjjrmed", "woe:centroid": [-1.75063, 48.544022], "geom:latitude": 48.544022, "geom:longitude": -1.75063, "geom:hash": "gbwu0jjjrmed", "woe:latitude": 48.544022, "geom:centroid": [-1.75063, 48.544022], "woe:longitude": -1.75063, "woe:repo": "woeplanet-poi-fr", "geom:area": 0.0, "woe:scale": 19}}