{"type": "Feature", "id": 56060315, "properties": {"woe:id": 56060315, "woe:parent_id": 29332047, "woe:name": "Campus d'Orl\u00e9ans", "woe:placetype": 20, "woe:placetype_name": "POI", "woe:lang": "FRE", "iso:country": "FR", "meta:provider": ["geoplanet:7.3.1", "geoplanet:7.3.2", "geoplanet:7.4.0", "geoplanet:7.4.1", "geoplanet:7.5.1", "geoplanet:7.5.2", "geoplanet:7.6.0", "geoplanet:7.8.1", "geoplanet:7.9.0", "geoplanet:7.10.0", "geoplanet:8.0.0", "woeplanet:8.0.0"], "meta:indexed": "2020-08-20T20:54:07.906391", "meta:updated": "2020-08-22T01:53:30.201999", "woe:alias_FRE_V": ["Campus d'Orleans"], "woe:hierarchy": {"continent": 24865675, "country": 23424819, "town": 0, "planet": 1, "county": 12597141, "suburb": 0, "state": 7153314, "region": 0, "localadmin": 12650242}, "woe:timezone_id": 28350911, "woe:hash": "u092hm8wbj4q", "woe:centroid": [1.94527, 47.843899], "geom:latitude": 47.843899, "geom:longitude": 1.94527, "geom:hash": "u092hm8wbj4q", "woe:latitude": 47.843899, "geom:centroid": [1.94527, 47.843899], "woe:longitude": 1.94527, "woe:repo": "woeplanet-poi-fr"}, "geometry": {"coordinates": [1.94527, 47.843899], "type": "Point"}}