{"type": "Feature", "id": 22891187, "properties": {"woe:id": 22891187, "woe:parent_id": 575718, "woe:name": "Musee Alesia", "woe:placetype": 20, "woe:placetype_name": "POI", "woe:lang": "FRE", "iso:country": "FR", "meta:provider": ["geoplanet:7.3.1", "geoplanet:7.3.2", "geoplanet:7.4.0", "geoplanet:7.4.1", "geoplanet:7.5.1", "geoplanet:7.5.2", "geoplanet:7.6.0", "geoplanet:7.8.1", "geoplanet:7.9.0", "geoplanet:7.10.0", "geoplanet:8.0.0", "woeplanet:8.0.0"], "meta:indexed": "2020-08-20T20:54:05.978144", "meta:updated": "2020-08-22T01:53:29.498075", "woe:hierarchy": {"continent": 24865675, "country": 23424819, "town": 0, "planet": 1, "county": 12597144, "suburb": 0, "state": 7153312, "region": 0, "localadmin": 12636898}, "woe:timezone_id": 28350911, "woe:hash": "u07nqjbu2fh3", "woe:centroid": [4.48349, 47.537209], "geom:latitude": 47.537209, "geom:longitude": 4.48349, "geom:hash": "u07nqjbu2fh3", "woe:latitude": 47.537209, "geom:centroid": [4.48349, 47.537209], "woe:longitude": 4.48349, "woe:repo": "woeplanet-poi-fr"}, "geometry": {"coordinates": [4.48349, 47.537209], "type": "Point"}}