{"type": "Feature", "id": 55863273, "geometry": {"type": "Point", "coordinates": [2.4519, 48.634521]}, "properties": {"woe:id": 55863273, "woe:parent_id": 590398, "woe:name": "RER-\u00c9vry", "woe:placetype": 20, "woe:placetype_name": "POI", "woe:lang": "FRE", "iso:country": "FR", "meta:provider": ["geoplanet:7.3.1", "geoplanet:7.3.2", "geoplanet:7.4.0", "geoplanet:7.4.1", "geoplanet:7.5.1", "geoplanet:7.5.2", "geoplanet:7.6.0", "geoplanet:7.8.1", "geoplanet:7.9.0", "geoplanet:7.10.0", "geoplanet:8.0.0", "woeplanet:8.0.0"], "meta:indexed": "2020-08-20T20:54:07.469735", "woe:alias_ENG_V": ["Evry Railway Station"], "woe:alias_ENG_P": ["Evry Station"], "meta:updated": "2020-10-14T11:52:04.863783", "woe:alias_FRE_S": ["Gare Evry", "RER-Evry", "Gare de Evry"], "woe:alias_FRE_V": ["Gare de \u00c9vry", "Gare \u00c9vry"], "woe:hierarchy": {"continent": 24865675, "country": 23424819, "town": 0, "planet": 1, "county": 12597118, "suburb": 0, "state": 7153319, "region": 0, "localadmin": 12643588}, "woe:timezone_id": 28350911, "woe:hash": "u09sxv9kt7v4", "woe:centroid": [2.4519, 48.634521], "geom:latitude": 48.634521, "geom:longitude": 2.4519, "geom:hash": "u09sxv9kt7v4", "woe:latitude": 48.634521, "geom:centroid": [2.4519, 48.634521], "woe:longitude": 2.4519, "woe:repo": "woeplanet-poi-fr", "geom:area": 0.0, "woe:scale": 19}}