{"type": "Feature", "id": 22893041, "properties": {"woe:id": 22893041, "woe:parent_id": 591001, "woe:name": "Gare de Fismes", "woe:placetype": 20, "woe:placetype_name": "POI", "woe:lang": "FRE", "iso:country": "FR", "meta:provider": ["geoplanet:7.3.1", "geoplanet:7.3.2", "geoplanet:7.4.0", "geoplanet:7.4.1", "geoplanet:7.5.1", "geoplanet:7.5.2", "geoplanet:7.6.0", "geoplanet:7.8.1", "geoplanet:7.9.0", "geoplanet:7.10.0", "geoplanet:8.0.0", "woeplanet:8.0.0"], "meta:indexed": "2020-08-20T20:54:06.029180", "woe:alias_ENG_V": ["Fismes Railway Station"], "meta:updated": "2020-08-22T01:53:29.519965", "woe:alias_ENG_P": ["Fismes Station"], "woe:alias_FRE_V": ["Gare Fismes"], "woe:hierarchy": {"continent": 24865675, "country": 23424819, "town": 0, "planet": 1, "county": 12597123, "suburb": 0, "state": 7153315, "region": 0, "localadmin": 12643801}, "woe:timezone_id": 28350911, "woe:hash": "u0f8eb9qb8cq", "woe:centroid": [3.68216, 49.310551], "geom:latitude": 49.310551, "geom:longitude": 3.68216, "geom:hash": "u0f8eb9qb8cq", "woe:latitude": 49.310551, "geom:centroid": [3.68216, 49.310551], "woe:longitude": 3.68216, "woe:repo": "woeplanet-poi-fr"}, "geometry": {"coordinates": [3.68216, 49.310551], "type": "Point"}}