{"type": "Feature", "id": 22865697, "properties": {"woe:id": 22865697, "woe:parent_id": 625918, "woe:name": "La Gare de Saint-M\u00e9dard-sur-Ille", "woe:placetype": 20, "woe:placetype_name": "POI", "woe:lang": "FRE", "iso:country": "FR", "meta:provider": ["geoplanet:7.3.1", "geoplanet:7.3.2", "geoplanet:7.4.0", "geoplanet:7.4.1", "geoplanet:7.5.1", "geoplanet:7.5.2", "geoplanet:7.6.0", "geoplanet:7.8.1", "geoplanet:7.9.0", "geoplanet:7.10.0", "geoplanet:8.0.0", "woeplanet:8.0.0"], "meta:indexed": "2020-08-20T20:54:05.360254", "woe:alias_ENG_V": ["La Saint-Medard-sur-Ille Railway Station"], "meta:updated": "2020-08-22T01:53:29.257838", "woe:alias_ENG_P": ["La Saint-Medard-sur-Ille Station"], "woe:alias_FRE_S": ["La Gare de Saint-Medard-sur-Ille"], "woe:hierarchy": {"continent": 24865675, "country": 23424819, "town": 0, "planet": 1, "county": 12597138, "suburb": 0, "state": 7153313, "region": 0, "localadmin": 12652963}, "woe:timezone_id": 28350911, "woe:hash": "gbwfdh1gjb13", "woe:centroid": [-1.66727, 48.274441], "geom:latitude": 48.274441, "geom:longitude": -1.66727, "geom:hash": "gbwfdh1gjb13", "woe:latitude": 48.274441, "geom:centroid": [-1.66727, 48.274441], "woe:longitude": -1.66727, "woe:repo": "woeplanet-poi-fr"}, "geometry": {"coordinates": [-1.66727, 48.274441], "type": "Point"}}