{"type": "Feature", "id": 22879868, "geometry": {"type": "Point", "coordinates": [2.76892, 43.20018]}, "properties": {"woe:id": 22879868, "woe:parent_id": 607922, "woe:name": "Gare de Lezignon Corbi\u00e9res", "woe:placetype": 20, "woe:placetype_name": "POI", "woe:lang": "FRE", "iso:country": "FR", "meta:provider": ["geoplanet:7.3.1", "geoplanet:7.3.2", "geoplanet:7.4.0", "geoplanet:7.4.1", "geoplanet:7.5.1", "geoplanet:7.5.2", "geoplanet:7.6.0", "geoplanet:7.8.1", "geoplanet:7.9.0", "geoplanet:7.10.0", "geoplanet:8.0.0", "woeplanet:8.0.0"], "meta:indexed": "2020-08-20T20:54:05.699484", "woe:alias_ENG_V": ["Lezignon Corbieres Railway Station"], "woe:alias_ENG_P": ["Lezignon Corbieres Station"], "meta:updated": "2020-10-14T11:52:12.347342", "woe:alias_FRE_S": ["Gare Lezignon Corbieres", "Gare Lezignan-Corbieres", "Gare de Lezignon Corbieres", "Gare de Lezignan-Corbieres"], "woe:alias_FRE_V": ["Gare L\u00e9zignan-Corbi\u00e8res", "Gare de L\u00e9zignan-Corbi\u00e8res", "Gare Lezignon Corbi\u00e9res"], "woe:hierarchy": {"continent": 24865675, "country": 23424819, "town": 0, "planet": 1, "county": 12597198, "suburb": 0, "state": 7153320, "region": 0, "localadmin": 12665601}, "woe:timezone_id": 28350911, "woe:hash": "sp9vz027290r", "woe:centroid": [2.76892, 43.20018], "geom:latitude": 43.20018, "geom:longitude": 2.76892, "geom:hash": "sp9vz027290r", "woe:latitude": 43.20018, "geom:centroid": [2.76892, 43.20018], "woe:longitude": 2.76892, "woe:repo": "woeplanet-poi-fr", "geom:area": 0.0, "woe:scale": 19}}