{"type": "Feature", "id": 22907817, "geometry": {"type": "Point", "coordinates": [2.34927, 48.87727]}, "properties": {"woe:id": 22907817, "woe:parent_id": 12638578, "woe:name": "M\u00e9tro-Poissonni\u00e8re", "woe:placetype": 20, "woe:placetype_name": "POI", "woe:lang": "FRE", "iso:country": "FR", "meta:provider": ["geoplanet:7.3.1", "geoplanet:7.3.2", "geoplanet:7.4.0", "geoplanet:7.4.1", "geoplanet:7.5.1", "geoplanet:7.5.2", "geoplanet:7.6.0", "geoplanet:7.8.1", "geoplanet:7.9.0", "geoplanet:7.10.0", "geoplanet:8.0.0", "woeplanet:8.0.0"], "meta:indexed": "2020-08-20T20:54:06.590872", "meta:updated": "2020-10-14T11:52:05.957437", "woe:alias_ENG_P": ["Poissonniere Metro Station"], "woe:alias_FRE_S": ["Metro-Poissonniere"], "woe:hierarchy": {"continent": 24865675, "country": 23424819, "town": 0, "planet": 1, "county": 12597155, "suburb": 0, "state": 7153319, "region": 0, "localadmin": 12638578}, "woe:timezone_id": 28350911, "woe:hash": "u09wj3ydtzw8", "woe:centroid": [2.34927, 48.87727], "geom:latitude": 48.87727, "geom:longitude": 2.34927, "geom:hash": "u09wj3ydtzw8", "woe:latitude": 48.87727, "geom:centroid": [2.34927, 48.87727], "woe:longitude": 2.34927, "woe:repo": "woeplanet-poi-fr", "geom:area": 0.0, "woe:scale": 19}}