{"type": "Feature", "id": 22913516, "geometry": {"type": "Point", "coordinates": [2.38256, 48.689129]}, "properties": {"woe:id": 22913516, "woe:parent_id": 55863490, "woe:name": "RER-Juvisy-sur-Orge", "woe:placetype": 20, "woe:placetype_name": "POI", "woe:lang": "FRE", "iso:country": "FR", "meta:provider": ["geoplanet:7.3.1", "geoplanet:7.3.2", "geoplanet:7.4.0", "geoplanet:7.4.1", "geoplanet:7.5.1", "geoplanet:7.5.2", "geoplanet:7.6.0", "geoplanet:7.8.1", "geoplanet:7.9.0", "geoplanet:7.10.0", "geoplanet:8.0.0", "woeplanet:8.0.0"], "meta:indexed": "2020-08-20T20:54:06.878965", "woe:alias_ENG_V": ["Juvisy-sur-Orge Railway Station"], "meta:updated": "2020-10-14T11:52:05.676626", "woe:alias_ENG_P": ["Juvisy-sur-Orge Station"], "woe:alias_FRE_V": ["Gare de Juvisy-sur-Orge", "Gare Juvisy-sur-Orge"], "woe:hierarchy": {"continent": 24865675, "country": 23424819, "town": 0, "planet": 1, "county": 12597118, "suburb": 0, "state": 7153319, "region": 0, "localadmin": 12645589}, "woe:timezone_id": 28350911, "woe:hash": "u09sypwftxmx", "woe:centroid": [2.38256, 48.689129], "geom:latitude": 48.689129, "geom:longitude": 2.38256, "geom:hash": "u09sypwftxmx", "woe:latitude": 48.689129, "geom:centroid": [2.38256, 48.689129], "woe:longitude": 2.38256, "woe:repo": "woeplanet-poi-fr", "geom:area": 0.0, "woe:scale": 19}}