{"type": "Feature", "id": 56060420, "geometry": {"type": "Point", "coordinates": [2.28663, 48.886311]}, "properties": {"woe:id": 56060420, "woe:parent_id": 55843839, "woe:name": "Negosup Paris", "woe:placetype": 20, "woe:placetype_name": "POI", "woe:lang": "FRE", "iso:country": "FR", "meta:provider": ["geoplanet:7.3.1", "geoplanet:7.3.2", "geoplanet:7.4.0", "geoplanet:7.4.1", "geoplanet:7.5.1", "geoplanet:7.5.2", "geoplanet:7.6.0", "geoplanet:7.8.1", "geoplanet:7.9.0", "geoplanet:7.10.0", "geoplanet:8.0.0", "woeplanet:8.0.0"], "meta:indexed": "2020-08-20T20:54:07.998020", "meta:updated": "2020-10-14T11:52:11.544895", "woe:hierarchy": {"continent": 24865675, "country": 23424819, "town": 0, "planet": 1, "county": 12597155, "suburb": 0, "state": 7153319, "region": 0, "localadmin": 12638223}, "woe:timezone_id": 28350911, "woe:hash": "u09wh53p6kfu", "woe:centroid": [2.28663, 48.886311], "geom:latitude": 48.886311, "geom:longitude": 2.28663, "geom:hash": "u09wh53p6kfu", "woe:latitude": 48.886311, "geom:centroid": [2.28663, 48.886311], "woe:longitude": 2.28663, "woe:repo": "woeplanet-poi-fr", "geom:area": 0.0, "woe:scale": 19}}