{"type": "Feature", "id": 56060081, "properties": {"woe:id": 56060081, "woe:parent_id": 582214, "woe:name": "\u00c9cole Sup. des Sciences Appliqu\u00e9es", "woe:placetype": 20, "woe:placetype_name": "POI", "woe:lang": "FRE", "iso:country": "FR", "meta:provider": ["geoplanet:7.3.1", "geoplanet:7.3.2", "geoplanet:7.4.0", "geoplanet:7.4.1", "geoplanet:7.5.1", "geoplanet:7.5.2", "geoplanet:7.6.0", "geoplanet:7.8.1", "geoplanet:7.9.0", "geoplanet:7.10.0", "geoplanet:8.0.0", "woeplanet:8.0.0"], "meta:indexed": "2020-08-20T20:54:07.698753", "meta:updated": "2020-08-22T01:53:30.128024", "woe:alias_FRE_V": ["Ecole Sup. des Sciences Appliquees"], "woe:hierarchy": {"continent": 24865675, "country": 23424819, "town": 0, "planet": 1, "county": 12597152, "suburb": 0, "state": 7153330, "region": 0, "localadmin": 12640071}, "woe:timezone_id": 28350911, "woe:hash": "u0mpw2ende5q", "woe:centroid": [7.31014, 47.728489], "geom:latitude": 47.728489, "geom:longitude": 7.31014, "geom:hash": "u0mpw2ende5q", "woe:latitude": 47.728489, "geom:centroid": [7.31014, 47.728489], "woe:longitude": 7.31014, "woe:repo": "woeplanet-poi-fr"}, "geometry": {"coordinates": [7.31014, 47.728489], "type": "Point"}}