{"type": "Feature", "id": 22918877, "geometry": {"type": "Point", "coordinates": [2.21728, 49.112141]}, "properties": {"woe:id": 22918877, "woe:parent_id": 596648, "woe:name": "Musee d'Art et d'Histoire Louis Senlecq", "woe:placetype": 20, "woe:placetype_name": "POI", "woe:lang": "FRE", "iso:country": "FR", "meta:provider": ["geoplanet:7.3.1", "geoplanet:7.3.2", "geoplanet:7.4.0", "geoplanet:7.4.1", "geoplanet:7.5.1", "geoplanet:7.5.2", "geoplanet:7.6.0", "geoplanet:7.8.1", "geoplanet:7.9.0", "geoplanet:7.10.0", "geoplanet:8.0.0", "woeplanet:8.0.0"], "meta:indexed": "2020-08-20T20:54:07.031156", "meta:updated": "2020-10-14T11:52:05.802386", "woe:hierarchy": {"continent": 24865675, "country": 23424819, "town": 0, "planet": 1, "county": 12597124, "suburb": 0, "state": 7153319, "region": 0, "localadmin": 12645824}, "woe:timezone_id": 28350911, "woe:hash": "u09x6kwdfqeu", "woe:centroid": [2.21728, 49.112141], "geom:latitude": 49.112141, "geom:longitude": 2.21728, "geom:hash": "u09x6kwdfqeu", "woe:latitude": 49.112141, "geom:centroid": [2.21728, 49.112141], "woe:longitude": 2.21728, "woe:repo": "woeplanet-poi-fr", "geom:area": 0.0, "woe:scale": 19}}