{"type": "Feature", "id": 22136669, "properties": {"woe:id": 22136669, "woe:parent_id": 585246, "woe:name": "Gare de Chaumont", "woe:placetype": 20, "woe:placetype_name": "POI", "woe:lang": "FRE", "iso:country": "FR", "meta:provider": ["geoplanet:7.3.1", "geoplanet:7.3.2", "geoplanet:7.4.0", "geoplanet:7.4.1", "geoplanet:7.5.1", "geoplanet:7.5.2", "geoplanet:7.6.0", "geoplanet:7.8.1", "geoplanet:7.9.0", "geoplanet:7.10.0", "geoplanet:8.0.0", "woeplanet:8.0.0"], "meta:indexed": "2020-08-20T20:54:04.713316", "woe:alias_ENG_V": ["Chaumont Railway Station"], "meta:updated": "2020-08-22T01:53:28.996434", "woe:alias_ENG_P": ["Chaumont Station"], "woe:alias_FRE_V": ["Gare Chaumont"], "woe:hierarchy": {"continent": 24865675, "country": 23424819, "town": 0, "planet": 1, "county": 12597145, "suburb": 0, "state": 7153315, "region": 0, "localadmin": 12640022}, "woe:timezone_id": 28350911, "woe:hash": "u0e9sy4s0zwz", "woe:centroid": [5.13409, 48.109859], "geom:latitude": 48.109859, "geom:longitude": 5.13409, "geom:hash": "u0e9sy4s0zwz", "woe:latitude": 48.109859, "geom:centroid": [5.13409, 48.109859], "woe:longitude": 5.13409, "woe:repo": "woeplanet-poi-fr"}, "geometry": {"coordinates": [5.13409, 48.109859], "type": "Point"}}