{"type": "Feature", "id": 22892221, "geometry": {"type": "Point", "coordinates": [5.9375, 47.227489]}, "properties": {"woe:id": 22892221, "woe:parent_id": 591906, "woe:name": "Gare de Franois", "woe:placetype": 20, "woe:placetype_name": "POI", "woe:lang": "FRE", "iso:country": "FR", "meta:provider": ["geoplanet:7.3.1", "geoplanet:7.3.2", "geoplanet:7.4.0", "geoplanet:7.4.1", "geoplanet:7.5.1", "geoplanet:7.5.2", "geoplanet:7.6.0", "geoplanet:7.8.1", "geoplanet:7.9.0", "geoplanet:7.10.0", "geoplanet:8.0.0", "woeplanet:8.0.0"], "meta:indexed": "2020-08-20T20:54:06.000775", "woe:alias_ENG_V": ["Franois Railway Station"], "meta:updated": "2020-10-14T11:52:11.666117", "woe:alias_ENG_P": ["Franois Station"], "woe:alias_FRE_V": ["Gare Franois"], "woe:hierarchy": {"continent": 24865675, "country": 23424819, "town": 0, "planet": 1, "county": 12597116, "suburb": 0, "state": 7153317, "region": 0, "localadmin": 12644138}, "woe:timezone_id": 28350911, "woe:hash": "u0khxje81f0c", "woe:centroid": [5.9375, 47.227489], "geom:latitude": 47.227489, "geom:longitude": 5.9375, "geom:hash": "u0khxje81f0c", "woe:latitude": 47.227489, "geom:centroid": [5.9375, 47.227489], "woe:longitude": 5.9375, "woe:repo": "woeplanet-poi-fr", "geom:area": 0.0, "woe:scale": 19}}