{"type": "Feature", "id": 22142490, "geometry": {"type": "Point", "coordinates": [6.16678, 49.137112]}, "properties": {"woe:id": 22142490, "woe:parent_id": 611317, "woe:name": "Gare de Metz-Nord", "woe:placetype": 20, "woe:placetype_name": "POI", "woe:lang": "FRE", "iso:country": "FR", "meta:provider": ["geoplanet:7.3.1", "geoplanet:7.3.2", "geoplanet:7.4.0", "geoplanet:7.4.1", "geoplanet:7.5.1", "geoplanet:7.5.2", "geoplanet:7.6.0", "geoplanet:7.8.1", "geoplanet:7.9.0", "geoplanet:7.10.0", "geoplanet:8.0.0", "woeplanet:8.0.0"], "meta:indexed": "2020-08-20T20:54:04.964156", "woe:alias_ENG_V": ["Metz-Nord Railway Station"], "meta:updated": "2020-10-14T11:52:04.987317", "woe:alias_ENG_P": ["Metz-Nord Station"], "woe:alias_FRE_V": ["Gare Metz-Nord"], "woe:hierarchy": {"continent": 24865675, "country": 23424819, "town": 0, "planet": 1, "county": 12597171, "suburb": 0, "state": 7153322, "region": 0, "localadmin": 12657410}, "woe:timezone_id": 28350911, "woe:hash": "u0srs34s2ms6", "woe:centroid": [6.16678, 49.137112], "geom:latitude": 49.137112, "geom:longitude": 6.16678, "geom:hash": "u0srs34s2ms6", "woe:latitude": 49.137112, "geom:centroid": [6.16678, 49.137112], "woe:longitude": 6.16678, "woe:repo": "woeplanet-poi-fr", "geom:area": 0.0, "woe:scale": 19}}