{"type": "Feature", "id": 22871306, "geometry": {"type": "Point", "coordinates": [-0.96249, 45.935638]}, "properties": {"woe:id": 22871306, "woe:parent_id": 619664, "woe:name": "Mus\u00e9e d'Art et d'Histoire de Rochefort", "woe:placetype": 20, "woe:placetype_name": "POI", "woe:lang": "FRE", "iso:country": "FR", "meta:provider": ["geoplanet:7.3.1", "geoplanet:7.3.2", "geoplanet:7.4.0", "geoplanet:7.4.1", "geoplanet:7.5.1", "geoplanet:7.5.2", "geoplanet:7.6.0", "geoplanet:7.8.1", "geoplanet:7.9.0", "geoplanet:7.10.0", "geoplanet:8.0.0", "woeplanet:8.0.0"], "meta:indexed": "2020-08-20T20:54:05.476902", "meta:updated": "2020-10-14T11:52:12.089212", "woe:alias_FRE_S": ["Musee d'Art et d'Histoire de Rochefort"], "woe:alias_FRE_V": ["Musee d'Art Et d'Histoire", "Mus\u00e9e d'Art Et d'Histoire"], "woe:hierarchy": {"continent": 24865675, "country": 23424819, "town": 0, "planet": 1, "county": 12597189, "suburb": 0, "state": 7153327, "region": 0, "localadmin": 12666364}, "woe:timezone_id": 28350911, "woe:hash": "gbpm6474kre6", "woe:centroid": [-0.96249, 45.935638], "geom:latitude": 45.935638, "geom:longitude": -0.96249, "geom:hash": "gbpm6474kre6", "woe:latitude": 45.935638, "geom:centroid": [-0.96249, 45.935638], "woe:longitude": -0.96249, "woe:repo": "woeplanet-poi-fr", "geom:area": 0.0, "woe:scale": 19}}