{"type": "Feature", "id": 22874761, "properties": {"woe:id": 22874761, "woe:parent_id": 600087, "woe:name": "Gare de la Teste-de-Buch", "woe:placetype": 20, "woe:placetype_name": "POI", "woe:lang": "FRE", "iso:country": "FR", "meta:provider": ["geoplanet:7.3.1", "geoplanet:7.3.2", "geoplanet:7.4.0", "geoplanet:7.4.1", "geoplanet:7.5.1", "geoplanet:7.5.2", "geoplanet:7.6.0", "geoplanet:7.8.1", "geoplanet:7.9.0", "geoplanet:7.10.0", "geoplanet:8.0.0", "woeplanet:8.0.0"], "meta:indexed": "2020-08-20T20:54:05.583093", "woe:alias_ENG_V": ["La Teste-de-Buch Railway Station"], "meta:updated": "2020-08-22T01:53:29.343993", "woe:alias_ENG_P": ["La Teste-de-Buch Station"], "woe:alias_FRE_V": ["Gare la Teste-de-Buch"], "woe:hierarchy": {"continent": 24865675, "country": 23424819, "town": 0, "planet": 1, "county": 12597132, "suburb": 0, "state": 7153309, "region": 0, "localadmin": 12640604}, "woe:timezone_id": 28350911, "woe:hash": "ezzjvvzs4ymj", "woe:centroid": [-1.14314, 44.636799], "geom:latitude": 44.636799, "geom:longitude": -1.14314, "geom:hash": "ezzjvvzs4ymj", "woe:latitude": 44.636799, "geom:centroid": [-1.14314, 44.636799], "woe:longitude": -1.14314, "woe:repo": "woeplanet-poi-fr"}, "geometry": {"coordinates": [-1.14314, 44.636799], "type": "Point"}}