{"type": "Feature", "id": 22143591, "geometry": {"type": "Point", "coordinates": [7.18809, 43.720451]}, "properties": {"woe:id": 22143591, "woe:parent_id": 608186, "woe:name": "Gare de Lingosti\u00e8re", "woe:placetype": 20, "woe:placetype_name": "POI", "woe:lang": "FRE", "iso:country": "FR", "meta:provider": ["geoplanet:7.3.1", "geoplanet:7.3.2", "geoplanet:7.4.0", "geoplanet:7.4.1", "geoplanet:7.5.1", "geoplanet:7.5.2", "geoplanet:7.6.0", "geoplanet:7.8.1", "geoplanet:7.9.0", "geoplanet:7.10.0", "geoplanet:8.0.0", "woeplanet:8.0.0"], "meta:indexed": "2020-08-20T20:54:05.021756", "woe:alias_ENG_V": ["Lingostiere Railway Station"], "woe:alias_ENG_P": ["Lingostiere Station"], "meta:updated": "2020-10-14T11:52:05.404791", "woe:alias_FRE_S": ["Gare de Lingostiere", "Gare Lingostiere"], "woe:alias_FRE_V": ["Gare Lingosti\u00e8re"], "woe:hierarchy": {"continent": 24865675, "country": 23424819, "town": 0, "planet": 1, "county": 12591800, "suburb": 0, "state": 7153328, "region": 0, "localadmin": 22755881}, "woe:timezone_id": 28350911, "woe:hash": "spv0ex44ndu2", "woe:centroid": [7.18809, 43.720451], "geom:latitude": 43.720451, "geom:longitude": 7.18809, "geom:hash": "spv0ex44ndu2", "woe:latitude": 43.720451, "geom:centroid": [7.18809, 43.720451], "woe:longitude": 7.18809, "woe:repo": "woeplanet-poi-fr", "geom:area": 0.0, "woe:scale": 19}}