{"type": "Feature", "id": 22892644, "properties": {"woe:id": 22892644, "woe:parent_id": 608609, "woe:name": "Mus\u00e9e des Beaux-Arts de Lons-le-Saunier", "woe:placetype": 20, "woe:placetype_name": "POI", "woe:lang": "FRE", "iso:country": "FR", "meta:provider": ["geoplanet:7.3.1", "geoplanet:7.3.2", "geoplanet:7.4.0", "geoplanet:7.4.1", "geoplanet:7.5.1", "geoplanet:7.5.2", "geoplanet:7.6.0", "geoplanet:7.8.1", "geoplanet:7.9.0", "geoplanet:7.10.0", "geoplanet:8.0.0", "woeplanet:8.0.0"], "meta:indexed": "2020-08-20T20:54:06.017297", "meta:updated": "2020-08-22T01:53:29.514347", "woe:alias_FRE_S": ["Musee des Beaux-Arts de Lons-le-Saunier"], "woe:hierarchy": {"continent": 24865675, "country": 23424819, "town": 0, "planet": 1, "county": 12597120, "suburb": 0, "state": 7153317, "region": 0, "localadmin": 12648399}, "woe:timezone_id": 28350911, "woe:hash": "u07cw3h5z00x", "woe:centroid": [5.55389, 46.67606], "geom:latitude": 46.67606, "geom:longitude": 5.55389, "geom:hash": "u07cw3h5z00x", "woe:latitude": 46.67606, "geom:centroid": [5.55389, 46.67606], "woe:longitude": 5.55389, "woe:repo": "woeplanet-poi-fr"}, "geometry": {"coordinates": [5.55389, 46.67606], "type": "Point"}}