{"type": "Feature", "id": 22889999, "properties": {"woe:id": 22889999, "woe:parent_id": 621571, "woe:name": "Mus\u00e9e de la Faune et de la Nature", "woe:placetype": 20, "woe:placetype_name": "POI", "woe:lang": "FRE", "iso:country": "FR", "meta:provider": ["geoplanet:7.3.1", "geoplanet:7.3.2", "geoplanet:7.4.0", "geoplanet:7.4.1", "geoplanet:7.5.1", "geoplanet:7.5.2", "geoplanet:7.6.0", "geoplanet:7.8.1", "geoplanet:7.9.0", "geoplanet:7.10.0", "geoplanet:8.0.0", "woeplanet:8.0.0"], "meta:indexed": "2020-08-20T20:54:05.936334", "meta:updated": "2020-08-22T01:53:29.481596", "woe:alias_FRE_S": ["Musee de la Faune et de la Nature"], "woe:hierarchy": {"continent": 24865675, "country": 23424819, "town": 0, "planet": 1, "county": 12597180, "suburb": 0, "state": 7153329, "region": 0, "localadmin": 12663412}, "woe:timezone_id": 28350911, "woe:hash": "u0hgd9rcp1kk", "woe:centroid": [6.8005, 45.62228], "geom:latitude": 45.62228, "geom:longitude": 6.8005, "geom:hash": "u0hgd9rcp1kk", "woe:latitude": 45.62228, "geom:centroid": [6.8005, 45.62228], "woe:longitude": 6.8005, "woe:repo": "woeplanet-poi-fr"}, "geometry": {"coordinates": [6.8005, 45.62228], "type": "Point"}}