{"type": "Feature", "id": 22875311, "geometry": {"type": "Point", "coordinates": [0.62031, 44.1926]}, "properties": {"woe:id": 22875311, "woe:parent_id": 575439, "woe:name": "Stade Armandie", "woe:placetype": 20, "woe:placetype_name": "POI", "woe:lang": "FRE", "iso:country": "FR", "meta:provider": ["geoplanet:7.4.0", "geoplanet:7.4.1", "geoplanet:7.5.1", "geoplanet:7.5.2", "geoplanet:7.6.0", "geoplanet:7.8.1", "geoplanet:7.9.0", "geoplanet:7.10.0", "geoplanet:8.0.0", "woeplanet:8.0.0"], "meta:indexed": "2020-08-21T00:28:27.331744", "meta:updated": "2020-10-14T11:52:11.598897", "woe:hierarchy": {"continent": 24865675, "country": 23424819, "town": 0, "planet": 1, "county": 12597143, "suburb": 0, "state": 7153309, "region": 0, "localadmin": 12636792}, "woe:timezone_id": 28350911, "woe:hash": "spb7qj58w38x", "woe:centroid": [0.62031, 44.1926], "geom:latitude": 44.1926, "geom:longitude": 0.62031, "geom:hash": "spb7qj58w38x", "woe:latitude": 44.1926, "geom:centroid": [0.62031, 44.1926], "woe:longitude": 0.62031, "woe:repo": "woeplanet-poi-fr", "geom:area": 0.0, "woe:scale": 19}}