{"type": "Feature", "id": 22885515, "properties": {"woe:id": 22885515, "woe:parent_id": 630100, "woe:name": "Mus\u00e9e Rural Montacurain", "woe:placetype": 20, "woe:placetype_name": "POI", "woe:lang": "FRE", "iso:country": "FR", "meta:provider": ["geoplanet:7.3.1", "geoplanet:7.3.2", "geoplanet:7.4.0", "geoplanet:7.4.1", "geoplanet:7.5.1", "geoplanet:7.5.2", "geoplanet:7.6.0", "geoplanet:7.8.1", "geoplanet:7.9.0", "geoplanet:7.10.0", "geoplanet:8.0.0", "woeplanet:8.0.0"], "meta:indexed": "2020-08-20T20:54:05.825123", "meta:updated": "2020-08-22T01:53:29.439417", "woe:alias_FRE_S": ["Musee Rural Montacurain"], "woe:hierarchy": {"continent": 24865675, "country": 23424819, "town": 0, "planet": 1, "county": 12597131, "suburb": 0, "state": 7153310, "region": 0, "localadmin": 20075080}, "woe:timezone_id": 28350911, "woe:hash": "u04rmrn058eq", "woe:centroid": [3.40317, 46.31287], "geom:latitude": 46.31287, "geom:longitude": 3.40317, "geom:hash": "u04rmrn058eq", "woe:latitude": 46.31287, "geom:centroid": [3.40317, 46.31287], "woe:longitude": 3.40317, "woe:repo": "woeplanet-poi-fr"}, "geometry": {"coordinates": [3.40317, 46.31287], "type": "Point"}}