{"type": "Feature", "id": 22907028, "properties": {"woe:id": 22907028, "woe:parent_id": 12654829, "woe:name": "Musee National de la Legion d'Honneur", "woe:placetype": 20, "woe:placetype_name": "POI", "woe:lang": "FRE", "iso:country": "FR", "meta:provider": ["geoplanet:7.3.1", "geoplanet:7.3.2", "geoplanet:7.4.0", "geoplanet:7.4.1", "geoplanet:7.5.1", "geoplanet:7.5.2", "geoplanet:7.6.0", "geoplanet:7.8.1", "geoplanet:7.9.0", "geoplanet:7.10.0", "geoplanet:8.0.0", "woeplanet:8.0.0"], "meta:indexed": "2020-08-20T20:54:06.552700", "meta:updated": "2020-08-22T01:53:29.714117", "woe:alias_FRE_V": ["Mus\u00e9e Nat. de la L\u00e9gion d'Honneur", "Musee Nat. de la Legion d'Honneur"], "woe:hierarchy": {"continent": 24865675, "country": 23424819, "town": 0, "planet": 1, "county": 12597155, "suburb": 0, "state": 7153319, "region": 0, "localadmin": 12654829}, "woe:timezone_id": 28350911, "woe:hash": "u09tuyubq369", "woe:centroid": [2.32491, 48.860371], "geom:latitude": 48.860371, "geom:longitude": 2.32491, "geom:hash": "u09tuyubq369", "woe:latitude": 48.860371, "geom:centroid": [2.32491, 48.860371], "woe:longitude": 2.32491, "woe:repo": "woeplanet-poi-fr"}, "geometry": {"coordinates": [2.32491, 48.860371], "type": "Point"}}