{"type": "Feature", "id": 22885947, "geometry": {"type": "Point", "coordinates": [2.19965, 44.706059]}, "properties": {"woe:id": 22885947, "woe:parent_id": 610633, "woe:name": "Gare de Maurs", "woe:placetype": 20, "woe:placetype_name": "POI", "woe:lang": "FRE", "iso:country": "FR", "meta:provider": ["geoplanet:7.3.1", "geoplanet:7.3.2", "geoplanet:7.4.0", "geoplanet:7.4.1", "geoplanet:7.5.1", "geoplanet:7.5.2", "geoplanet:7.6.0", "geoplanet:7.8.1", "geoplanet:7.9.0", "geoplanet:7.10.0", "geoplanet:8.0.0", "woeplanet:8.0.0"], "meta:indexed": "2020-08-20T20:54:05.831203", "woe:alias_ENG_V": ["Maurs Railway Station"], "meta:updated": "2020-10-14T11:52:12.109212", "woe:alias_ENG_P": ["Maurs Station"], "woe:alias_FRE_V": ["Gare Maurs"], "woe:hierarchy": {"continent": 24865675, "country": 23424819, "town": 0, "planet": 1, "county": 12597148, "suburb": 0, "state": 7153310, "region": 0, "localadmin": 12646382}, "woe:timezone_id": 28350911, "woe:hash": "spcw643xxt3v", "woe:centroid": [2.19965, 44.706059], "geom:latitude": 44.706059, "geom:longitude": 2.19965, "geom:hash": "spcw643xxt3v", "woe:latitude": 44.706059, "geom:centroid": [2.19965, 44.706059], "woe:longitude": 2.19965, "woe:repo": "woeplanet-poi-fr", "geom:area": 0.0, "woe:scale": 19}}