{"type": "Feature", "id": 55863102, "properties": {"woe:id": 55863102, "woe:parent_id": 579703, "woe:name": "Gare de Betton", "woe:placetype": 20, "woe:placetype_name": "POI", "woe:lang": "FRE", "iso:country": "FR", "meta:provider": ["geoplanet:7.3.1", "geoplanet:7.3.2", "geoplanet:7.4.0", "geoplanet:7.4.1", "geoplanet:7.5.1", "geoplanet:7.5.2", "geoplanet:7.6.0", "geoplanet:7.8.1", "geoplanet:7.9.0", "geoplanet:7.10.0", "geoplanet:8.0.0", "woeplanet:8.0.0"], "meta:indexed": "2020-08-20T20:54:07.322372", "woe:alias_ENG_V": ["Betton Railway Station"], "meta:updated": "2020-08-22T01:53:29.989953", "woe:alias_ENG_P": ["Betton Station"], "woe:alias_FRE_V": ["Gare Betton"], "woe:hierarchy": {"continent": 24865675, "country": 23424819, "town": 0, "planet": 1, "county": 12597138, "suburb": 0, "state": 7153313, "region": 0, "localadmin": 12638821}, "woe:timezone_id": 28350911, "woe:hash": "gbwf4g19b1d5", "woe:centroid": [-1.6349, 48.180851], "geom:latitude": 48.180851, "geom:longitude": -1.6349, "geom:hash": "gbwf4g19b1d5", "woe:latitude": 48.180851, "geom:centroid": [-1.6349, 48.180851], "woe:longitude": -1.6349, "woe:repo": "woeplanet-poi-fr"}, "geometry": {"coordinates": [-1.6349, 48.180851], "type": "Point"}}