{"type": "Feature", "id": 22873805, "geometry": {"type": "Point", "coordinates": [-0.56427, 44.856098]}, "properties": {"woe:id": 22873805, "woe:parent_id": 580778, "woe:name": "Vinorama Musee du Vin", "woe:placetype": 20, "woe:placetype_name": "POI", "woe:lang": "FRE", "iso:country": "FR", "meta:provider": ["geoplanet:7.3.1", "geoplanet:7.3.2", "geoplanet:7.4.0", "geoplanet:7.4.1", "geoplanet:7.5.1", "geoplanet:7.5.2", "geoplanet:7.6.0", "geoplanet:7.8.1", "geoplanet:7.9.0", "geoplanet:7.10.0", "geoplanet:8.0.0", "woeplanet:8.0.0"], "meta:indexed": "2020-08-20T20:54:05.558805", "meta:updated": "2020-10-14T11:52:11.940743", "woe:hierarchy": {"continent": 24865675, "country": 23424819, "town": 0, "planet": 1, "county": 12597132, "suburb": 0, "state": 7153309, "region": 0, "localadmin": 20074993}, "woe:timezone_id": 28350911, "woe:hash": "ezzx5jv1ew9z", "woe:centroid": [-0.56427, 44.856098], "geom:latitude": 44.856098, "geom:longitude": -0.56427, "geom:hash": "ezzx5jv1ew9z", "woe:latitude": 44.856098, "geom:centroid": [-0.56427, 44.856098], "woe:longitude": -0.56427, "woe:repo": "woeplanet-poi-fr", "geom:area": 0.0, "woe:scale": 19}}