{"type": "Feature", "id": 22145819, "geometry": {"type": "Point", "coordinates": [2.37604, 49.203079]}, "properties": {"woe:id": 22145819, "woe:parent_id": 617959, "woe:name": "Gare de Pr\u00e9cy-sur-Oise", "woe:placetype": 20, "woe:placetype_name": "POI", "woe:lang": "FRE", "iso:country": "FR", "meta:provider": ["geoplanet:7.3.1", "geoplanet:7.3.2", "geoplanet:7.4.0", "geoplanet:7.4.1", "geoplanet:7.5.1", "geoplanet:7.5.2", "geoplanet:7.6.0", "geoplanet:7.8.1", "geoplanet:7.9.0", "geoplanet:7.10.0", "geoplanet:8.0.0", "woeplanet:8.0.0"], "meta:indexed": "2020-08-20T20:54:05.098090", "woe:alias_ENG_V": ["Precy-sur-Oise Railway Station"], "woe:alias_ENG_P": ["Precy-sur-Oise Station"], "meta:updated": "2020-10-14T11:52:05.395759", "woe:alias_FRE_S": ["Gare de Precy-sur-Oise", "Gare Precy-sur-Oise"], "woe:alias_FRE_V": ["Gare Pr\u00e9cy-sur-Oise"], "woe:hierarchy": {"continent": 24865675, "country": 23424819, "town": 0, "planet": 1, "county": 12597158, "suburb": 0, "state": 7153326, "region": 0, "localadmin": 22757176}, "woe:timezone_id": 28350911, "woe:hash": "u09xyj4htwxy", "woe:centroid": [2.37604, 49.203079], "geom:latitude": 49.203079, "geom:longitude": 2.37604, "geom:hash": "u09xyj4htwxy", "woe:latitude": 49.203079, "geom:centroid": [2.37604, 49.203079], "woe:longitude": 2.37604, "woe:repo": "woeplanet-poi-fr", "geom:area": 0.0, "woe:scale": 19}}