{"type": "Feature", "id": 22910357, "properties": {"woe:id": 22910357, "woe:parent_id": 581316, "woe:name": "SNCF-Bourron-Marlotte-Grez", "woe:placetype": 20, "woe:placetype_name": "POI", "woe:lang": "FRE", "iso:country": "FR", "meta:provider": ["geoplanet:7.3.1", "geoplanet:7.3.2", "geoplanet:7.4.0", "geoplanet:7.4.1", "geoplanet:7.5.1", "geoplanet:7.5.2", "geoplanet:7.6.0", "geoplanet:7.8.1", "geoplanet:7.9.0", "geoplanet:7.10.0", "geoplanet:8.0.0", "woeplanet:8.0.0"], "meta:indexed": "2020-08-20T20:54:06.764586", "woe:alias_ENG_V": ["Bourron-Marlotte-Grez Railway Station"], "meta:updated": "2020-08-22T01:53:29.791598", "woe:alias_ENG_P": ["Bourron-Marlotte-Grez Station"], "woe:alias_FRE_V": ["Gare du Bourron-Marlotte-Grez", "Gare Bourron-Marlotte-Grez"], "woe:hierarchy": {"continent": 24865675, "country": 23424819, "town": 0, "planet": 1, "county": 12597137, "suburb": 0, "state": 7153319, "region": 0, "localadmin": 12639643}, "woe:timezone_id": 28350911, "woe:hash": "u09fvqb21zbb", "woe:centroid": [2.69207, 48.333019], "geom:latitude": 48.333019, "geom:longitude": 2.69207, "geom:hash": "u09fvqb21zbb", "woe:latitude": 48.333019, "geom:centroid": [2.69207, 48.333019], "woe:longitude": 2.69207, "woe:repo": "woeplanet-poi-fr"}, "geometry": {"coordinates": [2.69207, 48.333019], "type": "Point"}}