{"type": "Feature", "id": 22888938, "properties": {"woe:id": 22888938, "woe:parent_id": 24865736, "woe:name": "Funiculaire-Minimes-Th\u00e9atre Romain", "woe:placetype": 20, "woe:placetype_name": "POI", "woe:lang": "FRE", "iso:country": "FR", "meta:provider": ["geoplanet:7.3.1", "geoplanet:7.3.2", "geoplanet:7.4.0", "geoplanet:7.4.1", "geoplanet:7.5.1", "geoplanet:7.5.2", "geoplanet:7.6.0", "geoplanet:7.8.1", "geoplanet:7.9.0", "geoplanet:7.10.0", "geoplanet:8.0.0", "woeplanet:8.0.0"], "meta:indexed": "2020-08-20T20:54:05.909301", "meta:updated": "2020-08-22T01:53:29.470954", "woe:alias_FRE_S": ["Funiculaire-Minimes-Theatre Romain"], "woe:alias_FRE_V": ["Gare de Minimes", "Gare Minimes"], "woe:hierarchy": {"continent": 24865675, "country": 23424819, "town": 0, "planet": 1, "county": 12597185, "suburb": 0, "state": 7153329, "region": 0, "localadmin": 24865736}, "woe:timezone_id": 28350911, "woe:hash": "u05kmdnbtwcc", "woe:centroid": [4.82152, 45.758179], "geom:latitude": 45.758179, "geom:longitude": 4.82152, "geom:hash": "u05kmdnbtwcc", "woe:latitude": 45.758179, "geom:centroid": [4.82152, 45.758179], "woe:longitude": 4.82152, "woe:repo": "woeplanet-poi-fr"}, "geometry": {"coordinates": [4.82152, 45.758179], "type": "Point"}}