{"type": "Feature", "id": 22918225, "properties": {"woe:id": 22918225, "woe:parent_id": 55863620, "woe:name": "M\u00e9tro-B\u00e9rault", "woe:placetype": 20, "woe:placetype_name": "POI", "woe:lang": "FRE", "iso:country": "FR", "meta:provider": ["geoplanet:7.3.1", "geoplanet:7.3.2", "geoplanet:7.4.0", "geoplanet:7.4.1", "geoplanet:7.5.1", "geoplanet:7.5.2", "geoplanet:7.6.0", "geoplanet:7.8.1", "geoplanet:7.9.0", "geoplanet:7.10.0", "geoplanet:8.0.0", "woeplanet:8.0.0"], "meta:indexed": "2020-08-20T20:54:07.013800", "meta:updated": "2020-08-22T01:53:29.893961", "woe:alias_ENG_P": ["Berault Metro Station"], "woe:alias_FRE_S": ["Metro-Berault"], "woe:hierarchy": {"continent": 24865675, "country": 23424819, "town": 0, "planet": 1, "county": 12597151, "suburb": 0, "state": 7153319, "region": 0, "localadmin": 12654592}, "woe:timezone_id": 28350911, "woe:hash": "u09tzk0cq3fr", "woe:centroid": [2.42928, 48.84544], "geom:latitude": 48.84544, "geom:longitude": 2.42928, "geom:hash": "u09tzk0cq3fr", "woe:latitude": 48.84544, "geom:centroid": [2.42928, 48.84544], "woe:longitude": 2.42928, "woe:repo": "woeplanet-poi-fr"}, "geometry": {"coordinates": [2.42928, 48.84544], "type": "Point"}}