{"type": "Feature", "id": 22911036, "properties": {"woe:id": 22911036, "woe:parent_id": 613524, "woe:name": "SNCF-Mouroux", "woe:placetype": 20, "woe:placetype_name": "POI", "woe:lang": "FRE", "iso:country": "FR", "meta:provider": ["geoplanet:7.3.1", "geoplanet:7.3.2", "geoplanet:7.4.0", "geoplanet:7.4.1", "geoplanet:7.5.1", "geoplanet:7.5.2", "geoplanet:7.6.0", "geoplanet:7.8.1", "geoplanet:7.9.0", "geoplanet:7.10.0", "geoplanet:8.0.0", "woeplanet:8.0.0"], "meta:indexed": "2020-08-20T20:54:06.798506", "woe:alias_ENG_V": ["Mouroux Railway Station"], "meta:updated": "2020-08-22T01:53:29.807015", "woe:alias_ENG_P": ["Mouroux Station"], "woe:alias_FRE_V": ["Gare du Mouroux", "Gare Mouroux"], "woe:hierarchy": {"continent": 24865675, "country": 23424819, "town": 0, "planet": 1, "county": 12597137, "suburb": 0, "state": 7153319, "region": 0, "localadmin": 12649740}, "woe:timezone_id": 28350911, "woe:hash": "u0djtq2bqjx4", "woe:centroid": [3.04451, 48.813702], "geom:latitude": 48.813702, "geom:longitude": 3.04451, "geom:hash": "u0djtq2bqjx4", "woe:latitude": 48.813702, "geom:centroid": [3.04451, 48.813702], "woe:longitude": 3.04451, "woe:repo": "woeplanet-poi-fr"}, "geometry": {"coordinates": [3.04451, 48.813702], "type": "Point"}}