{"type": "Feature", "id": 22148240, "geometry": {"type": "Point", "coordinates": [6.04627, 43.190971]}, "properties": {"woe:id": 22148240, "woe:parent_id": 622323, "woe:name": "Gare de Solli\u00e8s-Pont", "woe:placetype": 20, "woe:placetype_name": "POI", "woe:lang": "FRE", "iso:country": "FR", "meta:provider": ["geoplanet:7.3.1", "geoplanet:7.3.2", "geoplanet:7.4.0", "geoplanet:7.4.1", "geoplanet:7.5.1", "geoplanet:7.5.2", "geoplanet:7.6.0", "geoplanet:7.8.1", "geoplanet:7.9.0", "geoplanet:7.10.0", "geoplanet:8.0.0", "woeplanet:8.0.0"], "meta:indexed": "2020-08-20T20:54:05.199271", "woe:alias_ENG_V": ["Sollies-Pont Railway Station"], "woe:alias_ENG_P": ["Sollies-Pont Station"], "meta:updated": "2020-10-14T11:52:05.100691", "woe:alias_FRE_S": ["Gare de Sollies-Pont", "Gare Sollies-Pont"], "woe:alias_FRE_V": ["Gare Solli\u00e8s-Pont"], "woe:hierarchy": {"continent": 24865675, "country": 23424819, "town": 0, "planet": 1, "county": 12597187, "suburb": 0, "state": 7153328, "region": 0, "localadmin": 12670348}, "woe:timezone_id": 28350911, "woe:hash": "spsm9wdv8k99", "woe:centroid": [6.04627, 43.190971], "geom:latitude": 43.190971, "geom:longitude": 6.04627, "geom:hash": "spsm9wdv8k99", "woe:latitude": 43.190971, "geom:centroid": [6.04627, 43.190971], "woe:longitude": 6.04627, "woe:repo": "woeplanet-poi-fr", "geom:area": 0.0, "woe:scale": 19}}