{"type": "Feature", "id": 55863083, "geometry": {"type": "Point", "coordinates": [-1.34684, 47.143398]}, "properties": {"woe:id": 55863083, "woe:parent_id": 603838, "woe:name": "Gare du Pallet", "woe:placetype": 20, "woe:placetype_name": "POI", "woe:lang": "FRE", "iso:country": "FR", "meta:provider": ["geoplanet:7.3.1", "geoplanet:7.3.2", "geoplanet:7.4.0", "geoplanet:7.4.1", "geoplanet:7.5.1", "geoplanet:7.5.2", "geoplanet:7.6.0", "geoplanet:7.8.1", "geoplanet:7.9.0", "geoplanet:7.10.0", "geoplanet:8.0.0", "woeplanet:8.0.0"], "meta:indexed": "2020-08-20T20:54:07.304508", "woe:alias_ENG_V": ["Pallet Railway Station"], "meta:updated": "2020-10-14T11:52:04.901266", "woe:alias_ENG_P": ["Pallet Station"], "woe:alias_FRE_V": ["Gare Pallet"], "woe:hierarchy": {"continent": 24865675, "country": 23424819, "town": 0, "planet": 1, "county": 12597177, "suburb": 0, "state": 7153325, "region": 0, "localadmin": 12664979}, "woe:timezone_id": 28350911, "woe:hash": "gbrh1q5q0q77", "woe:centroid": [-1.34684, 47.143398], "geom:latitude": 47.143398, "geom:longitude": -1.34684, "geom:hash": "gbrh1q5q0q77", "woe:latitude": 47.143398, "geom:centroid": [-1.34684, 47.143398], "woe:longitude": -1.34684, "woe:repo": "woeplanet-poi-fr", "geom:area": 0.0, "woe:scale": 19}}