{"type": "Feature", "id": 22900549, "properties": {"woe:id": 22900549, "woe:parent_id": 598125, "woe:name": "Mus\u00e9e Jeanne d'Aboville de la F\u00e8re", "woe:placetype": 20, "woe:placetype_name": "POI", "woe:lang": "FRE", "iso:country": "FR", "meta:provider": ["geoplanet:7.3.1", "geoplanet:7.3.2", "geoplanet:7.4.0", "geoplanet:7.4.1", "geoplanet:7.5.1", "geoplanet:7.5.2", "geoplanet:7.6.0", "geoplanet:7.8.1", "geoplanet:7.9.0", "geoplanet:7.10.0", "geoplanet:8.0.0", "woeplanet:8.0.0"], "meta:indexed": "2020-08-20T20:54:06.270967", "meta:updated": "2020-08-22T01:53:29.614760", "woe:alias_FRE_S": ["Musee Jeanne d'Aboville de la Fere"], "woe:hierarchy": {"continent": 24865675, "country": 23424819, "town": 0, "planet": 1, "county": 12597170, "suburb": 0, "state": 7153326, "region": 0, "localadmin": 22756703}, "woe:timezone_id": 28350911, "woe:hash": "u0f6s8t15vsw", "woe:centroid": [3.36885, 49.661152], "geom:latitude": 49.661152, "geom:longitude": 3.36885, "geom:hash": "u0f6s8t15vsw", "woe:latitude": 49.661152, "geom:centroid": [3.36885, 49.661152], "woe:longitude": 3.36885, "woe:repo": "woeplanet-poi-fr"}, "geometry": {"coordinates": [3.36885, 49.661152], "type": "Point"}}