{"type": "Feature", "id": 22871203, "geometry": {"type": "Point", "coordinates": [-0.44154, 45.439121]}, "properties": {"woe:id": 22871203, "woe:parent_id": 595588, "woe:name": "Gare de Jonzac", "woe:placetype": 20, "woe:placetype_name": "POI", "woe:lang": "FRE", "iso:country": "FR", "meta:provider": ["geoplanet:7.3.1", "geoplanet:7.3.2", "geoplanet:7.4.0", "geoplanet:7.4.1", "geoplanet:7.5.1", "geoplanet:7.5.2", "geoplanet:7.6.0", "geoplanet:7.8.1", "geoplanet:7.9.0", "geoplanet:7.10.0", "geoplanet:8.0.0", "woeplanet:8.0.0"], "meta:indexed": "2020-08-20T20:54:05.474946", "woe:alias_ENG_V": ["Jonzac Railway Station"], "meta:updated": "2020-10-14T11:52:11.740104", "woe:alias_ENG_P": ["Jonzac Station"], "woe:alias_FRE_V": ["Gare Jonzac"], "woe:hierarchy": {"continent": 24865675, "country": 23424819, "town": 0, "planet": 1, "county": 12597189, "suburb": 0, "state": 7153327, "region": 0, "localadmin": 12663069}, "woe:timezone_id": 28350911, "woe:hash": "gbpdmzyqp65f", "woe:centroid": [-0.44154, 45.439121], "geom:latitude": 45.439121, "geom:longitude": -0.44154, "geom:hash": "gbpdmzyqp65f", "woe:latitude": 45.439121, "geom:centroid": [-0.44154, 45.439121], "woe:longitude": -0.44154, "woe:repo": "woeplanet-poi-fr", "geom:area": 0.0, "woe:scale": 19}}