{"type": "Feature", "id": 22914323, "geometry": {"type": "Point", "coordinates": [2.25787, 48.913319]}, "properties": {"woe:id": 22914323, "woe:parent_id": 55863428, "woe:name": "SNCF-Les Vall\u00e9es", "woe:placetype": 20, "woe:placetype_name": "POI", "woe:lang": "FRE", "iso:country": "FR", "meta:provider": ["geoplanet:7.3.1", "geoplanet:7.3.2", "geoplanet:7.4.0", "geoplanet:7.4.1", "geoplanet:7.5.1", "geoplanet:7.5.2", "geoplanet:7.6.0", "geoplanet:7.8.1", "geoplanet:7.9.0", "geoplanet:7.10.0", "geoplanet:8.0.0", "woeplanet:8.0.0"], "meta:indexed": "2020-08-20T20:54:06.900810", "woe:alias_ENG_V": ["Les Vallees Railway Station"], "woe:alias_ENG_P": ["Les Vallees Station"], "meta:updated": "2020-10-14T11:52:05.776892", "woe:alias_FRE_S": ["Gare Les Vallees", "SNCF-Les Vallees", "Gare du Les Vallees"], "woe:alias_FRE_V": ["Gare du Les Vall\u00e9es", "Gare Les Vall\u00e9es"], "woe:hierarchy": {"continent": 24865675, "country": 23424819, "town": 0, "planet": 1, "county": 15022631, "suburb": 0, "state": 7153319, "region": 0, "localadmin": 12646767}, "woe:timezone_id": 28350911, "woe:hash": "u09w72khsptc", "woe:centroid": [2.25787, 48.913319], "geom:latitude": 48.913319, "geom:longitude": 2.25787, "geom:hash": "u09w72khsptc", "woe:latitude": 48.913319, "geom:centroid": [2.25787, 48.913319], "woe:longitude": 2.25787, "woe:repo": "woeplanet-poi-fr", "geom:area": 0.0, "woe:scale": 19}}