{"type": "Feature", "id": 22914235, "geometry": {"type": "Point", "coordinates": [2.29492, 48.91613]}, "properties": {"woe:id": 22914235, "woe:parent_id": 55863417, "woe:name": "M\u00e9tro-Gabriel P\u00e9ri-Asni\u00e8res-Gennevilliers", "woe:placetype": 20, "woe:placetype_name": "POI", "woe:lang": "FRE", "iso:country": "FR", "meta:provider": ["geoplanet:7.3.1", "geoplanet:7.3.2", "geoplanet:7.4.0", "geoplanet:7.4.1", "geoplanet:7.5.1", "geoplanet:7.5.2", "geoplanet:7.6.0", "geoplanet:7.8.1", "geoplanet:7.9.0", "geoplanet:7.10.0", "geoplanet:8.0.0", "woeplanet:8.0.0"], "meta:indexed": "2020-08-20T20:54:06.899956", "meta:updated": "2020-10-14T11:52:06.223157", "woe:alias_ENG_P": ["Gabriel Peri-Asnieres-Gennevilliers Metro Station"], "woe:alias_FRE_S": ["Metro-Gabriel Peri-Asnieres-Gennevilliers"], "woe:hierarchy": {"continent": 24865675, "country": 23424819, "town": 0, "planet": 1, "county": 15022631, "suburb": 0, "state": 7153319, "region": 0, "localadmin": 12637505}, "woe:timezone_id": 28350911, "woe:hash": "u09wk0zj5e83", "woe:centroid": [2.29492, 48.91613], "geom:latitude": 48.91613, "geom:longitude": 2.29492, "geom:hash": "u09wk0zj5e83", "woe:latitude": 48.91613, "geom:centroid": [2.29492, 48.91613], "woe:longitude": 2.29492, "woe:repo": "woeplanet-poi-fr", "geom:area": 0.0, "woe:scale": 19}}