{"type": "Feature", "id": 22908853, "geometry": {"type": "Point", "coordinates": [2.31783, 48.844559]}, "properties": {"woe:id": 22908853, "woe:parent_id": 12644806, "woe:name": "M\u00e9tro-Falgui\u00e8re", "woe:placetype": 20, "woe:placetype_name": "POI", "woe:lang": "FRE", "iso:country": "FR", "meta:provider": ["geoplanet:7.3.1", "geoplanet:7.3.2", "geoplanet:7.4.0", "geoplanet:7.4.1", "geoplanet:7.5.1", "geoplanet:7.5.2", "geoplanet:7.6.0", "geoplanet:7.8.1", "geoplanet:7.9.0", "geoplanet:7.10.0", "geoplanet:8.0.0", "woeplanet:8.0.0"], "meta:indexed": "2020-08-20T20:54:06.668766", "meta:updated": "2020-10-14T11:52:05.713470", "woe:alias_ENG_P": ["Falguiere Metro Station"], "woe:alias_FRE_S": ["Metro-Falguiere"], "woe:hierarchy": {"continent": 24865675, "country": 23424819, "town": 0, "planet": 1, "county": 12597155, "suburb": 0, "state": 7153319, "region": 0, "localadmin": 12644806}, "woe:timezone_id": 28350911, "woe:hash": "u09tuezu1mer", "woe:centroid": [2.31783, 48.844559], "geom:latitude": 48.844559, "geom:longitude": 2.31783, "geom:hash": "u09tuezu1mer", "woe:latitude": 48.844559, "geom:centroid": [2.31783, 48.844559], "woe:longitude": 2.31783, "woe:repo": "woeplanet-poi-fr", "geom:area": 0.0, "woe:scale": 19}}