{"type": "Feature", "id": 22138888, "properties": {"woe:id": 22138888, "woe:parent_id": 593797, "woe:name": "Gare de Grigny", "woe:placetype": 20, "woe:placetype_name": "POI", "woe:lang": "FRE", "iso:country": "FR", "meta:provider": ["geoplanet:7.3.1", "geoplanet:7.3.2", "geoplanet:7.4.0", "geoplanet:7.4.1", "geoplanet:7.5.1", "geoplanet:7.5.2", "geoplanet:7.6.0", "geoplanet:7.8.1", "geoplanet:7.9.0", "geoplanet:7.10.0", "geoplanet:8.0.0", "woeplanet:8.0.0"], "meta:indexed": "2020-08-20T20:54:04.805691", "woe:alias_ENG_V": ["Grigny Railway Station"], "meta:updated": "2020-08-22T01:53:29.037165", "woe:alias_ENG_P": ["Grigny Station"], "woe:alias_FRE_V": ["Gare Grigny"], "woe:hierarchy": {"continent": 24865675, "country": 23424819, "town": 0, "planet": 1, "county": 12597185, "suburb": 0, "state": 7153329, "region": 0, "localadmin": 22756628}, "woe:timezone_id": 28350911, "woe:hash": "u057mns0z0v7", "woe:centroid": [4.79584, 45.607128], "geom:latitude": 45.607128, "geom:longitude": 4.79584, "geom:hash": "u057mns0z0v7", "woe:latitude": 45.607128, "geom:centroid": [4.79584, 45.607128], "woe:longitude": 4.79584, "woe:repo": "woeplanet-poi-fr"}, "geometry": {"coordinates": [4.79584, 45.607128], "type": "Point"}}