{"type": "Feature", "id": 22913087, "properties": {"woe:id": 22913087, "woe:parent_id": 579908, "woe:name": "Maison Litteraire de Victor Hugo", "woe:placetype": 20, "woe:placetype_name": "POI", "woe:lang": "FRE", "iso:country": "FR", "meta:provider": ["geoplanet:7.3.1", "geoplanet:7.3.2", "geoplanet:7.4.0", "geoplanet:7.4.1", "geoplanet:7.5.1", "geoplanet:7.5.2", "geoplanet:7.6.0", "geoplanet:7.8.1", "geoplanet:7.9.0", "geoplanet:7.10.0", "geoplanet:8.0.0", "woeplanet:8.0.0"], "meta:indexed": "2020-08-20T20:54:06.856622", "meta:updated": "2020-08-22T01:53:29.829533", "woe:hierarchy": {"continent": 24865675, "country": 23424819, "town": 0, "planet": 1, "county": 12597118, "suburb": 0, "state": 7153319, "region": 0, "localadmin": 12638922}, "woe:timezone_id": 28350911, "woe:hash": "u09t6h51s54p", "woe:centroid": [2.20156, 48.757599], "geom:latitude": 48.757599, "geom:longitude": 2.20156, "geom:hash": "u09t6h51s54p", "woe:latitude": 48.757599, "geom:centroid": [2.20156, 48.757599], "woe:longitude": 2.20156, "woe:repo": "woeplanet-poi-fr"}, "geometry": {"coordinates": [2.20156, 48.757599], "type": "Point"}}