{"type": "Feature", "id": 56059931, "geometry": {"type": "Point", "coordinates": [1.37823, 43.595909]}, "properties": {"woe:id": 56059931, "woe:parent_id": 601484, "woe:name": "\u00c9cole Nationale du Cadastre", "woe:placetype": 20, "woe:placetype_name": "POI", "woe:lang": "FRE", "iso:country": "FR", "meta:provider": ["geoplanet:7.3.1", "geoplanet:7.3.2", "geoplanet:7.4.0", "geoplanet:7.4.1", "geoplanet:7.5.1", "geoplanet:7.5.2", "geoplanet:7.6.0", "geoplanet:7.8.1", "geoplanet:7.9.0", "geoplanet:7.10.0", "geoplanet:8.0.0", "woeplanet:8.0.0"], "meta:indexed": "2020-08-20T20:54:07.564511", "meta:updated": "2020-10-14T11:52:11.148007", "woe:alias_FRE_V": ["Ecole Nationale du Cadastre"], "woe:hierarchy": {"continent": 24865675, "country": 23424819, "town": 0, "planet": 1, "county": 12597186, "suburb": 0, "state": 7153323, "region": 0, "localadmin": 12657325}, "woe:timezone_id": 28350911, "woe:hash": "spbbp27se46y", "woe:centroid": [1.37823, 43.595909], "geom:latitude": 43.595909, "geom:longitude": 1.37823, "geom:hash": "spbbp27se46y", "woe:latitude": 43.595909, "geom:centroid": [1.37823, 43.595909], "woe:longitude": 1.37823, "woe:repo": "woeplanet-poi-fr", "geom:area": 0.0, "woe:scale": 19}}