{"type": "Feature", "id": 29333624, "properties": {"woe:id": 29333624, "woe:parent_id": 12651012, "woe:name": "Porte Brunet", "woe:placetype": 20, "woe:placetype_name": "POI", "woe:lang": "FRE", "iso:country": "FR", "meta:provider": ["geoplanet:7.3.1", "geoplanet:7.3.2", "geoplanet:7.4.0", "geoplanet:7.4.1", "geoplanet:7.5.1", "geoplanet:7.5.2", "geoplanet:7.6.0", "geoplanet:7.8.1", "geoplanet:7.9.0", "geoplanet:7.10.0", "geoplanet:8.0.0", "woeplanet:8.0.0"], "meta:indexed": "2020-08-20T20:54:07.121466", "meta:updated": "2020-08-22T01:53:29.915299", "woe:hierarchy": {"continent": 24865675, "country": 23424819, "town": 0, "planet": 1, "county": 12597155, "suburb": 0, "state": 7153319, "region": 0, "localadmin": 12651012}, "woe:timezone_id": 28350911, "woe:hash": "u09wne4b8g1q", "woe:centroid": [2.39883, 48.88377], "geom:latitude": 48.88377, "geom:longitude": 2.39883, "geom:hash": "u09wne4b8g1q", "woe:latitude": 48.88377, "geom:centroid": [2.39883, 48.88377], "woe:longitude": 2.39883, "woe:repo": "woeplanet-poi-fr"}, "geometry": {"coordinates": [2.39883, 48.88377], "type": "Point"}}