{"type": "Feature", "id": 56060655, "properties": {"woe:id": 56060655, "woe:parent_id": 579854, "woe:name": "\u00c9cole Sup. des Tech. Ind. Avanc\u00e9es", "woe:placetype": 20, "woe:placetype_name": "POI", "woe:lang": "FRE", "iso:country": "FR", "meta:provider": ["geoplanet:7.3.1", "geoplanet:7.3.2", "geoplanet:7.4.0", "geoplanet:7.4.1", "geoplanet:7.5.1", "geoplanet:7.5.2", "geoplanet:7.6.0", "geoplanet:7.8.1", "geoplanet:7.9.0", "geoplanet:7.10.0", "geoplanet:8.0.0", "woeplanet:8.0.0"], "meta:indexed": "2020-08-20T20:54:08.210515", "meta:updated": "2020-08-22T01:53:30.309806", "woe:alias_FRE_V": ["Ecole Sup. des Tech. Ind. Avancees"], "woe:hierarchy": {"continent": 24865675, "country": 23424819, "town": 0, "planet": 1, "county": 12597114, "suburb": 0, "state": 7153309, "region": 0, "localadmin": 20075004}, "woe:timezone_id": 28350911, "woe:hash": "ezwzht5ynwrm", "woe:centroid": [-1.55462, 43.446499], "geom:latitude": 43.446499, "geom:longitude": -1.55462, "geom:hash": "ezwzht5ynwrm", "woe:latitude": 43.446499, "geom:centroid": [-1.55462, 43.446499], "woe:longitude": -1.55462, "woe:repo": "woeplanet-poi-fr"}, "geometry": {"coordinates": [-1.55462, 43.446499], "type": "Point"}}