{"type": "Feature", "id": 55863070, "geometry": {"type": "Point", "coordinates": [6.50643, 43.969891]}, "properties": {"woe:id": 55863070, "woe:parent_id": 622961, "woe:name": "Gare de Saint-Andr\u00e9-Les-Alpes", "woe:placetype": 20, "woe:placetype_name": "POI", "woe:lang": "FRE", "iso:country": "FR", "meta:provider": ["geoplanet:7.3.1", "geoplanet:7.3.2", "geoplanet:7.4.0", "geoplanet:7.4.1", "geoplanet:7.5.1", "geoplanet:7.5.2", "geoplanet:7.6.0", "geoplanet:7.8.1", "geoplanet:7.9.0", "geoplanet:7.10.0", "geoplanet:8.0.0", "woeplanet:8.0.0"], "meta:indexed": "2020-08-20T20:54:07.292845", "woe:alias_ENG_V": ["Saint-Andre-Les-Alpes Railway Station"], "woe:alias_ENG_P": ["Saint-Andre-Les-Alpes Station"], "meta:updated": "2020-10-14T11:52:04.924064", "woe:alias_FRE_S": ["Gare de Saint-Andre-Les-Alpes", "Gare Saint-Andre-Les-Alpes"], "woe:alias_FRE_V": ["Gare Saint-Andr\u00e9-Les-Alpes"], "woe:hierarchy": {"continent": 24865675, "country": 23424819, "town": 0, "planet": 1, "county": 12597191, "suburb": 0, "state": 7153328, "region": 0, "localadmin": 22756183}, "woe:timezone_id": 28350911, "woe:hash": "spudhh3z4vcb", "woe:centroid": [6.50643, 43.969891], "geom:latitude": 43.969891, "geom:longitude": 6.50643, "geom:hash": "spudhh3z4vcb", "woe:latitude": 43.969891, "geom:centroid": [6.50643, 43.969891], "woe:longitude": 6.50643, "woe:repo": "woeplanet-poi-fr", "geom:area": 0.0, "woe:scale": 19}}