{"type": "Feature", "id": 22874649, "properties": {"woe:id": 22874649, "woe:parent_id": 29331436, "woe:name": "Gare de Saint-\u00c9milion", "woe:placetype": 20, "woe:placetype_name": "POI", "woe:lang": "FRE", "iso:country": "FR", "meta:provider": ["geoplanet:7.3.1", "geoplanet:7.3.2", "geoplanet:7.4.0", "geoplanet:7.4.1", "geoplanet:7.5.1", "geoplanet:7.5.2", "geoplanet:7.6.0", "geoplanet:7.8.1", "geoplanet:7.9.0", "geoplanet:7.10.0", "geoplanet:8.0.0", "woeplanet:8.0.0"], "meta:indexed": "2020-08-20T20:54:05.575734", "woe:alias_ENG_V": ["Saint-Emilion Railway Station"], "woe:alias_ENG_P": ["Saint-Emilion Station"], "meta:updated": "2020-08-22T01:53:29.341374", "woe:alias_FRE_S": ["Gare Saint-Emilion", "Gare de Saint-Emilion"], "woe:alias_FRE_V": ["Gare Saint-\u00c9milion"], "woe:hierarchy": {"continent": 24865675, "country": 23424819, "town": 0, "planet": 1, "county": 12597132, "suburb": 0, "state": 7153309, "region": 0, "localadmin": 12652416}, "woe:timezone_id": 28350911, "woe:hash": "ezzzk67qyj5h", "woe:centroid": [-0.16007, 44.88171], "geom:latitude": 44.88171, "geom:longitude": -0.16007, "geom:hash": "ezzzk67qyj5h", "woe:latitude": 44.88171, "geom:centroid": [-0.16007, 44.88171], "woe:longitude": -0.16007, "woe:repo": "woeplanet-poi-fr"}, "geometry": {"coordinates": [-0.16007, 44.88171], "type": "Point"}}