{"type": "Feature", "id": 56060432, "properties": {"woe:id": 56060432, "woe:parent_id": 55843787, "woe:name": "Ensatt", "woe:placetype": 20, "woe:placetype_name": "POI", "woe:lang": "FRE", "iso:country": "FR", "meta:provider": ["geoplanet:7.3.1", "geoplanet:7.3.2", "geoplanet:7.4.0", "geoplanet:7.4.1", "geoplanet:7.5.1", "geoplanet:7.5.2", "geoplanet:7.6.0", "geoplanet:7.8.1", "geoplanet:7.9.0", "geoplanet:7.10.0", "geoplanet:8.0.0", "woeplanet:8.0.0"], "meta:indexed": "2020-08-20T20:54:08.010574", "meta:updated": "2020-08-22T01:53:30.239003", "woe:hierarchy": {"continent": 24865675, "country": 23424819, "town": 0, "planet": 1, "county": 12597155, "suburb": 0, "state": 7153319, "region": 0, "localadmin": 12654831}, "woe:timezone_id": 28350911, "woe:hash": "u09wj41sqerp", "woe:centroid": [2.33145, 48.878922], "geom:latitude": 48.878922, "geom:longitude": 2.33145, "geom:hash": "u09wj41sqerp", "woe:latitude": 48.878922, "geom:centroid": [2.33145, 48.878922], "woe:longitude": 2.33145, "woe:repo": "woeplanet-poi-fr"}, "geometry": {"coordinates": [2.33145, 48.878922], "type": "Point"}}