{"type": "Feature", "id": 22918435, "geometry": {"type": "Point", "coordinates": [2.4158, 48.994289]}, "properties": {"woe:id": 22918435, "woe:parent_id": 576680, "woe:name": "RER-Villiers-le-Bel-Gonesse", "woe:placetype": 20, "woe:placetype_name": "POI", "woe:lang": "FRE", "iso:country": "FR", "meta:provider": ["geoplanet:7.3.1", "geoplanet:7.3.2", "geoplanet:7.4.0", "geoplanet:7.4.1", "geoplanet:7.5.1", "geoplanet:7.5.2", "geoplanet:7.6.0", "geoplanet:7.8.1", "geoplanet:7.9.0", "geoplanet:7.10.0", "geoplanet:8.0.0", "woeplanet:8.0.0"], "meta:indexed": "2020-08-20T20:54:07.017850", "woe:alias_ENG_V": ["Villiers-le-Bel-Gonesse Railway Station"], "meta:updated": "2020-10-14T11:52:06.064806", "woe:alias_ENG_P": ["Villiers-le-Bel-Gonesse Station"], "woe:alias_FRE_V": ["Gare de Villiers-le-Bel-Gonesse", "Gare Villiers-le-Bel-Gonesse", "Gare de Villiers-Le Bel-Gonesse-Arnouville", "Gare Villiers-Le Bel-Gonesse-Arnouville"], "woe:hierarchy": {"continent": 24865675, "country": 23424819, "town": 0, "planet": 1, "county": 12597124, "suburb": 0, "state": 7153319, "region": 0, "localadmin": 12637400}, "woe:timezone_id": 28350911, "woe:hash": "u09wwzphkjrj", "woe:centroid": [2.4158, 48.994289], "geom:latitude": 48.994289, "geom:longitude": 2.4158, "geom:hash": "u09wwzphkjrj", "woe:latitude": 48.994289, "geom:centroid": [2.4158, 48.994289], "woe:longitude": 2.4158, "woe:repo": "woeplanet-poi-fr", "geom:area": 0.0, "woe:scale": 19}}