{"type": "Feature", "id": 29333646, "properties": {"woe:id": 29333646, "woe:parent_id": 12651011, "woe:name": "Porte de Montrouge", "woe:placetype": 20, "woe:placetype_name": "POI", "woe:lang": "FRE", "iso:country": "FR", "meta:provider": ["geoplanet:7.3.1", "geoplanet:7.3.2", "geoplanet:7.4.0", "geoplanet:7.4.1", "geoplanet:7.5.1", "geoplanet:7.5.2", "geoplanet:7.6.0", "geoplanet:7.8.1", "geoplanet:7.9.0", "geoplanet:7.10.0", "geoplanet:8.0.0", "woeplanet:8.0.0"], "meta:indexed": "2020-08-20T20:54:07.140532", "meta:updated": "2020-08-22T01:53:29.923765", "woe:hierarchy": {"continent": 24865675, "country": 23424819, "town": 0, "planet": 1, "county": 12597155, "suburb": 0, "state": 7153319, "region": 0, "localadmin": 12651011}, "woe:timezone_id": 28350911, "woe:hash": "u09tub5dnk0n", "woe:centroid": [2.32319, 48.823608], "geom:latitude": 48.823608, "geom:longitude": 2.32319, "geom:hash": "u09tub5dnk0n", "woe:latitude": 48.823608, "geom:centroid": [2.32319, 48.823608], "woe:longitude": 2.32319, "woe:repo": "woeplanet-poi-fr"}, "geometry": {"coordinates": [2.32319, 48.823608], "type": "Point"}}