{"type": "Feature", "id": 22905613, "properties": {"woe:id": 22905613, "woe:parent_id": 575319, "woe:name": "Ch\u00e2teau de Bagatelle", "woe:placetype": 20, "woe:placetype_name": "POI", "woe:lang": "FRE", "iso:country": "FR", "meta:provider": ["geoplanet:7.3.1", "geoplanet:7.3.2", "geoplanet:7.4.0", "geoplanet:7.4.1", "geoplanet:7.5.1", "geoplanet:7.5.2", "geoplanet:7.6.0", "geoplanet:7.8.1", "geoplanet:7.9.0", "geoplanet:7.10.0", "geoplanet:8.0.0", "woeplanet:8.0.0"], "meta:indexed": "2020-08-20T20:54:06.435199", "meta:updated": "2020-08-22T01:53:29.675964", "woe:alias_FRE_S": ["Chateau de Bagatelle"], "woe:alias_FRE_V": ["Ch\u00e2teau de Bagatelles", "Chateau de Bagatelles"], "woe:hierarchy": {"continent": 24865675, "country": 23424819, "town": 0, "planet": 1, "county": 12597178, "suburb": 0, "state": 7153326, "region": 0, "localadmin": 12654842}, "woe:timezone_id": 28350911, "woe:hash": "u0ckczts2vtc", "woe:centroid": [1.84231, 50.095669], "geom:latitude": 50.095669, "geom:longitude": 1.84231, "geom:hash": "u0ckczts2vtc", "woe:latitude": 50.095669, "geom:centroid": [1.84231, 50.095669], "woe:longitude": 1.84231, "woe:repo": "woeplanet-poi-fr"}, "geometry": {"coordinates": [1.84231, 50.095669], "type": "Point"}}