{"type": "Feature", "id": 22870975, "geometry": {"type": "Point", "coordinates": [-0.05037, 45.599628]}, "properties": {"woe:id": 22870975, "woe:parent_id": 584987, "woe:name": "Gare de Ch\u00e2teauneuf-sur-Charente", "woe:placetype": 20, "woe:placetype_name": "POI", "woe:lang": "FRE", "iso:country": "FR", "meta:provider": ["geoplanet:7.3.1", "geoplanet:7.3.2", "geoplanet:7.4.0", "geoplanet:7.4.1", "geoplanet:7.5.1", "geoplanet:7.5.2", "geoplanet:7.6.0", "geoplanet:7.8.1", "geoplanet:7.9.0", "geoplanet:7.10.0", "geoplanet:8.0.0", "woeplanet:8.0.0"], "meta:indexed": "2020-08-20T20:54:05.469066", "woe:alias_ENG_V": ["Chateauneuf-sur-Charente Railway Station"], "woe:alias_ENG_P": ["Chateauneuf-sur-Charente Station"], "meta:updated": "2020-10-14T11:52:12.358147", "woe:alias_FRE_S": ["Gare de Chateauneuf-sur-Charente", "Gare Chateauneuf-sur-Charente"], "woe:alias_FRE_V": ["Gare Ch\u00e2teauneuf-sur-Charente"], "woe:hierarchy": {"continent": 24865675, "country": 23424819, "town": 0, "planet": 1, "county": 12597157, "suburb": 0, "state": 7153327, "region": 0, "localadmin": 12659104}, "woe:timezone_id": 28350911, "woe:hash": "gbpgqv5m46c2", "woe:centroid": [-0.05037, 45.599628], "geom:latitude": 45.599628, "geom:longitude": -0.05037, "geom:hash": "gbpgqv5m46c2", "woe:latitude": 45.599628, "geom:centroid": [-0.05037, 45.599628], "woe:longitude": -0.05037, "woe:repo": "woeplanet-poi-fr", "geom:area": 0.0, "woe:scale": 19}}