{"type": "Feature", "id": 22137720, "geometry": {"type": "Point", "coordinates": [2.98776, 50.432419]}, "properties": {"woe:id": 22137720, "woe:parent_id": 589115, "woe:name": "Gare de Dourges", "woe:placetype": 20, "woe:placetype_name": "POI", "woe:lang": "FRE", "iso:country": "FR", "meta:provider": ["geoplanet:7.3.1", "geoplanet:7.3.2", "geoplanet:7.4.0", "geoplanet:7.4.1", "geoplanet:7.5.1", "geoplanet:7.5.2", "geoplanet:7.6.0", "geoplanet:7.8.1", "geoplanet:7.9.0", "geoplanet:7.10.0", "geoplanet:8.0.0", "woeplanet:8.0.0"], "meta:indexed": "2020-08-20T20:54:04.759045", "woe:alias_ENG_V": ["Dourges Railway Station"], "meta:updated": "2020-10-14T11:52:05.506194", "woe:alias_ENG_P": ["Dourges Station"], "woe:alias_FRE_V": ["Gare Dourges"], "woe:hierarchy": {"continent": 24865675, "country": 23424819, "town": 0, "planet": 1, "county": 12597181, "suburb": 0, "state": 7153324, "region": 0, "localadmin": 12660643}, "woe:timezone_id": 28350911, "woe:hash": "u0fnguzw5u73", "woe:centroid": [2.98776, 50.432419], "geom:latitude": 50.432419, "geom:longitude": 2.98776, "geom:hash": "u0fnguzw5u73", "woe:latitude": 50.432419, "geom:centroid": [2.98776, 50.432419], "woe:longitude": 2.98776, "woe:repo": "woeplanet-poi-fr", "geom:area": 0.0, "woe:scale": 19}}