{"type": "Feature", "id": 22139783, "geometry": {"type": "Point", "coordinates": [1.76521, 48.810879]}, "properties": {"woe:id": 22139783, "woe:parent_id": 592396, "woe:name": "SNCF-Garanci\u00e8re-la Queue", "woe:placetype": 20, "woe:placetype_name": "POI", "woe:lang": "FRE", "iso:country": "FR", "meta:provider": ["geoplanet:7.3.1", "geoplanet:7.3.2", "geoplanet:7.4.0", "geoplanet:7.4.1", "geoplanet:7.5.1", "geoplanet:7.5.2", "geoplanet:7.6.0", "geoplanet:7.8.1", "geoplanet:7.9.0", "geoplanet:7.10.0", "geoplanet:8.0.0", "woeplanet:8.0.0"], "meta:indexed": "2020-08-20T20:54:04.849941", "woe:alias_ENG_V": ["Garanciere-La Queue Railway Station"], "woe:alias_ENG_P": ["Garanciere-La Queue Station"], "meta:updated": "2020-10-14T11:52:04.996587", "woe:alias_FRE_S": ["Gare Garanciere-la Queue", "SNCF-Garanciere-la Queue", "Gare du Garanciere-la Queue"], "woe:alias_FRE_V": ["Gare du Garanci\u00e8re-la Queue", "Gare Garanci\u00e8re-la Queue"], "woe:hierarchy": {"continent": 24865675, "country": 23424819, "town": 0, "planet": 1, "county": 12597126, "suburb": 0, "state": 7153319, "region": 0, "localadmin": 12638198}, "woe:timezone_id": 28350911, "woe:hash": "u09m8jtrur7f", "woe:centroid": [1.76521, 48.810879], "geom:latitude": 48.810879, "geom:longitude": 1.76521, "geom:hash": "u09m8jtrur7f", "woe:latitude": 48.810879, "geom:centroid": [1.76521, 48.810879], "woe:longitude": 1.76521, "woe:repo": "woeplanet-poi-fr", "geom:area": 0.0, "woe:scale": 19}}