{"type": "Feature", "id": 55863082, "properties": {"woe:id": 55863082, "woe:parent_id": 581364, "woe:name": "Gare de Boussay", "woe:placetype": 20, "woe:placetype_name": "POI", "woe:lang": "FRE", "iso:country": "FR", "meta:provider": ["geoplanet:7.3.1", "geoplanet:7.3.2", "geoplanet:7.4.0", "geoplanet:7.4.1", "geoplanet:7.5.1", "geoplanet:7.5.2", "geoplanet:7.6.0", "geoplanet:7.8.1", "geoplanet:7.9.0", "geoplanet:7.10.0", "geoplanet:8.0.0", "woeplanet:8.0.0"], "meta:indexed": "2020-08-20T20:54:07.303612", "woe:alias_ENG_V": ["Boussay Railway Station"], "meta:updated": "2020-08-22T01:53:29.983742", "woe:alias_ENG_P": ["Boussay Station"], "woe:alias_FRE_V": ["Gare Boussay"], "woe:hierarchy": {"continent": 24865675, "country": 23424819, "town": 0, "planet": 1, "county": 12597177, "suburb": 0, "state": 7153325, "region": 0, "localadmin": 12657625}, "woe:timezone_id": 28350911, "woe:hash": "gbr5tj4x8fmz", "woe:centroid": [-1.18305, 47.050251], "geom:latitude": 47.050251, "geom:longitude": -1.18305, "geom:hash": "gbr5tj4x8fmz", "woe:latitude": 47.050251, "geom:centroid": [-1.18305, 47.050251], "woe:longitude": -1.18305, "woe:repo": "woeplanet-poi-fr"}, "geometry": {"coordinates": [-1.18305, 47.050251], "type": "Point"}}