{"type": "Feature", "id": 22919286, "properties": {"woe:id": 22919286, "woe:parent_id": 622285, "woe:name": "Hippodrome d'Enghien", "woe:placetype": 20, "woe:placetype_name": "POI", "woe:lang": "FRE", "iso:country": "FR", "meta:provider": ["geoplanet:7.3.1", "geoplanet:7.3.2", "geoplanet:7.4.0", "geoplanet:7.4.1", "geoplanet:7.5.1", "geoplanet:7.5.2", "geoplanet:7.6.0", "geoplanet:7.8.1", "geoplanet:7.9.0", "geoplanet:7.10.0", "geoplanet:8.0.0", "woeplanet:8.0.0"], "meta:indexed": "2020-08-20T20:54:07.043528", "meta:updated": "2020-08-22T01:53:29.905527", "woe:hierarchy": {"continent": 24865675, "country": 23424819, "town": 0, "planet": 1, "county": 12597124, "suburb": 0, "state": 7153319, "region": 0, "localadmin": 12651998}, "woe:timezone_id": 28350911, "woe:hash": "u09wshscpew9", "woe:centroid": [2.29201, 48.979988], "geom:latitude": 48.979988, "geom:longitude": 2.29201, "geom:hash": "u09wshscpew9", "woe:latitude": 48.979988, "geom:centroid": [2.29201, 48.979988], "woe:longitude": 2.29201, "woe:repo": "woeplanet-poi-fr"}, "geometry": {"coordinates": [2.29201, 48.979988], "type": "Point"}}