{"type": "Feature", "id": 56060053, "geometry": {"type": "Point", "coordinates": [5.41171, 43.340801]}, "properties": {"woe:id": 56060053, "woe:parent_id": 610264, "woe:name": "I.u.t. Saint-J\u00e9r\u00f4me", "woe:placetype": 20, "woe:placetype_name": "POI", "woe:lang": "FRE", "iso:country": "FR", "meta:provider": ["geoplanet:7.3.1", "geoplanet:7.3.2", "geoplanet:7.4.0", "geoplanet:7.4.1", "geoplanet:7.5.1", "geoplanet:7.5.2", "geoplanet:7.6.0", "geoplanet:7.8.1", "geoplanet:7.9.0", "geoplanet:7.10.0", "geoplanet:8.0.0", "woeplanet:8.0.0"], "meta:indexed": "2020-08-20T20:54:07.673692", "meta:updated": "2020-10-14T11:52:11.034574", "woe:alias_FRE_V": ["I.u.t. Saint-Jerome"], "woe:hierarchy": {"continent": 24865675, "country": 23424819, "town": 0, "planet": 1, "county": 12597199, "suburb": 0, "state": 7153328, "region": 0, "localadmin": 24865753}, "woe:timezone_id": 28350911, "woe:hash": "speye1uwmyzk", "woe:centroid": [5.41171, 43.340801], "geom:latitude": 43.340801, "geom:longitude": 5.41171, "geom:hash": "speye1uwmyzk", "woe:latitude": 43.340801, "geom:centroid": [5.41171, 43.340801], "woe:longitude": 5.41171, "woe:repo": "woeplanet-poi-fr", "geom:area": 0.0, "woe:scale": 19}}