{"type": "Feature", "id": 22906265, "geometry": {"type": "Point", "coordinates": [2.33592, 48.86956]}, "properties": {"woe:id": 22906265, "woe:parent_id": 12654825, "woe:name": "M\u00e9tro-Quatre Septembre", "woe:placetype": 20, "woe:placetype_name": "POI", "woe:lang": "FRE", "iso:country": "FR", "meta:provider": ["geoplanet:7.3.1", "geoplanet:7.3.2", "geoplanet:7.4.0", "geoplanet:7.4.1", "geoplanet:7.5.1", "geoplanet:7.5.2", "geoplanet:7.6.0", "geoplanet:7.8.1", "geoplanet:7.9.0", "geoplanet:7.10.0", "geoplanet:8.0.0", "woeplanet:8.0.0"], "meta:indexed": "2020-08-20T20:54:06.475794", "meta:updated": "2020-10-14T11:52:06.076839", "woe:alias_ENG_P": ["Quatre Septembre Metro Station"], "woe:alias_FRE_S": ["Metro-Quatre Septembre"], "woe:hierarchy": {"continent": 24865675, "country": 23424819, "town": 0, "planet": 1, "county": 12597155, "suburb": 0, "state": 7153319, "region": 0, "localadmin": 12654825}, "woe:timezone_id": 28350911, "woe:hash": "u09wj0kvyfk0", "woe:centroid": [2.33592, 48.86956], "geom:latitude": 48.86956, "geom:longitude": 2.33592, "geom:hash": "u09wj0kvyfk0", "woe:latitude": 48.86956, "geom:centroid": [2.33592, 48.86956], "woe:longitude": 2.33592, "woe:repo": "woeplanet-poi-fr", "geom:area": 0.0, "woe:scale": 19}}