{"type": "Feature", "id": 22900546, "properties": {"woe:id": 22900546, "woe:parent_id": 598125, "woe:name": "Gare de la F\u00e8re", "woe:placetype": 20, "woe:placetype_name": "POI", "woe:lang": "FRE", "iso:country": "FR", "meta:provider": ["geoplanet:7.3.1", "geoplanet:7.3.2", "geoplanet:7.4.0", "geoplanet:7.4.1", "geoplanet:7.5.1", "geoplanet:7.5.2", "geoplanet:7.6.0", "geoplanet:7.8.1", "geoplanet:7.9.0", "geoplanet:7.10.0", "geoplanet:8.0.0", "woeplanet:8.0.0"], "meta:indexed": "2020-08-20T20:54:06.270173", "woe:alias_ENG_V": ["La Fere Railway Station"], "woe:alias_ENG_P": ["La Fere Station"], "meta:updated": "2020-08-22T01:53:29.614440", "woe:alias_FRE_S": ["Gare de la Fere", "Gare la Fere"], "woe:alias_FRE_V": ["Gare la F\u00e9re", "Gare de la F\u00e9re", "Gare la F\u00e8re"], "woe:hierarchy": {"continent": 24865675, "country": 23424819, "town": 0, "planet": 1, "county": 12597170, "suburb": 0, "state": 7153326, "region": 0, "localadmin": 22756703}, "woe:timezone_id": 28350911, "woe:hash": "u0f6s8n0hr11", "woe:centroid": [3.37024, 49.658241], "geom:latitude": 49.658241, "geom:longitude": 3.37024, "geom:hash": "u0f6s8n0hr11", "woe:latitude": 49.658241, "geom:centroid": [3.37024, 49.658241], "woe:longitude": 3.37024, "woe:repo": "woeplanet-poi-fr"}, "geometry": {"coordinates": [3.37024, 49.658241], "type": "Point"}}