{"type": "Feature", "id": 22906374, "properties": {"woe:id": 22906374, "woe:parent_id": 12654826, "woe:name": "M\u00e9tro-Rambuteau", "woe:placetype": 20, "woe:placetype_name": "POI", "woe:lang": "FRE", "iso:country": "FR", "meta:provider": ["geoplanet:7.3.1", "geoplanet:7.3.2", "geoplanet:7.4.0", "geoplanet:7.4.1", "geoplanet:7.5.1", "geoplanet:7.5.2", "geoplanet:7.6.0", "geoplanet:7.8.1", "geoplanet:7.9.0", "geoplanet:7.10.0", "geoplanet:8.0.0", "woeplanet:8.0.0"], "meta:indexed": "2020-08-20T20:54:06.482580", "meta:updated": "2020-08-22T01:53:29.690622", "woe:alias_ENG_P": ["Rambuteau Metro Station"], "woe:alias_FRE_S": ["Metro-Rambuteau"], "woe:hierarchy": {"continent": 24865675, "country": 23424819, "town": 0, "planet": 1, "county": 12597155, "suburb": 0, "state": 7153319, "region": 0, "localadmin": 12654826}, "woe:timezone_id": 28350911, "woe:hash": "u09tvwcy3hz5", "woe:centroid": [2.35353, 48.86142], "geom:latitude": 48.86142, "geom:longitude": 2.35353, "geom:hash": "u09tvwcy3hz5", "woe:latitude": 48.86142, "geom:centroid": [2.35353, 48.86142], "woe:longitude": 2.35353, "woe:repo": "woeplanet-poi-fr"}, "geometry": {"coordinates": [2.35353, 48.86142], "type": "Point"}}