{"type": "Feature", "id": 22144353, "properties": {"woe:id": 22144353, "woe:parent_id": 12646533, "woe:name": "M\u00e9tro-Blanche", "woe:placetype": 20, "woe:placetype_name": "POI", "woe:lang": "FRE", "iso:country": "FR", "meta:provider": ["geoplanet:7.3.1", "geoplanet:7.3.2", "geoplanet:7.4.0", "geoplanet:7.4.1", "geoplanet:7.5.1", "geoplanet:7.5.2", "geoplanet:7.6.0", "geoplanet:7.8.1", "geoplanet:7.9.0", "geoplanet:7.10.0", "geoplanet:8.0.0", "woeplanet:8.0.0"], "meta:indexed": "2020-08-20T20:54:05.051746", "meta:updated": "2020-08-22T01:53:29.131062", "woe:alias_ENG_P": ["Blanche Metro Station"], "woe:alias_FRE_S": ["Metro-Blanche"], "woe:hierarchy": {"continent": 24865675, "country": 23424819, "town": 0, "planet": 1, "county": 12597155, "suburb": 0, "state": 7153319, "region": 0, "localadmin": 12646533}, "woe:timezone_id": 28350911, "woe:hash": "u09wj548u2fp", "woe:centroid": [2.33272, 48.883801], "geom:latitude": 48.883801, "geom:longitude": 2.33272, "geom:hash": "u09wj548u2fp", "woe:latitude": 48.883801, "geom:centroid": [2.33272, 48.883801], "woe:longitude": 2.33272, "woe:repo": "woeplanet-poi-fr"}, "geometry": {"coordinates": [2.33272, 48.883801], "type": "Point"}}