{"type": "Feature", "id": 56060557, "properties": {"woe:id": 56060557, "woe:parent_id": 601787, "woe:name": "Cnam", "woe:placetype": 20, "woe:placetype_name": "POI", "woe:lang": "FRE", "iso:country": "FR", "meta:provider": ["geoplanet:7.3.1", "geoplanet:7.3.2", "geoplanet:7.4.0", "geoplanet:7.4.1", "geoplanet:7.5.1", "geoplanet:7.5.2", "geoplanet:7.6.0", "geoplanet:7.8.1", "geoplanet:7.9.0", "geoplanet:7.10.0", "geoplanet:8.0.0", "woeplanet:8.0.0"], "meta:indexed": "2020-08-20T20:54:08.122692", "meta:updated": "2020-08-22T01:53:30.278706", "woe:hierarchy": {"continent": 24865675, "country": 23424819, "town": 0, "planet": 1, "county": 12597166, "suburb": 0, "state": 7153325, "region": 0, "localadmin": 12664611}, "woe:timezone_id": 28350911, "woe:hash": "gbx3qnwecns9", "woe:centroid": [-0.78204, 48.068611], "geom:latitude": 48.068611, "geom:longitude": -0.78204, "geom:hash": "gbx3qnwecns9", "woe:latitude": 48.068611, "geom:centroid": [-0.78204, 48.068611], "woe:longitude": -0.78204, "woe:repo": "woeplanet-poi-fr"}, "geometry": {"coordinates": [-0.78204, 48.068611], "type": "Point"}}