{"type": "Feature", "id": 55863254, "geometry": {"type": "Point", "coordinates": [2.35841, 48.879768]}, "properties": {"woe:id": 55863254, "woe:parent_id": 12638578, "woe:name": "RER-Magenta", "woe:placetype": 20, "woe:placetype_name": "POI", "woe:lang": "FRE", "iso:country": "FR", "meta:provider": ["geoplanet:7.3.1", "geoplanet:7.3.2", "geoplanet:7.4.0", "geoplanet:7.4.1", "geoplanet:7.5.1", "geoplanet:7.5.2", "geoplanet:7.6.0", "geoplanet:7.8.1", "geoplanet:7.9.0", "geoplanet:7.10.0", "geoplanet:8.0.0", "woeplanet:8.0.0"], "meta:indexed": "2020-08-20T20:54:07.453000", "woe:alias_ENG_V": ["Magenta Railway Station"], "meta:updated": "2020-10-14T11:52:04.845729", "woe:alias_ENG_P": ["Magenta Station"], "woe:alias_FRE_V": ["Gare de Magenta", "Gare Magenta"], "woe:hierarchy": {"continent": 24865675, "country": 23424819, "town": 0, "planet": 1, "county": 12597155, "suburb": 0, "state": 7153319, "region": 0, "localadmin": 12638578}, "woe:timezone_id": 28350911, "woe:hash": "u09wjdm36cjv", "woe:centroid": [2.35841, 48.879768], "geom:latitude": 48.879768, "geom:longitude": 2.35841, "geom:hash": "u09wjdm36cjv", "woe:latitude": 48.879768, "geom:centroid": [2.35841, 48.879768], "woe:longitude": 2.35841, "woe:repo": "woeplanet-poi-fr", "geom:area": 0.0, "woe:scale": 19}}