{"type": "Feature", "id": 55863186, "properties": {"woe:id": 55863186, "woe:parent_id": 609500, "woe:name": "Gare de Malesherbes", "woe:placetype": 20, "woe:placetype_name": "POI", "woe:lang": "FRE", "iso:country": "FR", "meta:provider": ["geoplanet:7.3.1", "geoplanet:7.3.2", "geoplanet:7.4.0", "geoplanet:7.4.1", "geoplanet:7.5.1", "geoplanet:7.5.2", "geoplanet:7.6.0", "geoplanet:7.8.1", "geoplanet:7.9.0", "geoplanet:7.10.0", "geoplanet:8.0.0", "woeplanet:8.0.0"], "meta:indexed": "2020-08-20T20:54:07.396434", "woe:alias_ENG_V": ["Malesherbes Railway Station"], "meta:updated": "2020-08-22T01:53:30.014788", "woe:alias_ENG_P": ["Malesherbes Station"], "woe:alias_FRE_V": ["Gare Malesherbes"], "woe:hierarchy": {"continent": 24865675, "country": 23424819, "town": 0, "planet": 1, "county": 12597141, "suburb": 0, "state": 7153314, "region": 0, "localadmin": 12648655}, "woe:timezone_id": 28350911, "woe:hash": "u09dwxseny2e", "woe:centroid": [2.40149, 48.293701], "geom:latitude": 48.293701, "geom:longitude": 2.40149, "geom:hash": "u09dwxseny2e", "woe:latitude": 48.293701, "geom:centroid": [2.40149, 48.293701], "woe:longitude": 2.40149, "woe:repo": "woeplanet-poi-fr"}, "geometry": {"coordinates": [2.40149, 48.293701], "type": "Point"}}