{"type": "Feature", "id": 56060587, "properties": {"woe:id": 56060587, "woe:parent_id": 589571, "woe:name": "I.u.t. de Rouen", "woe:placetype": 20, "woe:placetype_name": "POI", "woe:lang": "FRE", "iso:country": "FR", "meta:provider": ["geoplanet:7.3.1", "geoplanet:7.3.2", "geoplanet:7.4.0", "geoplanet:7.4.1", "geoplanet:7.5.1", "geoplanet:7.5.2", "geoplanet:7.6.0", "geoplanet:7.8.1", "geoplanet:7.9.0", "geoplanet:7.10.0", "geoplanet:8.0.0", "woeplanet:8.0.0"], "meta:indexed": "2020-08-20T20:54:08.151768", "meta:updated": "2020-08-22T01:53:30.288160", "woe:hierarchy": {"continent": 24865675, "country": 23424819, "town": 0, "planet": 1, "county": 12597115, "suburb": 0, "state": 7153318, "region": 0, "localadmin": 12643278}, "woe:timezone_id": 28350911, "woe:hash": "u0b8quh0u0yc", "woe:centroid": [1.00543, 49.284801], "geom:latitude": 49.284801, "geom:longitude": 1.00543, "geom:hash": "u0b8quh0u0yc", "woe:latitude": 49.284801, "geom:centroid": [1.00543, 49.284801], "woe:longitude": 1.00543, "woe:repo": "woeplanet-poi-fr"}, "geometry": {"coordinates": [1.00543, 49.284801], "type": "Point"}}