{"type": "Feature", "id": 22889469, "properties": {"woe:id": 22889469, "woe:parent_id": 632140, "woe:name": "Universit\u00e9 Claude Bernard-Lyon I", "woe:placetype": 20, "woe:placetype_name": "POI", "woe:lang": "FRE", "iso:country": "FR", "meta:provider": ["geoplanet:7.3.1", "geoplanet:7.3.2", "geoplanet:7.4.0", "geoplanet:7.4.1", "geoplanet:7.5.1", "geoplanet:7.5.2", "geoplanet:7.6.0", "geoplanet:7.8.1", "geoplanet:7.9.0", "geoplanet:7.10.0", "geoplanet:8.0.0", "woeplanet:8.0.0"], "meta:indexed": "2020-08-20T20:54:05.924391", "meta:updated": "2020-08-22T01:53:29.477728", "woe:alias_FRE_S": ["Universite Claude Bernard-Lyon I"], "woe:alias_FRE_V": ["Univ. Claude Bernard"], "woe:hierarchy": {"continent": 24865675, "country": 23424819, "town": 0, "planet": 1, "county": 12597185, "suburb": 0, "state": 7153329, "region": 0, "localadmin": 22756638}, "woe:timezone_id": 28350911, "woe:hash": "u05kqvggy9tc", "woe:centroid": [4.87238, 45.779308], "geom:latitude": 45.779308, "geom:longitude": 4.87238, "geom:hash": "u05kqvggy9tc", "woe:latitude": 45.779308, "geom:centroid": [4.87238, 45.779308], "woe:longitude": 4.87238, "woe:repo": "woeplanet-poi-fr"}, "geometry": {"coordinates": [4.87238, 45.779308], "type": "Point"}}