{"type": "Feature", "id": 22146495, "geometry": {"type": "Point", "coordinates": [1.0866, 49.4259]}, "properties": {"woe:id": 22146495, "woe:parent_id": 620108, "woe:name": "M\u00e9tro-Honor\u00e9-de-Balzac", "woe:placetype": 20, "woe:placetype_name": "POI", "woe:lang": "FRE", "iso:country": "FR", "meta:provider": ["geoplanet:7.3.1", "geoplanet:7.3.2", "geoplanet:7.4.0", "geoplanet:7.4.1", "geoplanet:7.5.1", "geoplanet:7.5.2", "geoplanet:7.6.0", "geoplanet:7.8.1", "geoplanet:7.9.0", "geoplanet:7.10.0", "geoplanet:8.0.0", "woeplanet:8.0.0"], "meta:indexed": "2020-08-20T20:54:05.139666", "meta:updated": "2020-10-14T11:52:05.024184", "woe:alias_ENG_P": ["Honore-de-Balzac Metro Station"], "woe:alias_FRE_S": ["Metro-Honore-de-Balzac"], "woe:hierarchy": {"continent": 24865675, "country": 23424819, "town": 0, "planet": 1, "county": 12597115, "suburb": 0, "state": 7153318, "region": 0, "localadmin": 12638064}, "woe:timezone_id": 28350911, "woe:hash": "u0bc0txnxxe9", "woe:centroid": [1.0866, 49.4259], "geom:latitude": 49.4259, "geom:longitude": 1.0866, "geom:hash": "u0bc0txnxxe9", "woe:latitude": 49.4259, "geom:centroid": [1.0866, 49.4259], "woe:longitude": 1.0866, "woe:repo": "woeplanet-poi-fr", "geom:area": 0.0, "woe:scale": 19}}