{"type": "Feature", "id": 22139090, "geometry": {"type": "Point", "coordinates": [6.07388, 49.33028]}, "properties": {"woe:id": 22139090, "woe:parent_id": 594554, "woe:name": "Gare d'Hayange", "woe:placetype": 20, "woe:placetype_name": "POI", "woe:lang": "FRE", "iso:country": "FR", "meta:provider": ["geoplanet:7.3.1", "geoplanet:7.3.2", "geoplanet:7.4.0", "geoplanet:7.4.1", "geoplanet:7.5.1", "geoplanet:7.5.2", "geoplanet:7.6.0", "geoplanet:7.8.1", "geoplanet:7.9.0", "geoplanet:7.10.0", "geoplanet:8.0.0", "woeplanet:8.0.0"], "meta:indexed": "2020-08-20T20:54:04.817185", "woe:alias_ENG_V": ["Hayange Railway Station"], "meta:updated": "2020-10-14T11:52:05.427340", "woe:alias_ENG_P": ["Hayange Station"], "woe:hierarchy": {"continent": 24865675, "country": 23424819, "town": 0, "planet": 1, "county": 12597171, "suburb": 0, "state": 7153322, "region": 0, "localadmin": 12662682}, "woe:timezone_id": 28350911, "woe:hash": "u0u2dhqcewtn", "woe:centroid": [6.07388, 49.33028], "geom:latitude": 49.33028, "geom:longitude": 6.07388, "geom:hash": "u0u2dhqcewtn", "woe:latitude": 49.33028, "geom:centroid": [6.07388, 49.33028], "woe:longitude": 6.07388, "woe:repo": "woeplanet-poi-fr", "geom:area": 0.0, "woe:scale": 19}}