{"type": "Feature", "id": 56059889, "properties": {"woe:id": 56059889, "woe:parent_id": 20179993, "woe:name": "Univ. Sciences Et Techniques", "woe:placetype": 20, "woe:placetype_name": "POI", "woe:lang": "FRE", "iso:country": "FR", "meta:provider": ["geoplanet:7.3.1", "geoplanet:7.3.2", "geoplanet:7.4.0", "geoplanet:7.4.1", "geoplanet:7.5.1", "geoplanet:7.5.2", "geoplanet:7.6.0", "geoplanet:7.8.1", "geoplanet:7.9.0", "geoplanet:7.10.0", "geoplanet:8.0.0", "woeplanet:8.0.0"], "meta:indexed": "2020-08-20T20:54:07.527533", "meta:updated": "2020-08-22T01:53:30.064216", "woe:hierarchy": {"continent": 24865675, "country": 23424819, "town": 0, "planet": 1, "county": 12597177, "suburb": 0, "state": 7153325, "region": 0, "localadmin": 12662073}, "woe:timezone_id": 28350911, "woe:hash": "gbqusxe5eswk", "woe:centroid": [-1.55578, 47.23909], "geom:latitude": 47.23909, "geom:longitude": -1.55578, "geom:hash": "gbqusxe5eswk", "woe:latitude": 47.23909, "geom:centroid": [-1.55578, 47.23909], "woe:longitude": -1.55578, "woe:repo": "woeplanet-poi-fr"}, "geometry": {"coordinates": [-1.55578, 47.23909], "type": "Point"}}