{"type": "Feature", "id": 56060448, "properties": {"woe:id": 56060448, "woe:parent_id": 55863587, "woe:name": "Cfa Sup2000", "woe:placetype": 20, "woe:placetype_name": "POI", "woe:lang": "FRE", "iso:country": "FR", "meta:provider": ["geoplanet:7.3.1", "geoplanet:7.3.2", "geoplanet:7.4.0", "geoplanet:7.4.1", "geoplanet:7.5.1", "geoplanet:7.5.2", "geoplanet:7.6.0", "geoplanet:7.8.1", "geoplanet:7.9.0", "geoplanet:7.10.0", "geoplanet:8.0.0", "woeplanet:8.0.0"], "meta:indexed": "2020-08-20T20:54:08.023199", "meta:updated": "2020-08-22T01:53:30.244063", "woe:hierarchy": {"continent": 24865675, "country": 23424819, "town": 0, "planet": 1, "county": 12597151, "suburb": 0, "state": 7153319, "region": 0, "localadmin": 12652949}, "woe:timezone_id": 28350911, "woe:hash": "u09txpjb8k8q", "woe:centroid": [2.4249, 48.81786], "geom:latitude": 48.81786, "geom:longitude": 2.4249, "geom:hash": "u09txpjb8k8q", "woe:latitude": 48.81786, "geom:centroid": [2.4249, 48.81786], "woe:longitude": 2.4249, "woe:repo": "woeplanet-poi-fr"}, "geometry": {"coordinates": [2.4249, 48.81786], "type": "Point"}}