{"type": "Feature", "id": 22149278, "geometry": {"type": "Point", "coordinates": [3.52466, 50.34848]}, "properties": {"woe:id": 22149278, "woe:parent_id": 629845, "woe:name": "Stade Nungesser", "woe:placetype": 20, "woe:placetype_name": "POI", "woe:lang": "FRE", "iso:country": "FR", "meta:provider": ["geoplanet:7.3.1", "geoplanet:7.3.2", "geoplanet:7.4.0", "geoplanet:7.4.1", "geoplanet:7.5.1", "geoplanet:7.5.2", "geoplanet:7.6.0", "geoplanet:7.8.1", "geoplanet:7.9.0", "geoplanet:7.10.0", "geoplanet:8.0.0", "woeplanet:8.0.0"], "meta:indexed": "2020-08-20T20:54:05.245703", "meta:updated": "2020-10-14T11:52:05.330281", "woe:hierarchy": {"continent": 24865675, "country": 23424819, "town": 0, "planet": 1, "county": 12597175, "suburb": 0, "state": 7153324, "region": 0, "localadmin": 12671988}, "woe:timezone_id": 28350911, "woe:hash": "u0fw2jwt4sbv", "woe:centroid": [3.52466, 50.34848], "geom:latitude": 50.34848, "geom:longitude": 3.52466, "geom:hash": "u0fw2jwt4sbv", "woe:latitude": 50.34848, "geom:centroid": [3.52466, 50.34848], "woe:longitude": 3.52466, "woe:repo": "woeplanet-poi-fr", "geom:area": 0.0, "woe:scale": 19}}