{"type": "Feature", "id": 56060422, "properties": {"woe:id": 56060422, "woe:parent_id": 55843841, "woe:name": "\u00c9cole Nationale de Commerce", "woe:placetype": 20, "woe:placetype_name": "POI", "woe:lang": "FRE", "iso:country": "FR", "meta:provider": ["geoplanet:7.3.1", "geoplanet:7.3.2", "geoplanet:7.4.0", "geoplanet:7.4.1", "geoplanet:7.5.1", "geoplanet:7.5.2", "geoplanet:7.6.0", "geoplanet:7.8.1", "geoplanet:7.9.0", "geoplanet:7.10.0", "geoplanet:8.0.0", "woeplanet:8.0.0"], "meta:indexed": "2020-08-20T20:54:07.999911", "meta:updated": "2020-08-22T01:53:30.235902", "woe:alias_FRE_V": ["Ecole Nationale de Commerce"], "woe:hierarchy": {"continent": 24865675, "country": 23424819, "town": 0, "planet": 1, "county": 12597155, "suburb": 0, "state": 7153319, "region": 0, "localadmin": 12638223}, "woe:timezone_id": 28350911, "woe:hash": "u09whv3vgvpg", "woe:centroid": [2.32069, 48.897041], "geom:latitude": 48.897041, "geom:longitude": 2.32069, "geom:hash": "u09whv3vgvpg", "woe:latitude": 48.897041, "geom:centroid": [2.32069, 48.897041], "woe:longitude": 2.32069, "woe:repo": "woeplanet-poi-fr"}, "geometry": {"coordinates": [2.32069, 48.897041], "type": "Point"}}