{"type": "Feature", "id": 22872575, "geometry": {"type": "Point", "coordinates": [1.51302, 43.547581]}, "properties": {"woe:id": 22872575, "woe:parent_id": 600591, "woe:name": "Gare de Lab\u00e8ge-Innopole", "woe:placetype": 20, "woe:placetype_name": "POI", "woe:lang": "FRE", "iso:country": "FR", "meta:provider": ["geoplanet:7.3.1", "geoplanet:7.3.2", "geoplanet:7.4.0", "geoplanet:7.4.1", "geoplanet:7.5.1", "geoplanet:7.5.2", "geoplanet:7.6.0", "geoplanet:7.8.1", "geoplanet:7.9.0", "geoplanet:7.10.0", "geoplanet:8.0.0", "woeplanet:8.0.0"], "meta:indexed": "2020-08-20T20:54:05.521110", "woe:alias_ENG_V": ["Labege-Innopole Railway Station"], "woe:alias_ENG_P": ["Labege-Innopole Station"], "meta:updated": "2020-10-14T11:52:11.827484", "woe:alias_FRE_S": ["Gare de Labege-Innopole", "Gare Labege-Innopole"], "woe:alias_FRE_V": ["Gare Lab\u00e8ge-Innopole"], "woe:hierarchy": {"continent": 24865675, "country": 23424819, "town": 0, "planet": 1, "county": 12597186, "suburb": 0, "state": 7153323, "region": 0, "localadmin": 12664166}, "woe:timezone_id": 28350911, "woe:hash": "sp9pdrtepcmr", "woe:centroid": [1.51302, 43.547581], "geom:latitude": 43.547581, "geom:longitude": 1.51302, "geom:hash": "sp9pdrtepcmr", "woe:latitude": 43.547581, "geom:centroid": [1.51302, 43.547581], "woe:longitude": 1.51302, "woe:repo": "woeplanet-poi-fr", "geom:area": 0.0, "woe:scale": 19}}