{"type": "Feature", "id": 22143892, "geometry": {"type": "Point", "coordinates": [2.45767, 48.896221]}, "properties": {"woe:id": 22143892, "woe:parent_id": 55863549, "woe:name": "RER-Noisy-le-Sec", "woe:placetype": 20, "woe:placetype_name": "POI", "woe:lang": "FRE", "iso:country": "FR", "meta:provider": ["geoplanet:7.3.1", "geoplanet:7.3.2", "geoplanet:7.4.0", "geoplanet:7.4.1", "geoplanet:7.5.1", "geoplanet:7.5.2", "geoplanet:7.6.0", "geoplanet:7.8.1", "geoplanet:7.9.0", "geoplanet:7.10.0", "geoplanet:8.0.0", "woeplanet:8.0.0"], "meta:indexed": "2020-08-20T20:54:05.035879", "woe:alias_ENG_V": ["Noisy-le-Sec Railway Station"], "meta:updated": "2020-10-14T11:52:05.135958", "woe:alias_ENG_P": ["Noisy-le-Sec Station"], "woe:alias_FRE_V": ["Gare de Noisy-le-Sec", "Gare Noisy-le-Sec"], "woe:hierarchy": {"continent": 24865675, "country": 23424819, "town": 0, "planet": 1, "county": 12597156, "suburb": 0, "state": 7153319, "region": 0, "localadmin": 12650030}, "woe:timezone_id": 28350911, "woe:hash": "u09wpvm95u5x", "woe:centroid": [2.45767, 48.896221], "geom:latitude": 48.896221, "geom:longitude": 2.45767, "geom:hash": "u09wpvm95u5x", "woe:latitude": 48.896221, "geom:centroid": [2.45767, 48.896221], "woe:longitude": 2.45767, "woe:repo": "woeplanet-poi-fr", "geom:area": 0.0, "woe:scale": 19}}