{"type": "Feature", "id": 22148141, "properties": {"woe:id": 22148141, "woe:parent_id": 55863575, "woe:name": "SNCF-S\u00e8vres-Rive Gauche", "woe:placetype": 20, "woe:placetype_name": "POI", "woe:lang": "FRE", "iso:country": "FR", "meta:provider": ["geoplanet:7.3.1", "geoplanet:7.3.2", "geoplanet:7.4.0", "geoplanet:7.4.1", "geoplanet:7.5.1", "geoplanet:7.5.2", "geoplanet:7.6.0", "geoplanet:7.8.1", "geoplanet:7.9.0", "geoplanet:7.10.0", "geoplanet:8.0.0", "woeplanet:8.0.0"], "meta:indexed": "2020-08-20T20:54:05.195525", "woe:alias_ENG_V": ["Sevres-Rive Gauche Railway Station"], "woe:alias_ENG_P": ["Sevres-Rive Gauche Station"], "meta:updated": "2020-08-22T01:53:29.190739", "woe:alias_FRE_S": ["Gare Sevres-Rive Gauche", "SNCF-Sevres-Rive Gauche", "Gare du Sevres-Rive Gauche"], "woe:alias_FRE_V": ["Gare du S\u00e8vres-Rive Gauche", "Gare S\u00e8vres-Rive Gauche"], "woe:hierarchy": {"continent": 24865675, "country": 23424819, "town": 0, "planet": 1, "county": 15022631, "suburb": 0, "state": 7153319, "region": 0, "localadmin": 12638579}, "woe:timezone_id": 28350911, "woe:hash": "u09tdrsvjqr5", "woe:centroid": [2.21501, 48.821388], "geom:latitude": 48.821388, "geom:longitude": 2.21501, "geom:hash": "u09tdrsvjqr5", "woe:latitude": 48.821388, "geom:centroid": [2.21501, 48.821388], "woe:longitude": 2.21501, "woe:repo": "woeplanet-poi-fr"}, "geometry": {"coordinates": [2.21501, 48.821388], "type": "Point"}}