{"type": "Feature", "id": 22910774, "properties": {"woe:id": 22910774, "woe:parent_id": 594699, "woe:name": "SNCF-H\u00e9ricy", "woe:placetype": 20, "woe:placetype_name": "POI", "woe:lang": "FRE", "iso:country": "FR", "meta:provider": ["geoplanet:7.3.1", "geoplanet:7.3.2", "geoplanet:7.4.0", "geoplanet:7.4.1", "geoplanet:7.5.1", "geoplanet:7.5.2", "geoplanet:7.6.0", "geoplanet:7.8.1", "geoplanet:7.9.0", "geoplanet:7.10.0", "geoplanet:8.0.0", "woeplanet:8.0.0"], "meta:indexed": "2020-08-20T20:54:06.785030", "woe:alias_ENG_V": ["Hericy Railway Station"], "woe:alias_ENG_P": ["Hericy Station"], "meta:updated": "2020-08-22T01:53:29.799908", "woe:alias_FRE_S": ["Gare Hericy", "SNCF-Hericy", "Gare du Hericy"], "woe:alias_FRE_V": ["Gare du H\u00e9ricy", "Gare H\u00e9ricy"], "woe:hierarchy": {"continent": 24865675, "country": 23424819, "town": 0, "planet": 1, "county": 12597137, "suburb": 0, "state": 7153319, "region": 0, "localadmin": 12643947}, "woe:timezone_id": 28350911, "woe:hash": "u09gwfcbm56y", "woe:centroid": [2.76019, 48.442902], "geom:latitude": 48.442902, "geom:longitude": 2.76019, "geom:hash": "u09gwfcbm56y", "woe:latitude": 48.442902, "geom:centroid": [2.76019, 48.442902], "woe:longitude": 2.76019, "woe:repo": "woeplanet-poi-fr"}, "geometry": {"coordinates": [2.76019, 48.442902], "type": "Point"}}