{"type": "Feature", "id": 22913946, "geometry": {"type": "Point", "coordinates": [2.30648, 48.635441]}, "properties": {"woe:id": 22913946, "woe:parent_id": 626021, "woe:name": "RER-Saint-Michel-sur-Orge", "woe:placetype": 20, "woe:placetype_name": "POI", "woe:lang": "FRE", "iso:country": "FR", "meta:provider": ["geoplanet:7.3.1", "geoplanet:7.3.2", "geoplanet:7.4.0", "geoplanet:7.4.1", "geoplanet:7.5.1", "geoplanet:7.5.2", "geoplanet:7.6.0", "geoplanet:7.8.1", "geoplanet:7.9.0", "geoplanet:7.10.0", "geoplanet:8.0.0", "woeplanet:8.0.0"], "meta:indexed": "2020-08-20T20:54:06.891632", "woe:alias_ENG_V": ["Saint-Michel-sur-Orge Railway Station"], "meta:updated": "2020-10-14T11:52:06.205063", "woe:alias_ENG_P": ["Saint-Michel-sur-Orge Station"], "woe:alias_FRE_V": ["Gare de Saint-Michel-sur-Orge", "Gare Saint-Michel-sur-Orge"], "woe:hierarchy": {"continent": 24865675, "country": 23424819, "town": 0, "planet": 1, "county": 12597118, "suburb": 0, "state": 7153319, "region": 0, "localadmin": 12645773}, "woe:timezone_id": 28350911, "woe:hash": "u09ssmz9bzk4", "woe:centroid": [2.30648, 48.635441], "geom:latitude": 48.635441, "geom:longitude": 2.30648, "geom:hash": "u09ssmz9bzk4", "woe:latitude": 48.635441, "geom:centroid": [2.30648, 48.635441], "woe:longitude": 2.30648, "woe:repo": "woeplanet-poi-fr", "geom:area": 0.0, "woe:scale": 19}}