{"type": "Feature", "id": 22138997, "properties": {"woe:id": 22138997, "woe:parent_id": 594174, "woe:name": "Gare de Arr\u00eat de Habsheim", "woe:placetype": 20, "woe:placetype_name": "POI", "woe:lang": "FRE", "iso:country": "FR", "meta:provider": ["geoplanet:7.3.1", "geoplanet:7.3.2", "geoplanet:7.4.0", "geoplanet:7.4.1", "geoplanet:7.5.1", "geoplanet:7.5.2", "geoplanet:7.6.0", "geoplanet:7.8.1", "geoplanet:7.9.0", "geoplanet:7.10.0", "geoplanet:8.0.0", "woeplanet:8.0.0"], "meta:indexed": "2020-08-20T20:54:04.810926", "woe:alias_ENG_V": ["Arret de Habsheim Railway Station"], "woe:alias_ENG_P": ["Arret de Habsheim Station"], "meta:updated": "2020-08-22T01:53:29.039037", "woe:alias_FRE_S": ["Gare de Arret de Habsheim", "Gare Arret de Habsheim"], "woe:alias_FRE_V": ["Gare Arr\u00eat de Habsheim"], "woe:hierarchy": {"continent": 24865675, "country": 23424819, "town": 0, "planet": 1, "county": 12597152, "suburb": 0, "state": 7153330, "region": 0, "localadmin": 12644991}, "woe:timezone_id": 28350911, "woe:hash": "u0mr8f3c2qgr", "woe:centroid": [7.41819, 47.737221], "geom:latitude": 47.737221, "geom:longitude": 7.41819, "geom:hash": "u0mr8f3c2qgr", "woe:latitude": 47.737221, "geom:centroid": [7.41819, 47.737221], "woe:longitude": 7.41819, "woe:repo": "woeplanet-poi-fr"}, "geometry": {"coordinates": [7.41819, 47.737221], "type": "Point"}}