{"type": "Feature", "id": 22888905, "properties": {"woe:id": 22888905, "woe:parent_id": 24865735, "woe:name": "M\u00e9tro-H\u00e9non", "woe:placetype": 20, "woe:placetype_name": "POI", "woe:lang": "FRE", "iso:country": "FR", "meta:provider": ["geoplanet:7.3.1", "geoplanet:7.3.2", "geoplanet:7.4.0", "geoplanet:7.4.1", "geoplanet:7.5.1", "geoplanet:7.5.2", "geoplanet:7.6.0", "geoplanet:7.8.1", "geoplanet:7.9.0", "geoplanet:7.10.0", "geoplanet:8.0.0", "woeplanet:8.0.0"], "meta:indexed": "2020-08-20T20:54:05.908672", "meta:updated": "2020-08-22T01:53:29.470637", "woe:alias_ENG_P": ["Henon Metro Station"], "woe:alias_FRE_S": ["Metro-Henon"], "woe:hierarchy": {"continent": 24865675, "country": 23424819, "town": 0, "planet": 1, "county": 12597185, "suburb": 0, "state": 7153329, "region": 0, "localadmin": 24865735}, "woe:timezone_id": 28350911, "woe:hash": "u05kmvgk07tg", "woe:centroid": [4.82748, 45.779362], "geom:latitude": 45.779362, "geom:longitude": 4.82748, "geom:hash": "u05kmvgk07tg", "woe:latitude": 45.779362, "geom:centroid": [4.82748, 45.779362], "woe:longitude": 4.82748, "woe:repo": "woeplanet-poi-fr"}, "geometry": {"coordinates": [4.82748, 45.779362], "type": "Point"}}