{"type": "Feature", "id": 22872047, "geometry": {"type": "Point", "coordinates": [0.48876, 44.85701]}, "properties": {"woe:id": 22872047, "woe:parent_id": 579344, "woe:name": "Gare de Bergerac", "woe:placetype": 20, "woe:placetype_name": "POI", "woe:lang": "FRE", "iso:country": "FR", "meta:provider": ["geoplanet:7.3.1", "geoplanet:7.3.2", "geoplanet:7.4.0", "geoplanet:7.4.1", "geoplanet:7.5.1", "geoplanet:7.5.2", "geoplanet:7.6.0", "geoplanet:7.8.1", "geoplanet:7.9.0", "geoplanet:7.10.0", "geoplanet:8.0.0", "woeplanet:8.0.0"], "meta:indexed": "2020-08-20T20:54:05.503658", "woe:alias_ENG_V": ["Bergerac Railway Station"], "meta:updated": "2020-10-14T11:52:12.020592", "woe:alias_ENG_P": ["Bergerac Station"], "woe:alias_FRE_V": ["Gare Bergerac"], "woe:hierarchy": {"continent": 24865675, "country": 23424819, "town": 0, "planet": 1, "county": 12597122, "suburb": 0, "state": 7153309, "region": 0, "localadmin": 12638659}, "woe:timezone_id": 28350911, "woe:hash": "spbr5jgzhbtz", "woe:centroid": [0.48876, 44.85701], "geom:latitude": 44.85701, "geom:longitude": 0.48876, "geom:hash": "spbr5jgzhbtz", "woe:latitude": 44.85701, "geom:centroid": [0.48876, 44.85701], "woe:longitude": 0.48876, "woe:repo": "woeplanet-poi-fr", "geom:area": 0.0, "woe:scale": 19}}