{"type": "Feature", "id": 22147193, "geometry": {"type": "Point", "coordinates": [2.41793, 49.213779]}, "properties": {"woe:id": 22147193, "woe:parent_id": 625280, "woe:name": "Gare de Saint-Leu d'Esserent", "woe:placetype": 20, "woe:placetype_name": "POI", "woe:lang": "FRE", "iso:country": "FR", "meta:provider": ["geoplanet:7.3.1", "geoplanet:7.3.2", "geoplanet:7.4.0", "geoplanet:7.4.1", "geoplanet:7.5.1", "geoplanet:7.5.2", "geoplanet:7.6.0", "geoplanet:7.8.1", "geoplanet:7.9.0", "geoplanet:7.10.0", "geoplanet:8.0.0", "woeplanet:8.0.0"], "meta:indexed": "2020-08-20T20:54:05.169682", "woe:alias_ENG_V": ["Saint-Leu d'Esserent Railway Station"], "meta:updated": "2020-10-14T11:52:05.150467", "woe:alias_ENG_P": ["Saint-Leu d'Esserent Station"], "woe:alias_FRE_V": ["Gare Saint-Leu d'Esserent"], "woe:hierarchy": {"continent": 24865675, "country": 23424819, "town": 0, "planet": 1, "county": 12597158, "suburb": 0, "state": 7153326, "region": 0, "localadmin": 22757328}, "woe:timezone_id": 28350911, "woe:hash": "u09xzp0ejc76", "woe:centroid": [2.41793, 49.213779], "geom:latitude": 49.213779, "geom:longitude": 2.41793, "geom:hash": "u09xzp0ejc76", "woe:latitude": 49.213779, "geom:centroid": [2.41793, 49.213779], "woe:longitude": 2.41793, "woe:repo": "woeplanet-poi-fr", "geom:area": 0.0, "woe:scale": 19}}