{"type": "Feature", "id": 22887937, "properties": {"woe:id": 22887937, "woe:parent_id": 575892, "woe:name": "Agrivap", "woe:placetype": 20, "woe:placetype_name": "POI", "woe:lang": "FRE", "iso:country": "FR", "meta:provider": ["geoplanet:7.3.1", "geoplanet:7.3.2", "geoplanet:7.4.0", "geoplanet:7.4.1", "geoplanet:7.5.1", "geoplanet:7.5.2", "geoplanet:7.6.0", "geoplanet:7.8.1", "geoplanet:7.9.0", "geoplanet:7.10.0", "geoplanet:8.0.0", "woeplanet:8.0.0"], "meta:indexed": "2020-08-20T20:54:05.879420", "meta:updated": "2020-08-22T01:53:29.459320", "woe:hierarchy": {"continent": 24865675, "country": 23424819, "town": 0, "planet": 1, "county": 12597146, "suburb": 0, "state": 7153310, "region": 0, "localadmin": 12636988}, "woe:timezone_id": 28350911, "woe:hash": "u04ehfyxzpjy", "woe:centroid": [3.7336, 45.543819], "geom:latitude": 45.543819, "geom:longitude": 3.7336, "geom:hash": "u04ehfyxzpjy", "woe:latitude": 45.543819, "geom:centroid": [3.7336, 45.543819], "woe:longitude": 3.7336, "woe:repo": "woeplanet-poi-fr"}, "geometry": {"coordinates": [3.7336, 45.543819], "type": "Point"}}