{"type": "Feature", "id": 22904113, "properties": {"woe:id": 22904113, "woe:parent_id": 617476, "woe:name": "Abbaye Royale du Moncel", "woe:placetype": 20, "woe:placetype_name": "POI", "woe:lang": "FRE", "iso:country": "FR", "meta:provider": ["geoplanet:7.3.1", "geoplanet:7.3.2", "geoplanet:7.4.0", "geoplanet:7.4.1", "geoplanet:7.5.1", "geoplanet:7.5.2", "geoplanet:7.6.0", "geoplanet:7.8.1", "geoplanet:7.9.0", "geoplanet:7.10.0", "geoplanet:8.0.0", "woeplanet:8.0.0"], "meta:indexed": "2020-08-20T20:54:06.389869", "meta:updated": "2020-08-22T01:53:29.659998", "woe:hierarchy": {"continent": 24865675, "country": 23424819, "town": 0, "planet": 1, "county": 12597158, "suburb": 0, "state": 7153326, "region": 0, "localadmin": 22757168}, "woe:timezone_id": 28350911, "woe:hash": "u0cb7rn75svn", "woe:centroid": [2.6125, 49.301689], "geom:latitude": 49.301689, "geom:longitude": 2.6125, "geom:hash": "u0cb7rn75svn", "woe:latitude": 49.301689, "geom:centroid": [2.6125, 49.301689], "woe:longitude": 2.6125, "woe:repo": "woeplanet-poi-fr"}, "geometry": {"coordinates": [2.6125, 49.301689], "type": "Point"}}