{"type": "Feature", "id": 22134743, "properties": {"woe:id": 22134743, "woe:parent_id": 579372, "woe:name": "Gare de Berlaimont", "woe:placetype": 20, "woe:placetype_name": "POI", "woe:lang": "FRE", "iso:country": "FR", "meta:provider": ["geoplanet:7.3.1", "geoplanet:7.3.2", "geoplanet:7.4.0", "geoplanet:7.4.1", "geoplanet:7.5.1", "geoplanet:7.5.2", "geoplanet:7.6.0", "geoplanet:7.8.1", "geoplanet:7.9.0", "geoplanet:7.10.0", "geoplanet:8.0.0", "woeplanet:8.0.0"], "meta:indexed": "2020-08-20T20:54:04.654125", "woe:alias_ENG_V": ["Berlaimont Railway Station"], "meta:updated": "2020-08-22T01:53:28.969247", "woe:alias_ENG_P": ["Berlaimont Station"], "woe:alias_FRE_V": ["Gare Berlaimont"], "woe:hierarchy": {"continent": 24865675, "country": 23424819, "town": 0, "planet": 1, "county": 12597175, "suburb": 0, "state": 7153324, "region": 0, "localadmin": 12656822}, "woe:timezone_id": 28350911, "woe:hash": "u0ftwd7ycpvz", "woe:centroid": [3.80647, 50.199108], "geom:latitude": 50.199108, "geom:longitude": 3.80647, "geom:hash": "u0ftwd7ycpvz", "woe:latitude": 50.199108, "geom:centroid": [3.80647, 50.199108], "woe:longitude": 3.80647, "woe:repo": "woeplanet-poi-fr"}, "geometry": {"coordinates": [3.80647, 50.199108], "type": "Point"}}