{"type": "Feature", "id": 22896288, "properties": {"woe:id": 22896288, "woe:parent_id": 589245, "woe:name": "Gare de Drusenheim", "woe:placetype": 20, "woe:placetype_name": "POI", "woe:lang": "FRE", "iso:country": "FR", "meta:provider": ["geoplanet:7.3.1", "geoplanet:7.3.2", "geoplanet:7.4.0", "geoplanet:7.4.1", "geoplanet:7.5.1", "geoplanet:7.5.2", "geoplanet:7.6.0", "geoplanet:7.8.1", "geoplanet:7.9.0", "geoplanet:7.10.0", "geoplanet:8.0.0", "woeplanet:8.0.0"], "meta:indexed": "2020-08-20T20:54:06.108191", "woe:alias_ENG_V": ["Drusenheim Railway Station"], "meta:updated": "2020-08-22T01:53:29.551373", "woe:alias_ENG_P": ["Drusenheim Station"], "woe:alias_FRE_V": ["Gare Drusenheim"], "woe:hierarchy": {"continent": 24865675, "country": 23424819, "town": 0, "planet": 1, "county": 12597135, "suburb": 0, "state": 7153330, "region": 0, "localadmin": 12643115}, "woe:timezone_id": 28350911, "woe:hash": "u0ttkve6nrf2", "woe:centroid": [7.94785, 48.765949], "geom:latitude": 48.765949, "geom:longitude": 7.94785, "geom:hash": "u0ttkve6nrf2", "woe:latitude": 48.765949, "geom:centroid": [7.94785, 48.765949], "woe:longitude": 7.94785, "woe:repo": "woeplanet-poi-fr"}, "geometry": {"coordinates": [7.94785, 48.765949], "type": "Point"}}