{"type": "Feature", "id": 22877414, "geometry": {"type": "Point", "coordinates": [2.2599, 43.54253]}, "properties": {"woe:id": 22877414, "woe:parent_id": 600656, "woe:name": "Gare de Labrugui\u00e8re", "woe:placetype": 20, "woe:placetype_name": "POI", "woe:lang": "FRE", "iso:country": "FR", "meta:provider": ["geoplanet:7.3.1", "geoplanet:7.3.2", "geoplanet:7.4.0", "geoplanet:7.4.1", "geoplanet:7.5.1", "geoplanet:7.5.2", "geoplanet:7.6.0", "geoplanet:7.8.1", "geoplanet:7.9.0", "geoplanet:7.10.0", "geoplanet:8.0.0", "woeplanet:8.0.0"], "meta:indexed": "2020-08-20T20:54:05.638649", "woe:alias_ENG_V": ["Labruguiere Railway Station"], "woe:alias_ENG_P": ["Labruguiere Station"], "meta:updated": "2020-10-14T11:52:11.999397", "woe:alias_FRE_S": ["Gare de Labruguiere", "Gare Labruguiere"], "woe:alias_FRE_V": ["Gare Labrugui\u00e8re"], "woe:hierarchy": {"continent": 24865675, "country": 23424819, "town": 0, "planet": 1, "county": 12597192, "suburb": 0, "state": 7153323, "region": 0, "localadmin": 12664190}, "woe:timezone_id": 28350911, "woe:hash": "sp9xeqtte7zs", "woe:centroid": [2.2599, 43.54253], "geom:latitude": 43.54253, "geom:longitude": 2.2599, "geom:hash": "sp9xeqtte7zs", "woe:latitude": 43.54253, "geom:centroid": [2.2599, 43.54253], "woe:longitude": 2.2599, "woe:repo": "woeplanet-poi-fr", "geom:area": 0.0, "woe:scale": 19}}