{"type": "Feature", "id": 22137181, "geometry": {"type": "Point", "coordinates": [2.46169, 48.592522]}, "properties": {"woe:id": 22137181, "woe:parent_id": 631381, "woe:name": "SNCF-Villab\u00e9", "woe:placetype": 20, "woe:placetype_name": "POI", "woe:lang": "FRE", "iso:country": "FR", "meta:provider": ["geoplanet:7.3.1", "geoplanet:7.3.2", "geoplanet:7.4.0", "geoplanet:7.4.1", "geoplanet:7.5.1", "geoplanet:7.5.2", "geoplanet:7.6.0", "geoplanet:7.8.1", "geoplanet:7.9.0", "geoplanet:7.10.0", "geoplanet:8.0.0", "woeplanet:8.0.0"], "meta:indexed": "2020-08-20T20:54:04.735373", "woe:alias_ENG_V": ["Villabe Railway Station"], "woe:alias_ENG_P": ["Villabe Station"], "meta:updated": "2020-10-14T11:52:05.184685", "woe:alias_FRE_S": ["Gare Villabe", "SNCF-Villabe", "Gare du Villabe"], "woe:alias_FRE_V": ["Gare du Villab\u00e9", "Gare Villab\u00e9"], "woe:hierarchy": {"continent": 24865675, "country": 23424819, "town": 0, "planet": 1, "county": 12597118, "suburb": 0, "state": 7153319, "region": 0, "localadmin": 12654345}, "woe:timezone_id": 28350911, "woe:hash": "u09u2jbxcw9h", "woe:centroid": [2.46169, 48.592522], "geom:latitude": 48.592522, "geom:longitude": 2.46169, "geom:hash": "u09u2jbxcw9h", "woe:latitude": 48.592522, "geom:centroid": [2.46169, 48.592522], "woe:longitude": 2.46169, "woe:repo": "woeplanet-poi-fr", "geom:area": 0.0, "woe:scale": 19}}