{"type": "Feature", "id": 22906582, "geometry": {"type": "Point", "coordinates": [2.35481, 48.845821]}, "properties": {"woe:id": 22906582, "woe:parent_id": 12652969, "woe:name": "M\u00e9tro-Jussieu", "woe:placetype": 20, "woe:placetype_name": "POI", "woe:lang": "FRE", "iso:country": "FR", "meta:provider": ["geoplanet:7.3.1", "geoplanet:7.3.2", "geoplanet:7.4.0", "geoplanet:7.4.1", "geoplanet:7.5.1", "geoplanet:7.5.2", "geoplanet:7.6.0", "geoplanet:7.8.1", "geoplanet:7.9.0", "geoplanet:7.10.0", "geoplanet:8.0.0", "woeplanet:8.0.0"], "meta:indexed": "2020-08-20T20:54:06.508459", "meta:updated": "2020-10-14T11:52:06.040095", "woe:alias_ENG_P": ["Jussieu Metro Station"], "woe:alias_FRE_S": ["Metro-Jussieu"], "woe:hierarchy": {"continent": 24865675, "country": 23424819, "town": 0, "planet": 1, "county": 12597155, "suburb": 0, "state": 7153319, "region": 0, "localadmin": 12652969}, "woe:timezone_id": 28350911, "woe:hash": "u09tvs4ex0cx", "woe:centroid": [2.35481, 48.845821], "geom:latitude": 48.845821, "geom:longitude": 2.35481, "geom:hash": "u09tvs4ex0cx", "woe:latitude": 48.845821, "geom:centroid": [2.35481, 48.845821], "woe:longitude": 2.35481, "woe:repo": "woeplanet-poi-fr", "geom:area": 0.0, "woe:scale": 19}}