{"type": "Feature", "id": 22883465, "properties": {"woe:id": 22883465, "woe:parent_id": 582924, "woe:name": "Musee de l'Auto et du Bateau", "woe:placetype": 20, "woe:placetype_name": "POI", "woe:lang": "FRE", "iso:country": "FR", "meta:provider": ["geoplanet:7.3.1", "geoplanet:7.3.2", "geoplanet:7.4.0", "geoplanet:7.4.1", "geoplanet:7.5.1", "geoplanet:7.5.2", "geoplanet:7.6.0", "geoplanet:7.8.1", "geoplanet:7.9.0", "geoplanet:7.10.0", "geoplanet:8.0.0", "woeplanet:8.0.0"], "meta:indexed": "2020-08-20T20:54:05.772777", "meta:updated": "2020-08-22T01:53:29.415758", "woe:hierarchy": {"continent": 24865675, "country": 23424819, "town": 0, "planet": 1, "county": 12597201, "suburb": 0, "state": 7153320, "region": 0, "localadmin": 12658304}, "woe:timezone_id": 28350911, "woe:hash": "spd4ufpfykw2", "woe:centroid": [3.03216, 42.682381], "geom:latitude": 42.682381, "geom:longitude": 3.03216, "geom:hash": "spd4ufpfykw2", "woe:latitude": 42.682381, "geom:centroid": [3.03216, 42.682381], "woe:longitude": 3.03216, "woe:repo": "woeplanet-poi-fr"}, "geometry": {"coordinates": [3.03216, 42.682381], "type": "Point"}}