{"type": "Feature", "id": 56060585, "geometry": {"type": "Point", "coordinates": [-1.51788, 47.282928]}, "properties": {"woe:id": 56060585, "woe:parent_id": 624896, "woe:name": "\u00c9cole de Design Nantes Atlantique", "woe:placetype": 20, "woe:placetype_name": "POI", "woe:lang": "FRE", "iso:country": "FR", "meta:provider": ["geoplanet:7.3.1", "geoplanet:7.3.2", "geoplanet:7.4.0", "geoplanet:7.4.1", "geoplanet:7.5.1", "geoplanet:7.5.2", "geoplanet:7.6.0", "geoplanet:7.8.1", "geoplanet:7.9.0", "geoplanet:7.10.0", "geoplanet:8.0.0", "woeplanet:8.0.0"], "meta:indexed": "2020-08-20T20:54:08.150399", "meta:updated": "2020-10-14T11:52:11.277412", "woe:alias_FRE_V": ["Ecole de Design Nantes Atlantique"], "woe:hierarchy": {"continent": 24865675, "country": 23424819, "town": 0, "planet": 1, "county": 12597177, "suburb": 0, "state": 7153325, "region": 0, "localadmin": 12662073}, "woe:timezone_id": 28350911, "woe:hash": "gbquvrwenbde", "woe:centroid": [-1.51788, 47.282928], "geom:latitude": 47.282928, "geom:longitude": -1.51788, "geom:hash": "gbquvrwenbde", "woe:latitude": 47.282928, "geom:centroid": [-1.51788, 47.282928], "woe:longitude": -1.51788, "woe:repo": "woeplanet-poi-fr", "geom:area": 0.0, "woe:scale": 19}}